Workbook

Sheet Resumen
A1: MI CARTERA · DEMO
A2: Datos ficticios de ejemplo · importes en euros
A3: Cartera por posiciones | C3: =Cartera!B17 -> 85387
A4: Último valor del diario | C4: =IFERROR(LOOKUP(2,1/((Diario!B6:B370<>"")*(Diario!A6:A370<=TODAY())),Diario!B6:B370),"") -> 85387
A5: Capital neto desde la base | C5: =IF(C6="","",Evolucion!$C$3+SUMIFS(Movimientos!B6:B505,Movimientos!D6:D505,"<="&C6,Movimientos!D6:D505,">="&DATE(2025,2,1))) -> 63896
A6: Último registro | C6: =IFERROR(LOOKUP(2,1/((Diario!B6:B370<>"")*(Diario!A6:A370<=TODAY())),Diario!A6:A370),"") -> 46275
A7: Ganancia desde la base | C7: =IF(C4="","",C4-C5) -> 21491
A8: Mes abierto (provisional) | C8: =TEXT(TODAY(),"mmmm aaaa") -> septiembre 2026
A9: Último mes en estadísticas | C9: =IFERROR(__xludf.DUMMYFUNCTION("IFERROR(INDEX(FILTER('Estadísticas avanzadas'!A77:A98,ISNUMBER('Estadísticas avanzadas'!B77:B98)),COUNT('Estadísticas avanzadas'!B77:B98)),"""")"),"2026 Ago") -> 2026 Ago
A10: Meses completos | C10: ='Estadísticas avanzadas'!I55 -> 18
A11: Control de datos | C11: =Control!C14 -> OK
A12: =IF(C11="OK","Sin incidencias detectadas.",_xludf.TEXTJOIN(CHAR(10),TRUE,IF(ABS(Control!C12)>1/100,"Diferencia Cartera − Diario: "&TEXT(Control!C12,"0")&" €.",""),IF(Control!C11>0,Control!C11&" movimientos históricos sin fecha utilizable.",""),IF(C11="REVISAR","Hay controles pendientes: abre Revisar controles.",""))) -> Sin incidencias detectadas.
A13: Registra el valor de hoy en Diario
A14: Añade aportaciones o retiradas en Movimientos
A15: Ajusta pesos y próxima aportación en Objetivos
A16: Revisa la calidad de los datos en Control
A17: ESTADÍSTICAS · MESES COMPLETOS
A18: Sortino | C18: ='Estadísticas avanzadas'!E49 -> 4.4453847
A19: Sharpe | C19: ='Estadísticas avanzadas'!A49 -> 2.3028731
A20: Beta vs MSCI World | C20: ='Estadísticas avanzadas'!M49 -> 0.28397956
A21: Tracking error anual | C21: ='Estadísticas avanzadas'!I52 -> 0.12147204
A22: Information ratio | C22: ='Estadísticas avanzadas'!E52 -> 0.81089411
A23: Treynor | C23: ='Estadísticas avanzadas'!A58 -> 0.71742591
A24: Alpha anual | C24: ='Estadísticas avanzadas'!I49 -> 0.17385018
A25: Rentabilidad anualizada | C25: ='Estadísticas avanzadas'!A55 -> 0.25283895
A26: Volatilidad anualizada | C26: ='Estadísticas avanzadas'!E55 -> 0.088469613
A27: Máximo drawdown mensual | C27: ='Estadísticas avanzadas'!A52 -> -0.056746077
A28: Correlación | C28: ='Estadísticas avanzadas'!M52 -> 0.40649275
A29: Objetivo anual de Sortino | C29: ='Estadísticas avanzadas'!C43 -> 0.0275
A30: Meses por debajo del objetivo | C30: =COUNTIF('Estadísticas avanzadas'!J77:J98,"<0") -> 4
A31: Proporción bajo objetivo | C31: =IFERROR(C30/C10,"") -> 0.22222222
A32: Muestra corta: los ratios pueden variar mucho.
A33: AHORRO Y GANANCIA · DESDE FEB 2025

Sheet Cartera
A1: Activo | B1: Importe (€) | C1: Peso %
A2: ETF Global Desarrollado | B2: 20000 | C2: =B2/$B$17 -> 0.23422769
A3: ETF Mercados Emergentes | B3: 7000 | C3: =B3/$B$17 -> 0.081979692
A4: Fondo Asia Pacífico | B4: 2500 | C4: =B4/$B$17 -> 0.029278462
A5: Fondo Value Global | B5: 7500 | C5: =B5/$B$17 -> 0.087835385
A6: Fondo Internacional A | B6: 5000 | C6: =B6/$B$17 -> 0.058556923
A7: Fondo Internacional B | B7: 2000 | C7: =B7/$B$17 -> 0.023422769
A8: Fondo Crédito Flexible | B8: 5000 | C8: =B8/$B$17 -> 0.058556923
A9: Fondo Mixto Defensivo | B9: 8500 | C9: =B9/$B$17 -> 0.099546769
A10: Fondo Retorno Absoluto | B10: 3000 | C10: =B10/$B$17 -> 0.035134154
A11: Cuenta de efectivo | B11: 1387 | C11: =B11/$B$17 -> 0.01624369
A12: Acción tecnológica | B12: 15000 | C12: =B12/$B$17 -> 0.17567077
A13: Acción industrial | B13: 1800 | C13: =B13/$B$17 -> 0.021080492
... A16: Bitcoin | B16: 1000 | C16: =B16/$B$17 -> 0.011711385
A17: TOTAL | B17: =SUM(B2:B16) -> 85387

Sheet Evolucion
A1: 2025
A2: Mes | B2: Valor Total | C2: Capital Inicial | D2: Capital Aportado | E2: Plusvalías | F2: % mes / simple YTD | G2: TWR acumulado | N2: Periodo | O2: Valor Total | P2: Capital invertido estimado | Q2: Plusvalía estimada | T2: Mes | U2: Valor Total | V2: Capital invertido | W2: Plusvalías acumuladas
A3: Feb | B3: 52428 | C3: =51728 -> 51728 | D3: =IF(AND(B3="",COUNTIFS(Movimientos!$D$6:$D$505,">="&DATE(2025,2,1),Movimientos!$D$6:$D$505,"<"&DATE(2025,3,1))=0),"",SUMIFS(Movimientos!$B$6:$B$505,Movimientos!$D$6:$D$505,">="&DATE(2025,2,1),Movimientos!$D$6:$D$505,"<"&DATE(2025,3,1))) -> 700 | N3: ="2025 "&A3 -> 2025 Feb | O3: =B3 -> 52428 | P3: =C3+SUM(D3) -> 52428 | Q3: =O3-P3 -> 0 | T3: =A3 -> Feb | U3: =IF(B3="","",B3) -> 52428 | V3: =IF(B3="","",$C$3+SUM($D$3:D3)) -> 52428 | W3: =IF(U3="","",U3-V3) -> 0
A4: Mar | B4: 55139 | C4: 52428 | D4: =IF(AND(B4="",COUNTIFS(Movimientos!$D$6:$D$505,">="&DATE(2025,3,1),Movimientos!$D$6:$D$505,"<"&DATE(2025,4,1))=0),"",SUMIFS(Movimientos!$B$6:$B$505,Movimientos!$D$6:$D$505,">="&DATE(2025,3,1),Movimientos!$D$6:$D$505,"<"&DATE(2025,4,1))) -> 700 | E4: =B4-C4-D4 -> 2011 | F4: =IF(OR(B4="",C4=0),"",((B4-IF(D4="",0,D4))/C4-1)*100) -> 3.8357366 | G4: =IF(F4="","",F4) -> 3.8357366 | N4: ="2025 "&A4 -> 2025 Mar | O4: =B4 -> 55139 | P4: =C3+SUM(D3:D4) -> 53128 | Q4: =O4-P4 -> 2011 | T4: =A4 -> Mar | U4: =IF(B4="","",B4) -> 55139 | V4: =IF(B4="","",$C$3+SUM($D$3:D4)) -> 53128 | W4: =IF(U4="","",U4-V4) -> 2011
A5: Abr | B5: 57033 | C5: 55139 | D5: =IF(AND(B5="",COUNTIFS(Movimientos!$D$6:$D$505,">="&DATE(2025,4,1),Movimientos!$D$6:$D$505,"<"&DATE(2025,5,1))=0),"",SUMIFS(Movimientos!$B$6:$B$505,Movimientos!$D$6:$D$505,">="&DATE(2025,4,1),Movimientos!$D$6:$D$505,"<"&DATE(2025,5,1))) -> 700 | E5: =B5-C5-D5 -> 1194 | F5: =IF(OR(B5="",C5=0),"",((B5-IF(D5="",0,D5))/C5-1)*100) -> 2.1654364 | G5: =IF(F5="","",((1+G4/100)*(1+F5/100)-1)*100) -> 6.0842335 | N5: ="2025 "&A5 -> 2025 Abr | O5: =B5 -> 57033 | P5: =C3+SUM(D3:D5) -> 53828 | Q5: =O5-P5 -> 3205 | T5: =A5 -> Abr | U5: =IF(B5="","",B5) -> 57033 | V5: =IF(B5="","",$C$3+SUM($D$3:D5)) -> 53828 | W5: =IF(U5="","",U5-V5) -> 3205
A6: May | B6: 59028 | C6: 57033 | D6: =IF(AND(B6="",COUNTIFS(Movimientos!$D$6:$D$505,">="&DATE(2025,5,1),Movimientos!$D$6:$D$505,"<"&DATE(2025,6,1))=0),"",SUMIFS(Movimientos!$B$6:$B$505,Movimientos!$D$6:$D$505,">="&DATE(2025,5,1),Movimientos!$D$6:$D$505,"<"&DATE(2025,6,1))) -> 700 | E6: =B6-C6-D6 -> 1295 | F6: =IF(OR(B6="",C6=0),"",((B6-IF(D6="",0,D6))/C6-1)*100) -> 2.2706153 | G6: =IF(F6="","",((1+G5/100)*(1+F6/100)-1)*100) -> 8.4929983 | N6: ="2025 "&A6 -> 2025 May | O6: =B6 -> 59028 | P6: =C3+SUM(D3:D6) -> 54528 | Q6: =O6-P6 -> 4500 | T6: =A6 -> May | U6: =IF(B6="","",B6) -> 59028 | V6: =IF(B6="","",$C$3+SUM($D$3:D6)) -> 54528 | W6: =IF(U6="","",U6-V6) -> 4500
A7: Jun | B7: 60385 | C7: 59028 | D7: =IF(AND(B7="",COUNTIFS(Movimientos!$D$6:$D$505,">="&DATE(2025,6,1),Movimientos!$D$6:$D$505,"<"&DATE(2025,7,1))=0),"",SUMIFS(Movimientos!$B$6:$B$505,Movimientos!$D$6:$D$505,">="&DATE(2025,6,1),Movimientos!$D$6:$D$505,"<"&DATE(2025,7,1))) -> 700 | E7: =B7-C7-D7 -> 657 | F7: =IF(OR(B7="",C7=0),"",((B7-IF(D7="",0,D7))/C7-1)*100) -> 1.1130311 | G7: =IF(F7="","",((1+G6/100)*(1+F7/100)-1)*100) -> 9.7005591 | N7: ="2025 "&A7 -> 2025 Jun | O7: =B7 -> 60385 | P7: =C3+SUM(D3:D7) -> 55228 | Q7: =O7-P7 -> 5157 | T7: =A7 -> Jun | U7: =IF(B7="","",B7) -> 60385 | V7: =IF(B7="","",$C$3+SUM($D$3:D7)) -> 55228 | W7: =IF(U7="","",U7-V7) -> 5157
A8: Jul | B8: 61988 | C8: 60385 | D8: =IF(AND(B8="",COUNTIFS(Movimientos!$D$6:$D$505,">="&DATE(2025,7,1),Movimientos!$D$6:$D$505,"<"&DATE(2025,8,1))=0),"",SUMIFS(Movimientos!$B$6:$B$505,Movimientos!$D$6:$D$505,">="&DATE(2025,7,1),Movimientos!$D$6:$D$505,"<"&DATE(2025,8,1))) -> 700 | E8: =B8-C8-D8 -> 903 | F8: =IF(OR(B8="",C8=0),"",((B8-IF(D8="",0,D8))/C8-1)*100) -> 1.4954045 | G8: =IF(F8="","",((1+G7/100)*(1+F8/100)-1)*100) -> 11.341026 | N8: ="2025 "&A8 -> 2025 Jul | O8: =B8 -> 61988 | P8: =C3+SUM(D3:D8) -> 55928 | Q8: =O8-P8 -> 6060 | T8: =A8 -> Jul | U8: =IF(B8="","",B8) -> 61988 | V8: =IF(B8="","",$C$3+SUM($D$3:D8)) -> 55928 | W8: =IF(U8="","",U8-V8) -> 6060
A9: Ago | B9: 63184 | C9: 61988 | D9: =IF(AND(B9="",COUNTIFS(Movimientos!$D$6:$D$505,">="&DATE(2025,8,1),Movimientos!$D$6:$D$505,"<"&DATE(2025,9,1))=0),"",SUMIFS(Movimientos!$B$6:$B$505,Movimientos!$D$6:$D$505,">="&DATE(2025,8,1),Movimientos!$D$6:$D$505,"<"&DATE(2025,9,1))) -> 700 | E9: =B9-C9-D9 -> 496 | F9: =IF(OR(B9="",C9=0),"",((B9-IF(D9="",0,D9))/C9-1)*100) -> 0.80015487 | G9: =IF(F9="","",((1+G8/100)*(1+F9/100)-1)*100) -> 12.231927 | N9: ="2025 "&A9 -> 2025 Ago | O9: =B9 -> 63184 | P9: =C3+SUM(D3:D9) -> 56628 | Q9: =O9-P9 -> 6556 | T9: =A9 -> Ago | U9: =IF(B9="","",B9) -> 63184 | V9: =IF(B9="","",$C$3+SUM($D$3:D9)) -> 56628 | W9: =IF(U9="","",U9-V9) -> 6556
A10: Sep | B10: 67169 | C10: 63184 | D10: =IF(AND(B10="",COUNTIFS(Movimientos!$D$6:$D$505,">="&DATE(2025,9,1),Movimientos!$D$6:$D$505,"<"&DATE(2025,10,1))=0),"",SUMIFS(Movimientos!$B$6:$B$505,Movimientos!$D$6:$D$505,">="&DATE(2025,9,1),Movimientos!$D$6:$D$505,"<"&DATE(2025,10,1))) -> 700 | E10: =B10-C10-D10 -> 3285 | F10: =IF(OR(B10="",C10=0),"",((B10-IF(D10="",0,D10))/C10-1)*100) -> 5.199101 | G10: =IF(F10="","",((1+G9/100)*(1+F10/100)-1)*100) -> 18.066978 | N10: ="2025 "&A10 -> 2025 Sep | O10: =B10 -> 67169 | P10: =C3+SUM(D3:D10) -> 57328 | Q10: =O10-P10 -> 9841 | T10: =A10 -> Sep | U10: =IF(B10="","",B10) -> 67169 | V10: =IF(B10="","",$C$3+SUM($D$3:D10)) -> 57328 | W10: =IF(U10="","",U10-V10) -> 9841
A11: Oct | B11: 69786 | C11: 67169 | D11: =IF(AND(B11="",COUNTIFS(Movimientos!$D$6:$D$505,">="&DATE(2025,10,1),Movimientos!$D$6:$D$505,"<"&DATE(2025,11,1))=0),"",SUMIFS(Movimientos!$B$6:$B$505,Movimientos!$D$6:$D$505,">="&DATE(2025,10,1),Movimientos!$D$6:$D$505,"<"&DATE(2025,11,1))) -> 700 | E11: =B11-C11-D11 -> 1917 | F11: =IF(OR(B11="",C11=0),"",((B11-IF(D11="",0,D11))/C11-1)*100) -> 2.8539951 | G11: =IF(F11="","",((1+G10/100)*(1+F11/100)-1)*100) -> 21.436604 | N11: ="2025 "&A11 -> 2025 Oct | O11: =B11 -> 69786 | P11: =C3+SUM(D3:D11) -> 58028 | Q11: =O11-P11 -> 11758 | T11: =A11 -> Oct | U11: =IF(B11="","",B11) -> 69786 | V11: =IF(B11="","",$C$3+SUM($D$3:D11)) -> 58028 | W11: =IF(U11="","",U11-V11) -> 11758
A12: Nov | B12: 70299 | C12: 69786 | D12: =IF(AND(B12="",COUNTIFS(Movimientos!$D$6:$D$505,">="&DATE(2025,11,1),Movimientos!$D$6:$D$505,"<"&DATE(2025,12,1))=0),"",SUMIFS(Movimientos!$B$6:$B$505,Movimientos!$D$6:$D$505,">="&DATE(2025,11,1),Movimientos!$D$6:$D$505,"<"&DATE(2025,12,1))) -> 700 | E12: =B12-C12-D12 -> -187 | F12: =IF(OR(B12="",C12=0),"",((B12-IF(D12="",0,D12))/C12-1)*100) -> -0.26796206 | G12: =IF(F12="","",((1+G11/100)*(1+F12/100)-1)*100) -> 21.1112 | N12: ="2025 "&A12 -> 2025 Nov | O12: =B12 -> 70299 | P12: =C3+SUM(D3:D12) -> 58728 | Q12: =O12-P12 -> 11571 | T12: =A12 -> Nov | U12: =IF(B12="","",B12) -> 70299 | V12: =IF(B12="","",$C$3+SUM($D$3:D12)) -> 58728 | W12: =IF(U12="","",U12-V12) -> 11571
A13: Dic | B13: 73708 | C13: 70299 | D13: =IF(AND(B13="",COUNTIFS(Movimientos!$D$6:$D$505,">="&DATE(2025,12,1),Movimientos!$D$6:$D$505,"<"&DATE(2025,13,1))=0),"",SUMIFS(Movimientos!$B$6:$B$505,Movimientos!$D$6:$D$505,">="&DATE(2025,12,1),Movimientos!$D$6:$D$505,"<"&DATE(2025,13,1))) -> 700 | E13: =B13-C13-D13 -> 2709 | F13: =IF(OR(B13="",C13=0),"",((B13-IF(D13="",0,D13))/C13-1)*100) -> 3.8535399 | G13: =IF(F13="","",((1+G12/100)*(1+F13/100)-1)*100) -> 25.778268 | N13: ="2025 "&A13 -> 2025 Dic | O13: =B13 -> 73708 | P13: =C3+SUM(D3:D13) -> 59428 | Q13: =O13-P13 -> 14280 | T13: =A13 -> Dic | U13: =IF(B13="","",B13) -> 73708 | V13: =IF(B13="","",$C$3+SUM($D$3:D13)) -> 59428 | W13: =IF(U13="","",U13-V13) -> 14280
A14: YTD 2025 | B14: =B13 -> 73708 | C14: =C3 -> 51728 | D14: =SUM(D3:D13) -> 7700 | E14: =SUM(E4:E13) -> 14280 | F14: =IF(OR(B14="",C14=0),"",(B14-C14-D14)/C14) -> 0.27605939 | G14: =IFERROR(__xludf.DUMMYFUNCTION("IFERROR(INDEX(FILTER(G4:G13,ISNUMBER(G4:G13)),COUNT(FILTER(G4:G13,ISNUMBER(G4:G13)))),"""")"),25.7782683126974) -> 25.778268 | N14: ="2026 "&A19 -> 2026 Ene | O14: =B19 -> 76000 | P14: =C3+SUM(D3:D13)+SUM(D19) -> 59928 | Q14: =O14-P14 -> 16072
A15: Volatilidad mensual | B15: =IFERROR(__xludf.DUMMYFUNCTION("IFERROR(STDEV(FILTER(F4:F13,ISNUMBER(F4:F13)))*SQRT(12)/100,"""")"),0.0570294609061031) -> 0.057029461 | C15: =IFERROR(__xludf.DUMMYFUNCTION("""Mensual · ""&COUNT(FILTER(F4:F13,ISNUMBER(F4:F13)))&"" meses"""),"Mensual · 10 meses") -> Mensual · 10 meses | N15: ="2026 "&A20 -> 2026 Feb | O15: =B20 -> 76422 | P15: =C3+SUM(D3:D13)+SUM(D19:D20) -> 60628 | Q15: =O15-P15 -> 15794
N16: ="2026 "&A21 -> 2026 Mar | O16: =B21 -> 72950 | P16: =C3+SUM(D3:D13)+SUM(D19:D21) -> 61228 | Q16: =O16-P16 -> 11722
A17: 2026 | N17: ="2026 "&A22 -> 2026 Abr | O17: =B22 -> 76207 | P17: =C3+SUM(D3:D13)+SUM(D19:D22) -> 60528 | Q17: =O17-P17 -> 15679 | T17: Mes | U17: Valor Total | V17: Capital invertido | W17: Plusvalías acumuladas
A18: Mes | B18: Valor Total | C18: Capital Inicial | D18: Capital Aportado | E18: Plusvalías | F18: % mes / simple YTD | G18: TWR acumulado | N18: ="2026 "&A23 -> 2026 May | O18: =B23 -> 79485 | P18: =C3+SUM(D3:D13)+SUM(D19:D23) -> 59828 | Q18: =O18-P18 -> 19657 | T18: =A19 -> Ene | U18: =IF(B19="","",B19) -> 76000 | V18: =IF(U18="","",$C$19+SUM($D$19:D19)) -> 74208 | W18: =IF(U18="","",U18-V18) -> 1792
A19: Ene | B19: 76000 | C19: =73708 -> 73708 | D19: =IF(AND(B19="",COUNTIFS(Movimientos!$D$6:$D$505,">="&DATE(2026,1,1),Movimientos!$D$6:$D$505,"<"&DATE(2026,2,1))=0),"",SUMIFS(Movimientos!$B$6:$B$505,Movimientos!$D$6:$D$505,">="&DATE(2026,1,1),Movimientos!$D$6:$D$505,"<"&DATE(2026,2,1))) -> 500 | E19: =B19-C19-D19 -> 1792 | F19: =IF(OR(B19="",C19=0),"",((B19-IF(D19="",0,D19))/C19-1)*100) -> 2.4312151 | G19: =IF(F19="","",F19) -> 2.4312151 | N19: ="2026 "&A24 -> 2026 Jun | O19: =B24 -> 76115 | P19: =IF(O19="","",C3+SUM(D3:D13)+SUM(D19:D24)) -> 56388 | Q19: =IF(O19="","",O19-P19) -> 19727 | T19: =A20 -> Feb | U19: =IF(B20="","",B20) -> 76422 | V19: =IF(U19="","",$C$19+SUM($D$19:D20)) -> 74908 | W19: =IF(U19="","",U19-V19) -> 1514
A20: Feb | B20: 76422 | C20: =B19 -> 76000 | D20: =IF(AND(B20="",COUNTIFS(Movimientos!$D$6:$D$505,">="&DATE(2026,2,1),Movimientos!$D$6:$D$505,"<"&DATE(2026,3,1))=0),"",SUMIFS(Movimientos!$B$6:$B$505,Movimientos!$D$6:$D$505,">="&DATE(2026,2,1),Movimientos!$D$6:$D$505,"<"&DATE(2026,3,1))) -> 700 | E20: =B20-C20-D20 -> -278 | F20: =IF(OR(B20="",C20=0),"",((B20-IF(D20="",0,D20))/C20-1)*100) -> -0.36578947 | G20: =IF(F20="","",((1+G19/100)*(1+F20/100)-1)*100) -> 2.0565325 | N20: ="2026 "&A25 -> 2026 Jul | O20: =B25 -> 83862 | P20: =IF(O20="","",C3+SUM(D3:D13)+SUM(D19:D25)) -> 62388 | Q20: =IF(O20="","",O20-P20) -> 21474 | T20: =A21 -> Mar | U20: =IF(B21="","",B21) -> 72950 | V20: =IF(U20="","",$C$19+SUM($D$19:D21)) -> 75508 | W20: =IF(U20="","",U20-V20) -> -2558
A21: Mar | B21: 72950 | C21: =B20 -> 76422 | D21: =IF(AND(B21="",COUNTIFS(Movimientos!$D$6:$D$505,">="&DATE(2026,3,1),Movimientos!$D$6:$D$505,"<"&DATE(2026,4,1))=0),"",SUMIFS(Movimientos!$B$6:$B$505,Movimientos!$D$6:$D$505,">="&DATE(2026,3,1),Movimientos!$D$6:$D$505,"<"&DATE(2026,4,1))) -> 600 | E21: =B21-C21-D21 -> -4072 | F21: =IF(OR(B21="",C21=0),"",((B21-IF(D21="",0,D21))/C21-1)*100) -> -5.3283086 | G21: =IF(F21="","",((1+G20/100)*(1+F21/100)-1)*100) -> -3.3813545 | N21: ="2026 "&A26 -> 2026 Ago | O21: =B26 -> 86713 | P21: =IF(O21="","",C3+SUM(D3:D13)+SUM(D19:D26)) -> 63896 | Q21: =IF(O21="","",O21-P21) -> 22817 | T21: =A22 -> Abr | U21: =IF(B22="","",B22) -> 76207 | V21: =IF(U21="","",$C$19+SUM($D$19:D22)) -> 74808 | W21: =IF(U21="","",U21-V21) -> 1399
A22: Abr | B22: 76207 | C22: =B21 -> 72950 | D22: =IF(AND(B22="",COUNTIFS(Movimientos!$D$6:$D$505,">="&DATE(2026,4,1),Movimientos!$D$6:$D$505,"<"&DATE(2026,5,1))=0),"",SUMIFS(Movimientos!$B$6:$B$505,Movimientos!$D$6:$D$505,">="&DATE(2026,4,1),Movimientos!$D$6:$D$505,"<"&DATE(2026,5,1))) -> -700 | E22: =B22-C22-D22 -> 3957 | F22: =IF(OR(B22="",C22=0),"",((B22-IF(D22="",0,D22))/C22-1)*100) -> 5.4242632 | G22: =IF(F22="","",((1+G21/100)*(1+F22/100)-1)*100) -> 1.8594951 | N22: ="2026 "&A27 -> 2026 Sep | O22: =B27 -> 85387 | P22: =IF(O22="","",C3+SUM(D3:D13)+SUM(D19:D27)) -> 63896 | Q22: =IF(O22="","",O22-P22) -> 21491 | T22: =A23 -> May | U22: =IF(B23="","",B23) -> 79485 | V22: =IF(U22="","",$C$19+SUM($D$19:D23)) -> 74108 | W22: =IF(U22="","",U22-V22) -> 5377
A23: May | B23: 79485 | C23: =B22 -> 76207 | D23: =IF(AND(B23="",COUNTIFS(Movimientos!$D$6:$D$505,">="&DATE(2026,5,1),Movimientos!$D$6:$D$505,"<"&DATE(2026,6,1))=0),"",SUMIFS(Movimientos!$B$6:$B$505,Movimientos!$D$6:$D$505,">="&DATE(2026,5,1),Movimientos!$D$6:$D$505,"<"&DATE(2026,6,1))) -> -700 | E23: =B23-C23-D23 -> 3978 | F23: =IF(OR(B23="",C23=0),"",((B23-IF(D23="",0,D23))/C23-1)*100) -> 5.2199929 | G23: =IF(F23="","",((1+G22/100)*(1+F23/100)-1)*100) -> 7.1765535 | N23: ="2026 "&A28 -> 2026 Oct | O23: =B28 | P23: =IF(O23="","",C3+SUM(D3:D13)+SUM(D19:D28)) | Q23: =IF(O23="","",O23-P23) | T23: =A24 -> Jun | U23: =IF(B24="","",B24) -> 76115 | V23: =IF(U23="","",$C$19+SUM($D$19:D24)) -> 70668 | W23: =IF(U23="","",U23-V23) -> 5447
A24: Jun | B24: 76115 | C24: =B23 -> 79485 | D24: =IF(AND(B24="",COUNTIFS(Movimientos!$D$6:$D$505,">="&DATE(2026,6,1),Movimientos!$D$6:$D$505,"<"&DATE(2026,7,1))=0),"",SUMIFS(Movimientos!$B$6:$B$505,Movimientos!$D$6:$D$505,">="&DATE(2026,6,1),Movimientos!$D$6:$D$505,"<"&DATE(2026,7,1))) -> -3440 | E24: =B24-C24-D24 -> 70 | F24: =IF(OR(B24="",C24=0),"",((B24-IF(D24="",0,D24))/C24-1)*100) -> 0.088066931 | G24: =IF(F24="","",((1+G23/100)*(1+F24/100)-1)*100) -> 7.2709406 | N24: ="2026 "&A29 -> 2026 Nov | O24: =B29 | P24: =IF(O24="","",C3+SUM(D3:D13)+SUM(D19:D29)) | Q24: =IF(O24="","",O24-P24) | T24: =A25 -> Jul | U24: =IF(B25="","",B25) -> 83862 | V24: =IF(U24="","",$C$19+SUM($D$19:D25)) -> 76668 | W24: =IF(U24="","",U24-V24) -> 7194
A25: Jul | B25: =IFERROR(__xludf.DUMMYFUNCTION("IFERROR(XLOOKUP(MAX(FILTER('Datos diarios'!$A$2:$A$366,'Datos diarios'!$A$2:$A$366>=DATE(2026,7,1),'Datos diarios'!$A$2:$A$366<DATE(2026,8,1),'Datos diarios'!$B$2:$B$366<>"""")),'Datos diarios'!$A$2:$A$366,'Datos diarios'!$B$2:$B$366,""""),"""")"),83862) -> 83862 | C25: =B24 -> 76115 | D25: =IF(AND(B25="",COUNTIFS(Movimientos!$D$6:$D$505,">="&DATE(2026,7,1),Movimientos!$D$6:$D$505,"<"&DATE(2026,8,1))=0),"",SUMIFS(Movimientos!$B$6:$B$505,Movimientos!$D$6:$D$505,">="&DATE(2026,7,1),Movimientos!$D$6:$D$505,"<"&DATE(2026,8,1))) -> 6000 | E25: =B25-C25-D25 -> 1747 | F25: =IF(OR(B25="",C25=0),"",((B25-IF(D25="",0,D25))/C25-1)*100) -> 2.2952112 | G25: =IF(F25="","",((1+G24/100)*(1+F25/100)-1)*100) -> 9.7330353 | N25: ="2026 "&A30 -> 2026 Dic | O25: =B30 | P25: =IF(O25="","",C3+SUM(D3:D13)+SUM(D19:D30)) | Q25: =IF(O25="","",O25-P25) | T25: =A26 -> Ago | U25: =IF(B26="","",B26) -> 86713 | V25: =IF(U25="","",$C$19+SUM($D$19:D26)) -> 78176 | W25: =IF(U25="","",U25-V25) -> 8537
A26: Ago | B26: =IFERROR(__xludf.DUMMYFUNCTION("IFERROR(XLOOKUP(MAX(FILTER('Datos diarios'!$A$2:$A$366,'Datos diarios'!$A$2:$A$366>=DATE(2026,8,1),'Datos diarios'!$A$2:$A$366<DATE(2026,9,1),'Datos diarios'!$B$2:$B$366<>"""")),'Datos diarios'!$A$2:$A$366,'Datos diarios'!$B$2:$B$366,""""),"""")"),86713) -> 86713 | C26: =B25 -> 83862 | D26: =IF(AND(B26="",COUNTIFS(Movimientos!$D$6:$D$505,">="&DATE(2026,8,1),Movimientos!$D$6:$D$505,"<"&DATE(2026,9,1))=0),"",SUMIFS(Movimientos!$B$6:$B$505,Movimientos!$D$6:$D$505,">="&DATE(2026,8,1),Movimientos!$D$6:$D$505,"<"&DATE(2026,9,1))) -> 1508 | E26: =IF(B26="","",B26-C26-IF(D26="",0,D26)) -> 1343 | F26: =IF(OR(B26="",C26=0),"",((B26-IF(D26="",0,D26))/C26-1)*100) -> 1.6014405 | G26: =IF(F26="","",((1+G25/100)*(1+F26/100)-1)*100) -> 11.490344 | T26: =A27 -> Sep | U26: =IF(B27="","",B27) -> 85387 | V26: =IF(U26="","",$C$19+SUM($D$19:D27)) -> 78176 | W26: =IF(U26="","",U26-V26) -> 7211
A27: Sep | B27: =IFERROR(__xludf.DUMMYFUNCTION("IFERROR(XLOOKUP(MAX(FILTER('Datos diarios'!$A$2:$A$366,'Datos diarios'!$A$2:$A$366>=DATE(2026,9,1),'Datos diarios'!$A$2:$A$366<DATE(2026,10,1),'Datos diarios'!$B$2:$B$366<>"""")),'Datos diarios'!$A$2:$A$366,'Datos diarios'!$B$2:$B$366,""""),"""")"),85387) -> 85387 | C27: =B26 -> 86713 | D27: =IF(AND(B27="",COUNTIFS(Movimientos!$D$6:$D$505,">="&DATE(2026,9,1),Movimientos!$D$6:$D$505,"<"&DATE(2026,10,1))=0),"",SUMIFS(Movimientos!$B$6:$B$505,Movimientos!$D$6:$D$505,">="&DATE(2026,9,1),Movimientos!$D$6:$D$505,"<"&DATE(2026,10,1))) -> 0 | E27: =IF(B27="","",B27-C27-IF(D27="",0,D27)) -> -1326 | F27: =IF(OR(B27="",C27=0),"",((B27-IF(D27="",0,D27))/C27-1)*100) -> -1.5291825 | G27: =IF(F27="","",((1+G26/100)*(1+F27/100)-1)*100) -> 9.7854537 | T27: =A28 -> Oct | U27: =IF(B28="","",B28) | V27: =IF(U27="","",$C$19+SUM($D$19:D28)) | W27: =IF(U27="","",U27-V27)
A28: Oct | B28: =IFERROR(__xludf.DUMMYFUNCTION("IFERROR(XLOOKUP(MAX(FILTER('Datos diarios'!$A$2:$A$366,'Datos diarios'!$A$2:$A$366>=DATE(2026,10,1),'Datos diarios'!$A$2:$A$366<DATE(2026,11,1),'Datos diarios'!$B$2:$B$366<>"""")),'Datos diarios'!$A$2:$A$366,'Datos diarios'!$B$2:$B$366,""""),"""")"),"") | C28: =B27 -> 85387 | D28: =IF(AND(B28="",COUNTIFS(Movimientos!$D$6:$D$505,">="&DATE(2026,10,1),Movimientos!$D$6:$D$505,"<"&DATE(2026,11,1))=0),"",SUMIFS(Movimientos!$B$6:$B$505,Movimientos!$D$6:$D$505,">="&DATE(2026,10,1),Movimientos!$D$6:$D$505,"<"&DATE(2026,11,1))) | E28: =IF(B28="","",B28-C28-IF(D28="",0,D28)) | F28: =IF(OR(B28="",C28=0),"",((B28-IF(D28="",0,D28))/C28-1)*100) | G28: =IF(F28="","",((1+G27/100)*(1+F28/100)-1)*100) | T28: =A29 -> Nov | U28: =IF(B29="","",B29) | V28: =IF(U28="","",$C$19+SUM($D$19:D29)) | W28: =IF(U28="","",U28-V28)
A29: Nov | B29: =IFERROR(__xludf.DUMMYFUNCTION("IFERROR(XLOOKUP(MAX(FILTER('Datos diarios'!$A$2:$A$366,'Datos diarios'!$A$2:$A$366>=DATE(2026,11,1),'Datos diarios'!$A$2:$A$366<DATE(2026,12,1),'Datos diarios'!$B$2:$B$366<>"""")),'Datos diarios'!$A$2:$A$366,'Datos diarios'!$B$2:$B$366,""""),"""")"),"") | C29: =B28 | D29: =IF(AND(B29="",COUNTIFS(Movimientos!$D$6:$D$505,">="&DATE(2026,11,1),Movimientos!$D$6:$D$505,"<"&DATE(2026,12,1))=0),"",SUMIFS(Movimientos!$B$6:$B$505,Movimientos!$D$6:$D$505,">="&DATE(2026,11,1),Movimientos!$D$6:$D$505,"<"&DATE(2026,12,1))) | E29: =IF(B29="","",B29-C29-IF(D29="",0,D29)) | F29: =IF(OR(B29="",C29=0),"",((B29-IF(D29="",0,D29))/C29-1)*100) | G29: =IF(F29="","",((1+G28/100)*(1+F29/100)-1)*100) | T29: =A30 -> Dic | U29: =IF(B30="","",B30) | V29: =IF(U29="","",$C$19+SUM($D$19:D30)) | W29: =IF(U29="","",U29-V29)
A30: Dic | B30: =IFERROR(__xludf.DUMMYFUNCTION("IFERROR(XLOOKUP(MAX(FILTER('Datos diarios'!$A$2:$A$366,'Datos diarios'!$A$2:$A$366>=DATE(2026,12,1),'Datos diarios'!$A$2:$A$366<DATE(2027,1,1),'Datos diarios'!$B$2:$B$366<>"""")),'Datos diarios'!$A$2:$A$366,'Datos diarios'!$B$2:$B$366,""""),"""")"),"") | C30: =B29 | D30: =IF(AND(B30="",COUNTIFS(Movimientos!$D$6:$D$505,">="&DATE(2026,12,1),Movimientos!$D$6:$D$505,"<"&DATE(2026,13,1))=0),"",SUMIFS(Movimientos!$B$6:$B$505,Movimientos!$D$6:$D$505,">="&DATE(2026,12,1),Movimientos!$D$6:$D$505,"<"&DATE(2026,13,1))) | E30: =IF(B30="","",B30-C30-IF(D30="",0,D30)) | F30: =IF(OR(B30="",C30=0),"",((B30-IF(D30="",0,D30))/C30-1)*100) | G30: =IF(F30="","",((1+G29/100)*(1+F30/100)-1)*100)
A31: YTD 2026 | B31: =IFERROR(__xludf.DUMMYFUNCTION("IFERROR(INDEX(FILTER(B19:B30,ISNUMBER(B19:B30)),COUNT(FILTER(B19:B30,ISNUMBER(B19:B30)))),"""")"),85387) -> 85387 | C31: =C19 -> 73708 | D31: =SUM(D19:D30) -> 4468 | E31: =SUM(E19:E30) -> 7211 | F31: =IF(OR(B31="",C31=0),"",(B31-C31-D31)/C31) -> 0.097831986 | G31: =IFERROR(__xludf.DUMMYFUNCTION("IFERROR(INDEX(FILTER(G19:G30,ISNUMBER(G19:G30)),COUNT(FILTER(G19:G30,ISNUMBER(G19:G30)))),"""")"),9.78545366884213) -> 9.7854537
A32: Volatilidad híbrida | B32: =IFERROR(__xludf.DUMMYFUNCTION("LET(m,FILTER(F19:F24,ISNUMBER(F19:F24)),d,FILTER('Datos diarios'!D2:D366,'Datos diarios'!A2:A366>=DATE(2026,7,7),'Datos diarios'!A2:A366<=TODAY(),ISNUMBER('Datos diarios'!D2:D366)),vm,VAR(m)*12/10000,vd,VAR(d)*365/10000,wm,COUNT(m)/12,wd,COUNT(d)/365,SQRT"&"((vm*wm+vd*wd)/(wm+wd)))"),0.127843428409182) -> 0.12784343 | C32: =IFERROR(__xludf.DUMMYFUNCTION("""6 meses · ""&COUNT(FILTER('Datos diarios'!D2:D366,'Datos diarios'!A2:A366>=DATE(2026,7,7),'Datos diarios'!A2:A366<=TODAY(),ISNUMBER('Datos diarios'!D2:D366)))&"" días"""),"6 meses · 54 días") -> 6 meses · 54 días
A34: 2027
A35: Mes | B35: Valor Total | C35: Capital Inicial | D35: Capital Aportado | E35: Plusvalías | F35: % mes / simple YTD | G35: TWR acumulado
A36: Ene | C36: =B30 | D36: =IF(AND(B36="",COUNTIFS(Movimientos!$D$6:$D$505,">="&DATE(2027,1,1),Movimientos!$D$6:$D$505,"<"&DATE(2027,2,1))=0),"",SUMIFS(Movimientos!$B$6:$B$505,Movimientos!$D$6:$D$505,">="&DATE(2027,1,1),Movimientos!$D$6:$D$505,"<"&DATE(2027,2,1))) | E36: =IF(B36="","",B36-C36-IF(D36="",0,D36)) | F36: =IF(OR(B36="",C36=0),"",((B36-IF(D36="",0,D36))/C36-1)*100) | G36: =IF(F36="","",F36)
A37: Feb | C37: =B36 -> 0 | D37: =IF(AND(B37="",COUNTIFS(Movimientos!$D$6:$D$505,">="&DATE(2027,2,1),Movimientos!$D$6:$D$505,"<"&DATE(2027,3,1))=0),"",SUMIFS(Movimientos!$B$6:$B$505,Movimientos!$D$6:$D$505,">="&DATE(2027,2,1),Movimientos!$D$6:$D$505,"<"&DATE(2027,3,1))) | E37: =IF(B37="","",B37-C37-IF(D37="",0,D37)) | F37: =IF(OR(B37="",C37=0),"",((B37-IF(D37="",0,D37))/C37-1)*100) | G37: =IF(F37="","",((1+G36/100)*(1+F37/100)-1)*100)
A38: Mar | C38: =B37 -> 0 | D38: =IF(AND(B38="",COUNTIFS(Movimientos!$D$6:$D$505,">="&DATE(2027,3,1),Movimientos!$D$6:$D$505,"<"&DATE(2027,4,1))=0),"",SUMIFS(Movimientos!$B$6:$B$505,Movimientos!$D$6:$D$505,">="&DATE(2027,3,1),Movimientos!$D$6:$D$505,"<"&DATE(2027,4,1))) | E38: =IF(B38="","",B38-C38-IF(D38="",0,D38)) | F38: =IF(OR(B38="",C38=0),"",((B38-IF(D38="",0,D38))/C38-1)*100) | G38: =IF(F38="","",((1+G37/100)*(1+F38/100)-1)*100)
A39: Abr | C39: =B38 -> 0 | D39: =IF(AND(B39="",COUNTIFS(Movimientos!$D$6:$D$505,">="&DATE(2027,4,1),Movimientos!$D$6:$D$505,"<"&DATE(2027,5,1))=0),"",SUMIFS(Movimientos!$B$6:$B$505,Movimientos!$D$6:$D$505,">="&DATE(2027,4,1),Movimientos!$D$6:$D$505,"<"&DATE(2027,5,1))) | E39: =IF(B39="","",B39-C39-IF(D39="",0,D39)) | F39: =IF(OR(B39="",C39=0),"",((B39-IF(D39="",0,D39))/C39-1)*100) | G39: =IF(F39="","",((1+G38/100)*(1+F39/100)-1)*100)
A40: May | C40: =B39 -> 0 | D40: =IF(AND(B40="",COUNTIFS(Movimientos!$D$6:$D$505,">="&DATE(2027,5,1),Movimientos!$D$6:$D$505,"<"&DATE(2027,6,1))=0),"",SUMIFS(Movimientos!$B$6:$B$505,Movimientos!$D$6:$D$505,">="&DATE(2027,5,1),Movimientos!$D$6:$D$505,"<"&DATE(2027,6,1))) | E40: =IF(B40="","",B40-C40-IF(D40="",0,D40)) | F40: =IF(OR(B40="",C40=0),"",((B40-IF(D40="",0,D40))/C40-1)*100) | G40: =IF(F40="","",((1+G39/100)*(1+F40/100)-1)*100)
A41: Jun | C41: =B40 -> 0 | D41: =IF(AND(B41="",COUNTIFS(Movimientos!$D$6:$D$505,">="&DATE(2027,6,1),Movimientos!$D$6:$D$505,"<"&DATE(2027,7,1))=0),"",SUMIFS(Movimientos!$B$6:$B$505,Movimientos!$D$6:$D$505,">="&DATE(2027,6,1),Movimientos!$D$6:$D$505,"<"&DATE(2027,7,1))) | E41: =IF(B41="","",B41-C41-IF(D41="",0,D41)) | F41: =IF(OR(B41="",C41=0),"",((B41-IF(D41="",0,D41))/C41-1)*100) | G41: =IF(F41="","",((1+G40/100)*(1+F41/100)-1)*100)
A42: Jul | C42: =B41 -> 0 | D42: =IF(AND(B42="",COUNTIFS(Movimientos!$D$6:$D$505,">="&DATE(2027,7,1),Movimientos!$D$6:$D$505,"<"&DATE(2027,8,1))=0),"",SUMIFS(Movimientos!$B$6:$B$505,Movimientos!$D$6:$D$505,">="&DATE(2027,7,1),Movimientos!$D$6:$D$505,"<"&DATE(2027,8,1))) | E42: =IF(B42="","",B42-C42-IF(D42="",0,D42)) | F42: =IF(OR(B42="",C42=0),"",((B42-IF(D42="",0,D42))/C42-1)*100) | G42: =IF(F42="","",((1+G41/100)*(1+F42/100)-1)*100)
A43: Ago | C43: =B42 -> 0 | D43: =IF(AND(B43="",COUNTIFS(Movimientos!$D$6:$D$505,">="&DATE(2027,8,1),Movimientos!$D$6:$D$505,"<"&DATE(2027,9,1))=0),"",SUMIFS(Movimientos!$B$6:$B$505,Movimientos!$D$6:$D$505,">="&DATE(2027,8,1),Movimientos!$D$6:$D$505,"<"&DATE(2027,9,1))) | E43: =IF(B43="","",B43-C43-IF(D43="",0,D43)) | F43: =IF(OR(B43="",C43=0),"",((B43-IF(D43="",0,D43))/C43-1)*100) | G43: =IF(F43="","",((1+G42/100)*(1+F43/100)-1)*100)
A44: Sep | C44: =B43 -> 0 | D44: =IF(AND(B44="",COUNTIFS(Movimientos!$D$6:$D$505,">="&DATE(2027,9,1),Movimientos!$D$6:$D$505,"<"&DATE(2027,10,1))=0),"",SUMIFS(Movimientos!$B$6:$B$505,Movimientos!$D$6:$D$505,">="&DATE(2027,9,1),Movimientos!$D$6:$D$505,"<"&DATE(2027,10,1))) | E44: =IF(B44="","",B44-C44-IF(D44="",0,D44)) | F44: =IF(OR(B44="",C44=0),"",((B44-IF(D44="",0,D44))/C44-1)*100) | G44: =IF(F44="","",((1+G43/100)*(1+F44/100)-1)*100)
A45: Oct | C45: =B44 -> 0 | D45: =IF(AND(B45="",COUNTIFS(Movimientos!$D$6:$D$505,">="&DATE(2027,10,1),Movimientos!$D$6:$D$505,"<"&DATE(2027,11,1))=0),"",SUMIFS(Movimientos!$B$6:$B$505,Movimientos!$D$6:$D$505,">="&DATE(2027,10,1),Movimientos!$D$6:$D$505,"<"&DATE(2027,11,1))) | E45: =IF(B45="","",B45-C45-IF(D45="",0,D45)) | F45: =IF(OR(B45="",C45=0),"",((B45-IF(D45="",0,D45))/C45-1)*100) | G45: =IF(F45="","",((1+G44/100)*(1+F45/100)-1)*100)
A46: Nov | C46: =B45 -> 0 | D46: =IF(AND(B46="",COUNTIFS(Movimientos!$D$6:$D$505,">="&DATE(2027,11,1),Movimientos!$D$6:$D$505,"<"&DATE(2027,12,1))=0),"",SUMIFS(Movimientos!$B$6:$B$505,Movimientos!$D$6:$D$505,">="&DATE(2027,11,1),Movimientos!$D$6:$D$505,"<"&DATE(2027,12,1))) | E46: =IF(B46="","",B46-C46-IF(D46="",0,D46)) | F46: =IF(OR(B46="",C46=0),"",((B46-IF(D46="",0,D46))/C46-1)*100) | G46: =IF(F46="","",((1+G45/100)*(1+F46/100)-1)*100)
A47: Dic | C47: =B46 -> 0 | D47: =IF(AND(B47="",COUNTIFS(Movimientos!$D$6:$D$505,">="&DATE(2027,12,1),Movimientos!$D$6:$D$505,"<"&DATE(2027,13,1))=0),"",SUMIFS(Movimientos!$B$6:$B$505,Movimientos!$D$6:$D$505,">="&DATE(2027,12,1),Movimientos!$D$6:$D$505,"<"&DATE(2027,13,1))) | E47: =IF(B47="","",B47-C47-IF(D47="",0,D47)) | F47: =IF(OR(B47="",C47=0),"",((B47-IF(D47="",0,D47))/C47-1)*100) | G47: =IF(F47="","",((1+G46/100)*(1+F47/100)-1)*100)
A48: YTD 2027 | B48: =IFERROR(__xludf.DUMMYFUNCTION("IFERROR(INDEX(FILTER(B36:B47,ISNUMBER(B36:B47)),COUNT(FILTER(B36:B47,ISNUMBER(B36:B47)))),"""")"),"") | C48: =C36 | D48: =SUM(D36:D47) -> 0 | E48: =SUM(E36:E47) -> 0 | F48: =IF(OR(B48="",C48=0),"",(B48-C48-D48)/C48) | G48: =IFERROR(__xludf.DUMMYFUNCTION("IFERROR(INDEX(FILTER(G36:G47,ISNUMBER(G36:G47)),COUNT(FILTER(G36:G47,ISNUMBER(G36:G47)))),"""")"),"")
A49: Volatilidad | B49: =IFERROR(__xludf.DUMMYFUNCTION("IF(IFERROR(COUNT(FILTER('Datos diarios'!D2:D366,'Datos diarios'!A2:A366<>"""",YEAR('Datos diarios'!A2:A366)=2027,ISNUMBER('Datos diarios'!D2:D366))),0)>=20,STDEV(FILTER('Datos diarios'!D2:D366,'Datos diarios'!A2:A366<>"""",YEAR('Datos diarios'!A2:A366)=20"&"27,ISNUMBER('Datos diarios'!D2:D366)))*SQRT(365)/100,IFERROR(STDEV(FILTER(F36:F47,ISNUMBER(F36:F47)))*SQRT(12)/100,""""))"),"") | C49: =IFERROR(__xludf.DUMMYFUNCTION("IF(IFERROR(COUNT(FILTER('Datos diarios'!D2:D366,'Datos diarios'!A2:A366<>"""",YEAR('Datos diarios'!A2:A366)=2027,ISNUMBER('Datos diarios'!D2:D366))),0)>=20,""Diaria · ""&COUNT(FILTER('Datos diarios'!D2:D366,'Datos diarios'!A2:A366<>"""",YEAR('Datos diario"&"s'!A2:A366)=2027,ISNUMBER('Datos diarios'!D2:D366)))&"" días"",""Mensual · ""&COUNT(FILTER(F36:F47,ISNUMBER(F36:F47)))&"" meses"")"),"Mensual · 0 meses") -> Mensual · 0 meses

Sheet Diario
A1: DIARIO · 2026
A2: Introduce el valor total de la cartera en amarillo.
A3: Movimientos de dinero → pestaña Movimientos.
A4: Verde: cierre histórico. Gris: fin de semana.
A5: Fecha | B5: Valor € | C5: Estado
A6: 46023 | C6: =IF(B6="",IF(A6>TODAY(),"Pendiente","Sin dato"),IF(A6>TODAY(),"Fecha futura",IF(OR(A6=DATE(2026,1,30),A6=DATE(2026,2,27),A6=DATE(2026,3,31),A6=DATE(2026,4,30),A6=DATE(2026,5,29),A6=DATE(2026,6,30)),"Histórico",IF(WEEKDAY(A6,2)>5,"Fin semana","Registrado")))) -> Sin dato
A7: 46024 | C7: =IF(B7="",IF(A7>TODAY(),"Pendiente","Sin dato"),IF(A7>TODAY(),"Fecha futura",IF(OR(A7=DATE(2026,1,30),A7=DATE(2026,2,27),A7=DATE(2026,3,31),A7=DATE(2026,4,30),A7=DATE(2026,5,29),A7=DATE(2026,6,30)),"Histórico",IF(WEEKDAY(A7,2)>5,"Fin semana","Registrado")))) -> Sin dato
A8: 46025 | C8: =IF(B8="",IF(A8>TODAY(),"Pendiente","Sin dato"),IF(A8>TODAY(),"Fecha futura",IF(OR(A8=DATE(2026,1,30),A8=DATE(2026,2,27),A8=DATE(2026,3,31),A8=DATE(2026,4,30),A8=DATE(2026,5,29),A8=DATE(2026,6,30)),"Histórico",IF(WEEKDAY(A8,2)>5,"Fin semana","Registrado")))) -> Sin dato
A9: 46026 | C9: =IF(B9="",IF(A9>TODAY(),"Pendiente","Sin dato"),IF(A9>TODAY(),"Fecha futura",IF(OR(A9=DATE(2026,1,30),A9=DATE(2026,2,27),A9=DATE(2026,3,31),A9=DATE(2026,4,30),A9=DATE(2026,5,29),A9=DATE(2026,6,30)),"Histórico",IF(WEEKDAY(A9,2)>5,"Fin semana","Registrado")))) -> Sin dato
A10: 46027 | C10: =IF(B10="",IF(A10>TODAY(),"Pendiente","Sin dato"),IF(A10>TODAY(),"Fecha futura",IF(OR(A10=DATE(2026,1,30),A10=DATE(2026,2,27),A10=DATE(2026,3,31),A10=DATE(2026,4,30),A10=DATE(2026,5,29),A10=DATE(2026,6,30)),"Histórico",IF(WEEKDAY(A10,2)>5,"Fin semana","Registrado")))) -> Sin dato
A11: 46028 | C11: =IF(B11="",IF(A11>TODAY(),"Pendiente","Sin dato"),IF(A11>TODAY(),"Fecha futura",IF(OR(A11=DATE(2026,1,30),A11=DATE(2026,2,27),A11=DATE(2026,3,31),A11=DATE(2026,4,30),A11=DATE(2026,5,29),A11=DATE(2026,6,30)),"Histórico",IF(WEEKDAY(A11,2)>5,"Fin semana","Registrado")))) -> Sin dato
A12: 46029 | C12: =IF(B12="",IF(A12>TODAY(),"Pendiente","Sin dato"),IF(A12>TODAY(),"Fecha futura",IF(OR(A12=DATE(2026,1,30),A12=DATE(2026,2,27),A12=DATE(2026,3,31),A12=DATE(2026,4,30),A12=DATE(2026,5,29),A12=DATE(2026,6,30)),"Histórico",IF(WEEKDAY(A12,2)>5,"Fin semana","Registrado")))) -> Sin dato
A13: 46030 | C13: =IF(B13="",IF(A13>TODAY(),"Pendiente","Sin dato"),IF(A13>TODAY(),"Fecha futura",IF(OR(A13=DATE(2026,1,30),A13=DATE(2026,2,27),A13=DATE(2026,3,31),A13=DATE(2026,4,30),A13=DATE(2026,5,29),A13=DATE(2026,6,30)),"Histórico",IF(WEEKDAY(A13,2)>5,"Fin semana","Registrado")))) -> Sin dato
A14: 46031 | C14: =IF(B14="",IF(A14>TODAY(),"Pendiente","Sin dato"),IF(A14>TODAY(),"Fecha futura",IF(OR(A14=DATE(2026,1,30),A14=DATE(2026,2,27),A14=DATE(2026,3,31),A14=DATE(2026,4,30),A14=DATE(2026,5,29),A14=DATE(2026,6,30)),"Histórico",IF(WEEKDAY(A14,2)>5,"Fin semana","Registrado")))) -> Sin dato
A15: 46032 | C15: =IF(B15="",IF(A15>TODAY(),"Pendiente","Sin dato"),IF(A15>TODAY(),"Fecha futura",IF(OR(A15=DATE(2026,1,30),A15=DATE(2026,2,27),A15=DATE(2026,3,31),A15=DATE(2026,4,30),A15=DATE(2026,5,29),A15=DATE(2026,6,30)),"Histórico",IF(WEEKDAY(A15,2)>5,"Fin semana","Registrado")))) -> Sin dato
A16: 46033 | C16: =IF(B16="",IF(A16>TODAY(),"Pendiente","Sin dato"),IF(A16>TODAY(),"Fecha futura",IF(OR(A16=DATE(2026,1,30),A16=DATE(2026,2,27),A16=DATE(2026,3,31),A16=DATE(2026,4,30),A16=DATE(2026,5,29),A16=DATE(2026,6,30)),"Histórico",IF(WEEKDAY(A16,2)>5,"Fin semana","Registrado")))) -> Sin dato
A17: 46034 | C17: =IF(B17="",IF(A17>TODAY(),"Pendiente","Sin dato"),IF(A17>TODAY(),"Fecha futura",IF(OR(A17=DATE(2026,1,30),A17=DATE(2026,2,27),A17=DATE(2026,3,31),A17=DATE(2026,4,30),A17=DATE(2026,5,29),A17=DATE(2026,6,30)),"Histórico",IF(WEEKDAY(A17,2)>5,"Fin semana","Registrado")))) -> Sin dato
... A34: 46051 | C34: =IF(B34="",IF(A34>TODAY(),"Pendiente","Sin dato"),IF(A34>TODAY(),"Fecha futura",IF(OR(A34=DATE(2026,1,30),A34=DATE(2026,2,27),A34=DATE(2026,3,31),A34=DATE(2026,4,30),A34=DATE(2026,5,29),A34=DATE(2026,6,30)),"Histórico",IF(WEEKDAY(A34,2)>5,"Fin semana","Registrado")))) -> Sin dato
A35: 46052 | B35: =Evolucion!B19 -> 76000 | C35: =IF(B35="",IF(A35>TODAY(),"Pendiente","Sin dato"),IF(A35>TODAY(),"Fecha futura",IF(OR(A35=DATE(2026,1,30),A35=DATE(2026,2,27),A35=DATE(2026,3,31),A35=DATE(2026,4,30),A35=DATE(2026,5,29),A35=DATE(2026,6,30)),"Histórico",IF(WEEKDAY(A35,2)>5,"Fin semana","Registrado")))) -> Histórico
A36: 46053 | C36: =IF(B36="",IF(A36>TODAY(),"Pendiente","Sin dato"),IF(A36>TODAY(),"Fecha futura",IF(OR(A36=DATE(2026,1,30),A36=DATE(2026,2,27),A36=DATE(2026,3,31),A36=DATE(2026,4,30),A36=DATE(2026,5,29),A36=DATE(2026,6,30)),"Histórico",IF(WEEKDAY(A36,2)>5,"Fin semana","Registrado")))) -> Sin dato
A37: 46054 | C37: =IF(B37="",IF(A37>TODAY(),"Pendiente","Sin dato"),IF(A37>TODAY(),"Fecha futura",IF(OR(A37=DATE(2026,1,30),A37=DATE(2026,2,27),A37=DATE(2026,3,31),A37=DATE(2026,4,30),A37=DATE(2026,5,29),A37=DATE(2026,6,30)),"Histórico",IF(WEEKDAY(A37,2)>5,"Fin semana","Registrado")))) -> Sin dato
A38: 46055 | C38: =IF(B38="",IF(A38>TODAY(),"Pendiente","Sin dato"),IF(A38>TODAY(),"Fecha futura",IF(OR(A38=DATE(2026,1,30),A38=DATE(2026,2,27),A38=DATE(2026,3,31),A38=DATE(2026,4,30),A38=DATE(2026,5,29),A38=DATE(2026,6,30)),"Histórico",IF(WEEKDAY(A38,2)>5,"Fin semana","Registrado")))) -> Sin dato
A39: 46056 | C39: =IF(B39="",IF(A39>TODAY(),"Pendiente","Sin dato"),IF(A39>TODAY(),"Fecha futura",IF(OR(A39=DATE(2026,1,30),A39=DATE(2026,2,27),A39=DATE(2026,3,31),A39=DATE(2026,4,30),A39=DATE(2026,5,29),A39=DATE(2026,6,30)),"Histórico",IF(WEEKDAY(A39,2)>5,"Fin semana","Registrado")))) -> Sin dato
A40: 46057 | C40: =IF(B40="",IF(A40>TODAY(),"Pendiente","Sin dato"),IF(A40>TODAY(),"Fecha futura",IF(OR(A40=DATE(2026,1,30),A40=DATE(2026,2,27),A40=DATE(2026,3,31),A40=DATE(2026,4,30),A40=DATE(2026,5,29),A40=DATE(2026,6,30)),"Histórico",IF(WEEKDAY(A40,2)>5,"Fin semana","Registrado")))) -> Sin dato
A41: 46058 | C41: =IF(B41="",IF(A41>TODAY(),"Pendiente","Sin dato"),IF(A41>TODAY(),"Fecha futura",IF(OR(A41=DATE(2026,1,30),A41=DATE(2026,2,27),A41=DATE(2026,3,31),A41=DATE(2026,4,30),A41=DATE(2026,5,29),A41=DATE(2026,6,30)),"Histórico",IF(WEEKDAY(A41,2)>5,"Fin semana","Registrado")))) -> Sin dato
A42: 46059 | C42: =IF(B42="",IF(A42>TODAY(),"Pendiente","Sin dato"),IF(A42>TODAY(),"Fecha futura",IF(OR(A42=DATE(2026,1,30),A42=DATE(2026,2,27),A42=DATE(2026,3,31),A42=DATE(2026,4,30),A42=DATE(2026,5,29),A42=DATE(2026,6,30)),"Histórico",IF(WEEKDAY(A42,2)>5,"Fin semana","Registrado")))) -> Sin dato
A43: 46060 | C43: =IF(B43="",IF(A43>TODAY(),"Pendiente","Sin dato"),IF(A43>TODAY(),"Fecha futura",IF(OR(A43=DATE(2026,1,30),A43=DATE(2026,2,27),A43=DATE(2026,3,31),A43=DATE(2026,4,30),A43=DATE(2026,5,29),A43=DATE(2026,6,30)),"Histórico",IF(WEEKDAY(A43,2)>5,"Fin semana","Registrado")))) -> Sin dato
A44: 46061 | C44: =IF(B44="",IF(A44>TODAY(),"Pendiente","Sin dato"),IF(A44>TODAY(),"Fecha futura",IF(OR(A44=DATE(2026,1,30),A44=DATE(2026,2,27),A44=DATE(2026,3,31),A44=DATE(2026,4,30),A44=DATE(2026,5,29),A44=DATE(2026,6,30)),"Histórico",IF(WEEKDAY(A44,2)>5,"Fin semana","Registrado")))) -> Sin dato
A45: 46062 | C45: =IF(B45="",IF(A45>TODAY(),"Pendiente","Sin dato"),IF(A45>TODAY(),"Fecha futura",IF(OR(A45=DATE(2026,1,30),A45=DATE(2026,2,27),A45=DATE(2026,3,31),A45=DATE(2026,4,30),A45=DATE(2026,5,29),A45=DATE(2026,6,30)),"Histórico",IF(WEEKDAY(A45,2)>5,"Fin semana","Registrado")))) -> Sin dato
A46: 46063 | C46: =IF(B46="",IF(A46>TODAY(),"Pendiente","Sin dato"),IF(A46>TODAY(),"Fecha futura",IF(OR(A46=DATE(2026,1,30),A46=DATE(2026,2,27),A46=DATE(2026,3,31),A46=DATE(2026,4,30),A46=DATE(2026,5,29),A46=DATE(2026,6,30)),"Histórico",IF(WEEKDAY(A46,2)>5,"Fin semana","Registrado")))) -> Sin dato
A47: 46064 | C47: =IF(B47="",IF(A47>TODAY(),"Pendiente","Sin dato"),IF(A47>TODAY(),"Fecha futura",IF(OR(A47=DATE(2026,1,30),A47=DATE(2026,2,27),A47=DATE(2026,3,31),A47=DATE(2026,4,30),A47=DATE(2026,5,29),A47=DATE(2026,6,30)),"Histórico",IF(WEEKDAY(A47,2)>5,"Fin semana","Registrado")))) -> Sin dato
... A62: 46079 | C62: =IF(B62="",IF(A62>TODAY(),"Pendiente","Sin dato"),IF(A62>TODAY(),"Fecha futura",IF(OR(A62=DATE(2026,1,30),A62=DATE(2026,2,27),A62=DATE(2026,3,31),A62=DATE(2026,4,30),A62=DATE(2026,5,29),A62=DATE(2026,6,30)),"Histórico",IF(WEEKDAY(A62,2)>5,"Fin semana","Registrado")))) -> Sin dato
A63: 46080 | B63: =Evolucion!B20 -> 76422 | C63: =IF(B63="",IF(A63>TODAY(),"Pendiente","Sin dato"),IF(A63>TODAY(),"Fecha futura",IF(OR(A63=DATE(2026,1,30),A63=DATE(2026,2,27),A63=DATE(2026,3,31),A63=DATE(2026,4,30),A63=DATE(2026,5,29),A63=DATE(2026,6,30)),"Histórico",IF(WEEKDAY(A63,2)>5,"Fin semana","Registrado")))) -> Histórico
A64: 46081 | C64: =IF(B64="",IF(A64>TODAY(),"Pendiente","Sin dato"),IF(A64>TODAY(),"Fecha futura",IF(OR(A64=DATE(2026,1,30),A64=DATE(2026,2,27),A64=DATE(2026,3,31),A64=DATE(2026,4,30),A64=DATE(2026,5,29),A64=DATE(2026,6,30)),"Histórico",IF(WEEKDAY(A64,2)>5,"Fin semana","Registrado")))) -> Sin dato
A65: 46082 | C65: =IF(B65="",IF(A65>TODAY(),"Pendiente","Sin dato"),IF(A65>TODAY(),"Fecha futura",IF(OR(A65=DATE(2026,1,30),A65=DATE(2026,2,27),A65=DATE(2026,3,31),A65=DATE(2026,4,30),A65=DATE(2026,5,29),A65=DATE(2026,6,30)),"Histórico",IF(WEEKDAY(A65,2)>5,"Fin semana","Registrado")))) -> Sin dato
A66: 46083 | C66: =IF(B66="",IF(A66>TODAY(),"Pendiente","Sin dato"),IF(A66>TODAY(),"Fecha futura",IF(OR(A66=DATE(2026,1,30),A66=DATE(2026,2,27),A66=DATE(2026,3,31),A66=DATE(2026,4,30),A66=DATE(2026,5,29),A66=DATE(2026,6,30)),"Histórico",IF(WEEKDAY(A66,2)>5,"Fin semana","Registrado")))) -> Sin dato
A67: 46084 | C67: =IF(B67="",IF(A67>TODAY(),"Pendiente","Sin dato"),IF(A67>TODAY(),"Fecha futura",IF(OR(A67=DATE(2026,1,30),A67=DATE(2026,2,27),A67=DATE(2026,3,31),A67=DATE(2026,4,30),A67=DATE(2026,5,29),A67=DATE(2026,6,30)),"Histórico",IF(WEEKDAY(A67,2)>5,"Fin semana","Registrado")))) -> Sin dato
A68: 46085 | C68: =IF(B68="",IF(A68>TODAY(),"Pendiente","Sin dato"),IF(A68>TODAY(),"Fecha futura",IF(OR(A68=DATE(2026,1,30),A68=DATE(2026,2,27),A68=DATE(2026,3,31),A68=DATE(2026,4,30),A68=DATE(2026,5,29),A68=DATE(2026,6,30)),"Histórico",IF(WEEKDAY(A68,2)>5,"Fin semana","Registrado")))) -> Sin dato
A69: 46086 | C69: =IF(B69="",IF(A69>TODAY(),"Pendiente","Sin dato"),IF(A69>TODAY(),"Fecha futura",IF(OR(A69=DATE(2026,1,30),A69=DATE(2026,2,27),A69=DATE(2026,3,31),A69=DATE(2026,4,30),A69=DATE(2026,5,29),A69=DATE(2026,6,30)),"Histórico",IF(WEEKDAY(A69,2)>5,"Fin semana","Registrado")))) -> Sin dato
A70: 46087 | C70: =IF(B70="",IF(A70>TODAY(),"Pendiente","Sin dato"),IF(A70>TODAY(),"Fecha futura",IF(OR(A70=DATE(2026,1,30),A70=DATE(2026,2,27),A70=DATE(2026,3,31),A70=DATE(2026,4,30),A70=DATE(2026,5,29),A70=DATE(2026,6,30)),"Histórico",IF(WEEKDAY(A70,2)>5,"Fin semana","Registrado")))) -> Sin dato
A71: 46088 | C71: =IF(B71="",IF(A71>TODAY(),"Pendiente","Sin dato"),IF(A71>TODAY(),"Fecha futura",IF(OR(A71=DATE(2026,1,30),A71=DATE(2026,2,27),A71=DATE(2026,3,31),A71=DATE(2026,4,30),A71=DATE(2026,5,29),A71=DATE(2026,6,30)),"Histórico",IF(WEEKDAY(A71,2)>5,"Fin semana","Registrado")))) -> Sin dato
A72: 46089 | C72: =IF(B72="",IF(A72>TODAY(),"Pendiente","Sin dato"),IF(A72>TODAY(),"Fecha futura",IF(OR(A72=DATE(2026,1,30),A72=DATE(2026,2,27),A72=DATE(2026,3,31),A72=DATE(2026,4,30),A72=DATE(2026,5,29),A72=DATE(2026,6,30)),"Histórico",IF(WEEKDAY(A72,2)>5,"Fin semana","Registrado")))) -> Sin dato
A73: 46090 | C73: =IF(B73="",IF(A73>TODAY(),"Pendiente","Sin dato"),IF(A73>TODAY(),"Fecha futura",IF(OR(A73=DATE(2026,1,30),A73=DATE(2026,2,27),A73=DATE(2026,3,31),A73=DATE(2026,4,30),A73=DATE(2026,5,29),A73=DATE(2026,6,30)),"Histórico",IF(WEEKDAY(A73,2)>5,"Fin semana","Registrado")))) -> Sin dato
A74: 46091 | C74: =IF(B74="",IF(A74>TODAY(),"Pendiente","Sin dato"),IF(A74>TODAY(),"Fecha futura",IF(OR(A74=DATE(2026,1,30),A74=DATE(2026,2,27),A74=DATE(2026,3,31),A74=DATE(2026,4,30),A74=DATE(2026,5,29),A74=DATE(2026,6,30)),"Histórico",IF(WEEKDAY(A74,2)>5,"Fin semana","Registrado")))) -> Sin dato
A75: 46092 | C75: =IF(B75="",IF(A75>TODAY(),"Pendiente","Sin dato"),IF(A75>TODAY(),"Fecha futura",IF(OR(A75=DATE(2026,1,30),A75=DATE(2026,2,27),A75=DATE(2026,3,31),A75=DATE(2026,4,30),A75=DATE(2026,5,29),A75=DATE(2026,6,30)),"Histórico",IF(WEEKDAY(A75,2)>5,"Fin semana","Registrado")))) -> Sin dato
... A94: 46111 | C94: =IF(B94="",IF(A94>TODAY(),"Pendiente","Sin dato"),IF(A94>TODAY(),"Fecha futura",IF(OR(A94=DATE(2026,1,30),A94=DATE(2026,2,27),A94=DATE(2026,3,31),A94=DATE(2026,4,30),A94=DATE(2026,5,29),A94=DATE(2026,6,30)),"Histórico",IF(WEEKDAY(A94,2)>5,"Fin semana","Registrado")))) -> Sin dato
A95: 46112 | B95: =Evolucion!B21 -> 72950 | C95: =IF(B95="",IF(A95>TODAY(),"Pendiente","Sin dato"),IF(A95>TODAY(),"Fecha futura",IF(OR(A95=DATE(2026,1,30),A95=DATE(2026,2,27),A95=DATE(2026,3,31),A95=DATE(2026,4,30),A95=DATE(2026,5,29),A95=DATE(2026,6,30)),"Histórico",IF(WEEKDAY(A95,2)>5,"Fin semana","Registrado")))) -> Histórico
A96: 46113 | C96: =IF(B96="",IF(A96>TODAY(),"Pendiente","Sin dato"),IF(A96>TODAY(),"Fecha futura",IF(OR(A96=DATE(2026,1,30),A96=DATE(2026,2,27),A96=DATE(2026,3,31),A96=DATE(2026,4,30),A96=DATE(2026,5,29),A96=DATE(2026,6,30)),"Histórico",IF(WEEKDAY(A96,2)>5,"Fin semana","Registrado")))) -> Sin dato
A97: 46114 | C97: =IF(B97="",IF(A97>TODAY(),"Pendiente","Sin dato"),IF(A97>TODAY(),"Fecha futura",IF(OR(A97=DATE(2026,1,30),A97=DATE(2026,2,27),A97=DATE(2026,3,31),A97=DATE(2026,4,30),A97=DATE(2026,5,29),A97=DATE(2026,6,30)),"Histórico",IF(WEEKDAY(A97,2)>5,"Fin semana","Registrado")))) -> Sin dato
A98: 46115 | C98: =IF(B98="",IF(A98>TODAY(),"Pendiente","Sin dato"),IF(A98>TODAY(),"Fecha futura",IF(OR(A98=DATE(2026,1,30),A98=DATE(2026,2,27),A98=DATE(2026,3,31),A98=DATE(2026,4,30),A98=DATE(2026,5,29),A98=DATE(2026,6,30)),"Histórico",IF(WEEKDAY(A98,2)>5,"Fin semana","Registrado")))) -> Sin dato
A99: 46116 | C99: =IF(B99="",IF(A99>TODAY(),"Pendiente","Sin dato"),IF(A99>TODAY(),"Fecha futura",IF(OR(A99=DATE(2026,1,30),A99=DATE(2026,2,27),A99=DATE(2026,3,31),A99=DATE(2026,4,30),A99=DATE(2026,5,29),A99=DATE(2026,6,30)),"Histórico",IF(WEEKDAY(A99,2)>5,"Fin semana","Registrado")))) -> Sin dato
A100: 46117 | C100: =IF(B100="",IF(A100>TODAY(),"Pendiente","Sin dato"),IF(A100>TODAY(),"Fecha futura",IF(OR(A100=DATE(2026,1,30),A100=DATE(2026,2,27),A100=DATE(2026,3,31),A100=DATE(2026,4,30),A100=DATE(2026,5,29),A100=DATE(2026,6,30)),"Histórico",IF(WEEKDAY(A100,2)>5,"Fin semana","Registrado")))) -> Sin dato
A101: 46118 | C101: =IF(B101="",IF(A101>TODAY(),"Pendiente","Sin dato"),IF(A101>TODAY(),"Fecha futura",IF(OR(A101=DATE(2026,1,30),A101=DATE(2026,2,27),A101=DATE(2026,3,31),A101=DATE(2026,4,30),A101=DATE(2026,5,29),A101=DATE(2026,6,30)),"Histórico",IF(WEEKDAY(A101,2)>5,"Fin semana","Registrado")))) -> Sin dato
A102: 46119 | C102: =IF(B102="",IF(A102>TODAY(),"Pendiente","Sin dato"),IF(A102>TODAY(),"Fecha futura",IF(OR(A102=DATE(2026,1,30),A102=DATE(2026,2,27),A102=DATE(2026,3,31),A102=DATE(2026,4,30),A102=DATE(2026,5,29),A102=DATE(2026,6,30)),"Histórico",IF(WEEKDAY(A102,2)>5,"Fin semana","Registrado")))) -> Sin dato
A103: 46120 | C103: =IF(B103="",IF(A103>TODAY(),"Pendiente","Sin dato"),IF(A103>TODAY(),"Fecha futura",IF(OR(A103=DATE(2026,1,30),A103=DATE(2026,2,27),A103=DATE(2026,3,31),A103=DATE(2026,4,30),A103=DATE(2026,5,29),A103=DATE(2026,6,30)),"Histórico",IF(WEEKDAY(A103,2)>5,"Fin semana","Registrado")))) -> Sin dato
A104: 46121 | C104: =IF(B104="",IF(A104>TODAY(),"Pendiente","Sin dato"),IF(A104>TODAY(),"Fecha futura",IF(OR(A104=DATE(2026,1,30),A104=DATE(2026,2,27),A104=DATE(2026,3,31),A104=DATE(2026,4,30),A104=DATE(2026,5,29),A104=DATE(2026,6,30)),"Histórico",IF(WEEKDAY(A104,2)>5,"Fin semana","Registrado")))) -> Sin dato
A105: 46122 | C105: =IF(B105="",IF(A105>TODAY(),"Pendiente","Sin dato"),IF(A105>TODAY(),"Fecha futura",IF(OR(A105=DATE(2026,1,30),A105=DATE(2026,2,27),A105=DATE(2026,3,31),A105=DATE(2026,4,30),A105=DATE(2026,5,29),A105=DATE(2026,6,30)),"Histórico",IF(WEEKDAY(A105,2)>5,"Fin semana","Registrado")))) -> Sin dato
A106: 46123 | C106: =IF(B106="",IF(A106>TODAY(),"Pendiente","Sin dato"),IF(A106>TODAY(),"Fecha futura",IF(OR(A106=DATE(2026,1,30),A106=DATE(2026,2,27),A106=DATE(2026,3,31),A106=DATE(2026,4,30),A106=DATE(2026,5,29),A106=DATE(2026,6,30)),"Histórico",IF(WEEKDAY(A106,2)>5,"Fin semana","Registrado")))) -> Sin dato
A107: 46124 | C107: =IF(B107="",IF(A107>TODAY(),"Pendiente","Sin dato"),IF(A107>TODAY(),"Fecha futura",IF(OR(A107=DATE(2026,1,30),A107=DATE(2026,2,27),A107=DATE(2026,3,31),A107=DATE(2026,4,30),A107=DATE(2026,5,29),A107=DATE(2026,6,30)),"Histórico",IF(WEEKDAY(A107,2)>5,"Fin semana","Registrado")))) -> Sin dato
... A124: 46141 | C124: =IF(B124="",IF(A124>TODAY(),"Pendiente","Sin dato"),IF(A124>TODAY(),"Fecha futura",IF(OR(A124=DATE(2026,1,30),A124=DATE(2026,2,27),A124=DATE(2026,3,31),A124=DATE(2026,4,30),A124=DATE(2026,5,29),A124=DATE(2026,6,30)),"Histórico",IF(WEEKDAY(A124,2)>5,"Fin semana","Registrado")))) -> Sin dato
A125: 46142 | B125: =Evolucion!B22 -> 76207 | C125: =IF(B125="",IF(A125>TODAY(),"Pendiente","Sin dato"),IF(A125>TODAY(),"Fecha futura",IF(OR(A125=DATE(2026,1,30),A125=DATE(2026,2,27),A125=DATE(2026,3,31),A125=DATE(2026,4,30),A125=DATE(2026,5,29),A125=DATE(2026,6,30)),"Histórico",IF(WEEKDAY(A125,2)>5,"Fin semana","Registrado")))) -> Histórico
A126: 46143 | C126: =IF(B126="",IF(A126>TODAY(),"Pendiente","Sin dato"),IF(A126>TODAY(),"Fecha futura",IF(OR(A126=DATE(2026,1,30),A126=DATE(2026,2,27),A126=DATE(2026,3,31),A126=DATE(2026,4,30),A126=DATE(2026,5,29),A126=DATE(2026,6,30)),"Histórico",IF(WEEKDAY(A126,2)>5,"Fin semana","Registrado")))) -> Sin dato
A127: 46144 | C127: =IF(B127="",IF(A127>TODAY(),"Pendiente","Sin dato"),IF(A127>TODAY(),"Fecha futura",IF(OR(A127=DATE(2026,1,30),A127=DATE(2026,2,27),A127=DATE(2026,3,31),A127=DATE(2026,4,30),A127=DATE(2026,5,29),A127=DATE(2026,6,30)),"Histórico",IF(WEEKDAY(A127,2)>5,"Fin semana","Registrado")))) -> Sin dato
A128: 46145 | C128: =IF(B128="",IF(A128>TODAY(),"Pendiente","Sin dato"),IF(A128>TODAY(),"Fecha futura",IF(OR(A128=DATE(2026,1,30),A128=DATE(2026,2,27),A128=DATE(2026,3,31),A128=DATE(2026,4,30),A128=DATE(2026,5,29),A128=DATE(2026,6,30)),"Histórico",IF(WEEKDAY(A128,2)>5,"Fin semana","Registrado")))) -> Sin dato
A129: 46146 | C129: =IF(B129="",IF(A129>TODAY(),"Pendiente","Sin dato"),IF(A129>TODAY(),"Fecha futura",IF(OR(A129=DATE(2026,1,30),A129=DATE(2026,2,27),A129=DATE(2026,3,31),A129=DATE(2026,4,30),A129=DATE(2026,5,29),A129=DATE(2026,6,30)),"Histórico",IF(WEEKDAY(A129,2)>5,"Fin semana","Registrado")))) -> Sin dato
A130: 46147 | C130: =IF(B130="",IF(A130>TODAY(),"Pendiente","Sin dato"),IF(A130>TODAY(),"Fecha futura",IF(OR(A130=DATE(2026,1,30),A130=DATE(2026,2,27),A130=DATE(2026,3,31),A130=DATE(2026,4,30),A130=DATE(2026,5,29),A130=DATE(2026,6,30)),"Histórico",IF(WEEKDAY(A130,2)>5,"Fin semana","Registrado")))) -> Sin dato
A131: 46148 | C131: =IF(B131="",IF(A131>TODAY(),"Pendiente","Sin dato"),IF(A131>TODAY(),"Fecha futura",IF(OR(A131=DATE(2026,1,30),A131=DATE(2026,2,27),A131=DATE(2026,3,31),A131=DATE(2026,4,30),A131=DATE(2026,5,29),A131=DATE(2026,6,30)),"Histórico",IF(WEEKDAY(A131,2)>5,"Fin semana","Registrado")))) -> Sin dato
A132: 46149 | C132: =IF(B132="",IF(A132>TODAY(),"Pendiente","Sin dato"),IF(A132>TODAY(),"Fecha futura",IF(OR(A132=DATE(2026,1,30),A132=DATE(2026,2,27),A132=DATE(2026,3,31),A132=DATE(2026,4,30),A132=DATE(2026,5,29),A132=DATE(2026,6,30)),"Histórico",IF(WEEKDAY(A132,2)>5,"Fin semana","Registrado")))) -> Sin dato
A133: 46150 | C133: =IF(B133="",IF(A133>TODAY(),"Pendiente","Sin dato"),IF(A133>TODAY(),"Fecha futura",IF(OR(A133=DATE(2026,1,30),A133=DATE(2026,2,27),A133=DATE(2026,3,31),A133=DATE(2026,4,30),A133=DATE(2026,5,29),A133=DATE(2026,6,30)),"Histórico",IF(WEEKDAY(A133,2)>5,"Fin semana","Registrado")))) -> Sin dato
A134: 46151 | C134: =IF(B134="",IF(A134>TODAY(),"Pendiente","Sin dato"),IF(A134>TODAY(),"Fecha futura",IF(OR(A134=DATE(2026,1,30),A134=DATE(2026,2,27),A134=DATE(2026,3,31),A134=DATE(2026,4,30),A134=DATE(2026,5,29),A134=DATE(2026,6,30)),"Histórico",IF(WEEKDAY(A134,2)>5,"Fin semana","Registrado")))) -> Sin dato
A135: 46152 | C135: =IF(B135="",IF(A135>TODAY(),"Pendiente","Sin dato"),IF(A135>TODAY(),"Fecha futura",IF(OR(A135=DATE(2026,1,30),A135=DATE(2026,2,27),A135=DATE(2026,3,31),A135=DATE(2026,4,30),A135=DATE(2026,5,29),A135=DATE(2026,6,30)),"Histórico",IF(WEEKDAY(A135,2)>5,"Fin semana","Registrado")))) -> Sin dato
A136: 46153 | C136: =IF(B136="",IF(A136>TODAY(),"Pendiente","Sin dato"),IF(A136>TODAY(),"Fecha futura",IF(OR(A136=DATE(2026,1,30),A136=DATE(2026,2,27),A136=DATE(2026,3,31),A136=DATE(2026,4,30),A136=DATE(2026,5,29),A136=DATE(2026,6,30)),"Histórico",IF(WEEKDAY(A136,2)>5,"Fin semana","Registrado")))) -> Sin dato
A137: 46154 | C137: =IF(B137="",IF(A137>TODAY(),"Pendiente","Sin dato"),IF(A137>TODAY(),"Fecha futura",IF(OR(A137=DATE(2026,1,30),A137=DATE(2026,2,27),A137=DATE(2026,3,31),A137=DATE(2026,4,30),A137=DATE(2026,5,29),A137=DATE(2026,6,30)),"Histórico",IF(WEEKDAY(A137,2)>5,"Fin semana","Registrado")))) -> Sin dato
... A153: 46170 | C153: =IF(B153="",IF(A153>TODAY(),"Pendiente","Sin dato"),IF(A153>TODAY(),"Fecha futura",IF(OR(A153=DATE(2026,1,30),A153=DATE(2026,2,27),A153=DATE(2026,3,31),A153=DATE(2026,4,30),A153=DATE(2026,5,29),A153=DATE(2026,6,30)),"Histórico",IF(WEEKDAY(A153,2)>5,"Fin semana","Registrado")))) -> Sin dato
A154: 46171 | B154: =Evolucion!B23 -> 79485 | C154: =IF(B154="",IF(A154>TODAY(),"Pendiente","Sin dato"),IF(A154>TODAY(),"Fecha futura",IF(OR(A154=DATE(2026,1,30),A154=DATE(2026,2,27),A154=DATE(2026,3,31),A154=DATE(2026,4,30),A154=DATE(2026,5,29),A154=DATE(2026,6,30)),"Histórico",IF(WEEKDAY(A154,2)>5,"Fin semana","Registrado")))) -> Histórico
A155: 46172 | C155: =IF(B155="",IF(A155>TODAY(),"Pendiente","Sin dato"),IF(A155>TODAY(),"Fecha futura",IF(OR(A155=DATE(2026,1,30),A155=DATE(2026,2,27),A155=DATE(2026,3,31),A155=DATE(2026,4,30),A155=DATE(2026,5,29),A155=DATE(2026,6,30)),"Histórico",IF(WEEKDAY(A155,2)>5,"Fin semana","Registrado")))) -> Sin dato
A156: 46173 | C156: =IF(B156="",IF(A156>TODAY(),"Pendiente","Sin dato"),IF(A156>TODAY(),"Fecha futura",IF(OR(A156=DATE(2026,1,30),A156=DATE(2026,2,27),A156=DATE(2026,3,31),A156=DATE(2026,4,30),A156=DATE(2026,5,29),A156=DATE(2026,6,30)),"Histórico",IF(WEEKDAY(A156,2)>5,"Fin semana","Registrado")))) -> Sin dato
A157: 46174 | C157: =IF(B157="",IF(A157>TODAY(),"Pendiente","Sin dato"),IF(A157>TODAY(),"Fecha futura",IF(OR(A157=DATE(2026,1,30),A157=DATE(2026,2,27),A157=DATE(2026,3,31),A157=DATE(2026,4,30),A157=DATE(2026,5,29),A157=DATE(2026,6,30)),"Histórico",IF(WEEKDAY(A157,2)>5,"Fin semana","Registrado")))) -> Sin dato
A158: 46175 | C158: =IF(B158="",IF(A158>TODAY(),"Pendiente","Sin dato"),IF(A158>TODAY(),"Fecha futura",IF(OR(A158=DATE(2026,1,30),A158=DATE(2026,2,27),A158=DATE(2026,3,31),A158=DATE(2026,4,30),A158=DATE(2026,5,29),A158=DATE(2026,6,30)),"Histórico",IF(WEEKDAY(A158,2)>5,"Fin semana","Registrado")))) -> Sin dato
A159: 46176 | C159: =IF(B159="",IF(A159>TODAY(),"Pendiente","Sin dato"),IF(A159>TODAY(),"Fecha futura",IF(OR(A159=DATE(2026,1,30),A159=DATE(2026,2,27),A159=DATE(2026,3,31),A159=DATE(2026,4,30),A159=DATE(2026,5,29),A159=DATE(2026,6,30)),"Histórico",IF(WEEKDAY(A159,2)>5,"Fin semana","Registrado")))) -> Sin dato
A160: 46177 | C160: =IF(B160="",IF(A160>TODAY(),"Pendiente","Sin dato"),IF(A160>TODAY(),"Fecha futura",IF(OR(A160=DATE(2026,1,30),A160=DATE(2026,2,27),A160=DATE(2026,3,31),A160=DATE(2026,4,30),A160=DATE(2026,5,29),A160=DATE(2026,6,30)),"Histórico",IF(WEEKDAY(A160,2)>5,"Fin semana","Registrado")))) -> Sin dato
A161: 46178 | C161: =IF(B161="",IF(A161>TODAY(),"Pendiente","Sin dato"),IF(A161>TODAY(),"Fecha futura",IF(OR(A161=DATE(2026,1,30),A161=DATE(2026,2,27),A161=DATE(2026,3,31),A161=DATE(2026,4,30),A161=DATE(2026,5,29),A161=DATE(2026,6,30)),"Histórico",IF(WEEKDAY(A161,2)>5,"Fin semana","Registrado")))) -> Sin dato
A162: 46179 | C162: =IF(B162="",IF(A162>TODAY(),"Pendiente","Sin dato"),IF(A162>TODAY(),"Fecha futura",IF(OR(A162=DATE(2026,1,30),A162=DATE(2026,2,27),A162=DATE(2026,3,31),A162=DATE(2026,4,30),A162=DATE(2026,5,29),A162=DATE(2026,6,30)),"Histórico",IF(WEEKDAY(A162,2)>5,"Fin semana","Registrado")))) -> Sin dato
A163: 46180 | C163: =IF(B163="",IF(A163>TODAY(),"Pendiente","Sin dato"),IF(A163>TODAY(),"Fecha futura",IF(OR(A163=DATE(2026,1,30),A163=DATE(2026,2,27),A163=DATE(2026,3,31),A163=DATE(2026,4,30),A163=DATE(2026,5,29),A163=DATE(2026,6,30)),"Histórico",IF(WEEKDAY(A163,2)>5,"Fin semana","Registrado")))) -> Sin dato
A164: 46181 | C164: =IF(B164="",IF(A164>TODAY(),"Pendiente","Sin dato"),IF(A164>TODAY(),"Fecha futura",IF(OR(A164=DATE(2026,1,30),A164=DATE(2026,2,27),A164=DATE(2026,3,31),A164=DATE(2026,4,30),A164=DATE(2026,5,29),A164=DATE(2026,6,30)),"Histórico",IF(WEEKDAY(A164,2)>5,"Fin semana","Registrado")))) -> Sin dato
A165: 46182 | C165: =IF(B165="",IF(A165>TODAY(),"Pendiente","Sin dato"),IF(A165>TODAY(),"Fecha futura",IF(OR(A165=DATE(2026,1,30),A165=DATE(2026,2,27),A165=DATE(2026,3,31),A165=DATE(2026,4,30),A165=DATE(2026,5,29),A165=DATE(2026,6,30)),"Histórico",IF(WEEKDAY(A165,2)>5,"Fin semana","Registrado")))) -> Sin dato
A166: 46183 | C166: =IF(B166="",IF(A166>TODAY(),"Pendiente","Sin dato"),IF(A166>TODAY(),"Fecha futura",IF(OR(A166=DATE(2026,1,30),A166=DATE(2026,2,27),A166=DATE(2026,3,31),A166=DATE(2026,4,30),A166=DATE(2026,5,29),A166=DATE(2026,6,30)),"Histórico",IF(WEEKDAY(A166,2)>5,"Fin semana","Registrado")))) -> Sin dato
... A185: 46202 | C185: =IF(B185="",IF(A185>TODAY(),"Pendiente","Sin dato"),IF(A185>TODAY(),"Fecha futura",IF(OR(A185=DATE(2026,1,30),A185=DATE(2026,2,27),A185=DATE(2026,3,31),A185=DATE(2026,4,30),A185=DATE(2026,5,29),A185=DATE(2026,6,30)),"Histórico",IF(WEEKDAY(A185,2)>5,"Fin semana","Registrado")))) -> Sin dato
A186: 46203 | B186: =Evolucion!B24 -> 76115 | C186: =IF(B186="",IF(A186>TODAY(),"Pendiente","Sin dato"),IF(A186>TODAY(),"Fecha futura",IF(OR(A186=DATE(2026,1,30),A186=DATE(2026,2,27),A186=DATE(2026,3,31),A186=DATE(2026,4,30),A186=DATE(2026,5,29),A186=DATE(2026,6,30)),"Histórico",IF(WEEKDAY(A186,2)>5,"Fin semana","Registrado")))) -> Histórico
A187: 46204 | C187: =IF(B187="",IF(A187>TODAY(),"Pendiente","Sin dato"),IF(A187>TODAY(),"Fecha futura",IF(OR(A187=DATE(2026,1,30),A187=DATE(2026,2,27),A187=DATE(2026,3,31),A187=DATE(2026,4,30),A187=DATE(2026,5,29),A187=DATE(2026,6,30)),"Histórico",IF(WEEKDAY(A187,2)>5,"Fin semana","Registrado")))) -> Sin dato
A188: 46205 | C188: =IF(B188="",IF(A188>TODAY(),"Pendiente","Sin dato"),IF(A188>TODAY(),"Fecha futura",IF(OR(A188=DATE(2026,1,30),A188=DATE(2026,2,27),A188=DATE(2026,3,31),A188=DATE(2026,4,30),A188=DATE(2026,5,29),A188=DATE(2026,6,30)),"Histórico",IF(WEEKDAY(A188,2)>5,"Fin semana","Registrado")))) -> Sin dato
A189: 46206 | C189: =IF(B189="",IF(A189>TODAY(),"Pendiente","Sin dato"),IF(A189>TODAY(),"Fecha futura",IF(OR(A189=DATE(2026,1,30),A189=DATE(2026,2,27),A189=DATE(2026,3,31),A189=DATE(2026,4,30),A189=DATE(2026,5,29),A189=DATE(2026,6,30)),"Histórico",IF(WEEKDAY(A189,2)>5,"Fin semana","Registrado")))) -> Sin dato
A190: 46207 | C190: =IF(B190="",IF(A190>TODAY(),"Pendiente","Sin dato"),IF(A190>TODAY(),"Fecha futura",IF(OR(A190=DATE(2026,1,30),A190=DATE(2026,2,27),A190=DATE(2026,3,31),A190=DATE(2026,4,30),A190=DATE(2026,5,29),A190=DATE(2026,6,30)),"Histórico",IF(WEEKDAY(A190,2)>5,"Fin semana","Registrado")))) -> Sin dato
A191: 46208 | C191: =IF(B191="",IF(A191>TODAY(),"Pendiente","Sin dato"),IF(A191>TODAY(),"Fecha futura",IF(OR(A191=DATE(2026,1,30),A191=DATE(2026,2,27),A191=DATE(2026,3,31),A191=DATE(2026,4,30),A191=DATE(2026,5,29),A191=DATE(2026,6,30)),"Histórico",IF(WEEKDAY(A191,2)>5,"Fin semana","Registrado")))) -> Sin dato
A192: 46209 | C192: =IF(B192="",IF(A192>TODAY(),"Pendiente","Sin dato"),IF(A192>TODAY(),"Fecha futura",IF(OR(A192=DATE(2026,1,30),A192=DATE(2026,2,27),A192=DATE(2026,3,31),A192=DATE(2026,4,30),A192=DATE(2026,5,29),A192=DATE(2026,6,30)),"Histórico",IF(WEEKDAY(A192,2)>5,"Fin semana","Registrado")))) -> Sin dato
A193: 46210 | C193: =IF(B193="",IF(A193>TODAY(),"Pendiente","Sin dato"),IF(A193>TODAY(),"Fecha futura",IF(OR(A193=DATE(2026,1,30),A193=DATE(2026,2,27),A193=DATE(2026,3,31),A193=DATE(2026,4,30),A193=DATE(2026,5,29),A193=DATE(2026,6,30)),"Histórico",IF(WEEKDAY(A193,2)>5,"Fin semana","Registrado")))) -> Sin dato
A194: 46211 | C194: =IF(B194="",IF(A194>TODAY(),"Pendiente","Sin dato"),IF(A194>TODAY(),"Fecha futura",IF(OR(A194=DATE(2026,1,30),A194=DATE(2026,2,27),A194=DATE(2026,3,31),A194=DATE(2026,4,30),A194=DATE(2026,5,29),A194=DATE(2026,6,30)),"Histórico",IF(WEEKDAY(A194,2)>5,"Fin semana","Registrado")))) -> Sin dato
A195: 46212 | B195: 77695 | C195: =IF(B195="",IF(A195>TODAY(),"Pendiente","Sin dato"),IF(A195>TODAY(),"Fecha futura",IF(OR(A195=DATE(2026,1,30),A195=DATE(2026,2,27),A195=DATE(2026,3,31),A195=DATE(2026,4,30),A195=DATE(2026,5,29),A195=DATE(2026,6,30)),"Histórico",IF(WEEKDAY(A195,2)>5,"Fin semana","Registrado")))) -> Registrado
A196: 46213 | B196: 77600 | C196: =IF(B196="",IF(A196>TODAY(),"Pendiente","Sin dato"),IF(A196>TODAY(),"Fecha futura",IF(OR(A196=DATE(2026,1,30),A196=DATE(2026,2,27),A196=DATE(2026,3,31),A196=DATE(2026,4,30),A196=DATE(2026,5,29),A196=DATE(2026,6,30)),"Histórico",IF(WEEKDAY(A196,2)>5,"Fin semana","Registrado")))) -> Registrado
A197: 46214 | B197: 77711 | C197: =IF(B197="",IF(A197>TODAY(),"Pendiente","Sin dato"),IF(A197>TODAY(),"Fecha futura",IF(OR(A197=DATE(2026,1,30),A197=DATE(2026,2,27),A197=DATE(2026,3,31),A197=DATE(2026,4,30),A197=DATE(2026,5,29),A197=DATE(2026,6,30)),"Histórico",IF(WEEKDAY(A197,2)>5,"Fin semana","Registrado")))) -> Fin semana
...

Sheet Movimientos
A1: MOVIMIENTOS
A2: Datos ficticios: una sola entrada por movimiento.
A3: Fecha real o mes AAAA-MM; ingresos +, retiradas −.
A4: Histórico mensual: sustituye el total al detallar sus fechas.
A5: Fecha / mes | B5: Importe € | C5: Concepto | D5: Fecha contable | E5: Fecha exacta
A6: 45716 | B6: 700 | C6: Aportación demo | D6: =IF(A6="","",A6) -> 45716 | E6: =IF(A6="","",ISNUMBER(A6)) -> TRUE
A7: 45747 | B7: 700 | C7: Aportación demo | D7: =IF(A7="","",A7) -> 45747 | E7: =IF(A7="","",ISNUMBER(A7)) -> TRUE
A8: 45777 | B8: 700 | C8: Aportación demo | D8: =IF(A8="","",A8) -> 45777 | E8: =IF(A8="","",ISNUMBER(A8)) -> TRUE
A9: 45807 | B9: 700 | C9: Aportación demo | D9: =IF(A9="","",A9) -> 45807 | E9: =IF(A9="","",ISNUMBER(A9)) -> TRUE
A10: 45838 | B10: 700 | C10: Aportación demo | D10: =IF(A10="","",A10) -> 45838 | E10: =IF(A10="","",ISNUMBER(A10)) -> TRUE
A11: 45869 | B11: 700 | C11: Aportación demo | D11: =IF(A11="","",A11) -> 45869 | E11: =IF(A11="","",ISNUMBER(A11)) -> TRUE
A12: 45898 | B12: 700 | C12: Aportación demo | D12: =IF(A12="","",A12) -> 45898 | E12: =IF(A12="","",ISNUMBER(A12)) -> TRUE
A13: 45930 | B13: 700 | C13: Aportación demo | D13: =IF(A13="","",A13) -> 45930 | E13: =IF(A13="","",ISNUMBER(A13)) -> TRUE
A14: 45961 | B14: 700 | C14: Aportación demo | D14: =IF(A14="","",A14) -> 45961 | E14: =IF(A14="","",ISNUMBER(A14)) -> TRUE
A15: 45989 | B15: 700 | C15: Aportación demo | D15: =IF(A15="","",A15) -> 45989 | E15: =IF(A15="","",ISNUMBER(A15)) -> TRUE
A16: 46022 | B16: 700 | C16: Aportación demo | D16: =IF(A16="","",A16) -> 46022 | E16: =IF(A16="","",ISNUMBER(A16)) -> TRUE
A17: 46052 | B17: 500 | C17: Aportación demo | D17: =IF(A17="","",A17) -> 46052 | E17: =IF(A17="","",ISNUMBER(A17)) -> TRUE
... A24: 46260 | B24: 1508 | C24: Aportación demo | D24: =IF(A24="","",A24) -> 46260 | E24: =IF(A24="","",ISNUMBER(A24)) -> TRUE
D25: =IF(A25="","",IF(ISNUMBER(A25),A25,IFERROR(DATE(VALUE(LEFT(A25,4)),VALUE(RIGHT(A25,2)),1),""))) | E25: =IF(A25="","",ISNUMBER(A25))
D26: =IF(A26="","",IF(ISNUMBER(A26),A26,IFERROR(DATE(VALUE(LEFT(A26,4)),VALUE(RIGHT(A26,2)),1),""))) | E26: =IF(A26="","",ISNUMBER(A26))
D27: =IF(A27="","",IF(ISNUMBER(A27),A27,IFERROR(DATE(VALUE(LEFT(A27,4)),VALUE(RIGHT(A27,2)),1),""))) | E27: =IF(A27="","",ISNUMBER(A27))
D28: =IF(A28="","",IF(ISNUMBER(A28),A28,IFERROR(DATE(VALUE(LEFT(A28,4)),VALUE(RIGHT(A28,2)),1),""))) | E28: =IF(A28="","",ISNUMBER(A28))
D29: =IF(A29="","",IF(ISNUMBER(A29),A29,IFERROR(DATE(VALUE(LEFT(A29,4)),VALUE(RIGHT(A29,2)),1),""))) | E29: =IF(A29="","",ISNUMBER(A29))
D30: =IF(A30="","",IF(ISNUMBER(A30),A30,IFERROR(DATE(VALUE(LEFT(A30,4)),VALUE(RIGHT(A30,2)),1),""))) | E30: =IF(A30="","",ISNUMBER(A30))
D31: =IF(A31="","",IF(ISNUMBER(A31),A31,IFERROR(DATE(VALUE(LEFT(A31,4)),VALUE(RIGHT(A31,2)),1),""))) | E31: =IF(A31="","",ISNUMBER(A31))
D32: =IF(A32="","",IF(ISNUMBER(A32),A32,IFERROR(DATE(VALUE(LEFT(A32,4)),VALUE(RIGHT(A32,2)),1),""))) | E32: =IF(A32="","",ISNUMBER(A32))
D33: =IF(A33="","",IF(ISNUMBER(A33),A33,IFERROR(DATE(VALUE(LEFT(A33,4)),VALUE(RIGHT(A33,2)),1),""))) | E33: =IF(A33="","",ISNUMBER(A33))
D34: =IF(A34="","",IF(ISNUMBER(A34),A34,IFERROR(DATE(VALUE(LEFT(A34,4)),VALUE(RIGHT(A34,2)),1),""))) | E34: =IF(A34="","",ISNUMBER(A34))
D35: =IF(A35="","",IF(ISNUMBER(A35),A35,IFERROR(DATE(VALUE(LEFT(A35,4)),VALUE(RIGHT(A35,2)),1),""))) | E35: =IF(A35="","",ISNUMBER(A35))
D36: =IF(A36="","",IF(ISNUMBER(A36),A36,IFERROR(DATE(VALUE(LEFT(A36,4)),VALUE(RIGHT(A36,2)),1),""))) | E36: =IF(A36="","",ISNUMBER(A36))
... D505: =IF(A505="","",IF(ISNUMBER(A505),A505,IFERROR(DATE(VALUE(LEFT(A505,4)),VALUE(RIGHT(A505,2)),1),""))) | E505: =IF(A505="","",ISNUMBER(A505))

Sheet Comparativa
A1: Año | B1: Mes | C1: Periodo | D1: Rentabilidad Cartera (%) | E1: Rentabilidad MSCI World (%) | F1: Cartera Acum (%) | G1: MSCI Acum (%)
A2: 2025 | B2: Feb | C2: =A2&" "&B2 -> 2025 Feb | D2: =IF(OR(Evolucion!B3="",(Evolucion!C3+IF(Evolucion!D3="",0,Evolucion!D3))=0),"",TRUNC((Evolucion!B3-(Evolucion!C3+IF(Evolucion!D3="",0,Evolucion!D3)))/(Evolucion!C3+IF(Evolucion!D3="",0,Evolucion!D3))*100,3)) -> 0 | E2: 0 | F2: =IF(D2="","",D2) -> 0 | G2: =IF(E2="","",E2) -> 0
A3: 2025 | B3: Mar | C3: =A3&" "&B3 -> 2025 Mar | D3: =IF(Evolucion!F4="","",Evolucion!F4) -> 3.8357366 | E3: -6.97 | F3: =IF(D3="","",IF(F2="",D3,((1+F2/100)*(1+D3/100)-1)*100)) -> 3.8357366 | G3: =IF(E3="","",IF(G2="",E3,((1+G2/100)*(1+E3/100)-1)*100)) -> -6.97
A4: 2025 | B4: Abr | C4: =A4&" "&B4 -> 2025 Abr | D4: =IF(Evolucion!F5="","",Evolucion!F5) -> 2.1654364 | E4: -4.12 | F4: =IF(D4="","",IF(F3="",D4,((1+F3/100)*(1+D4/100)-1)*100)) -> 6.0842335 | G4: =IF(E4="","",IF(G3="",E4,((1+G3/100)*(1+E4/100)-1)*100)) -> -10.802836
A5: 2025 | B5: May | C5: =A5&" "&B5 -> 2025 May | D5: =IF(Evolucion!F6="","",Evolucion!F6) -> 2.2706153 | E5: 6.07 | F5: =IF(D5="","",IF(F4="",D5,((1+F4/100)*(1+D5/100)-1)*100)) -> 8.4929983 | G5: =IF(E5="","",IF(G4="",E5,((1+G4/100)*(1+E5/100)-1)*100)) -> -5.3885681
A6: 2025 | B6: Jun | C6: =A6&" "&B6 -> 2025 Jun | D6: =IF(Evolucion!F7="","",Evolucion!F7) -> 1.1130311 | E6: 0.88 | F6: =IF(D6="","",IF(F5="",D6,((1+F5/100)*(1+D6/100)-1)*100)) -> 9.7005591 | G6: =IF(E6="","",IF(G5="",E6,((1+G5/100)*(1+E6/100)-1)*100)) -> -4.5559875
A7: 2025 | B7: Jul | C7: =A7&" "&B7 -> 2025 Jul | D7: =IF(Evolucion!F8="","",Evolucion!F8) -> 1.4954045 | E7: 3.86 | F7: =IF(D7="","",IF(F6="",D7,((1+F6/100)*(1+D7/100)-1)*100)) -> 11.341026 | G7: =IF(E7="","",IF(G6="",E7,((1+G6/100)*(1+E7/100)-1)*100)) -> -0.87184866
A8: 2025 | B8: Ago | C8: =A8&" "&B8 -> 2025 Ago | D8: =IF(Evolucion!F9="","",Evolucion!F9) -> 0.80015487 | E8: 0.32 | F8: =IF(D8="","",IF(F7="",D8,((1+F7/100)*(1+D8/100)-1)*100)) -> 12.231927 | G8: =IF(E8="","",IF(G7="",E8,((1+G7/100)*(1+E8/100)-1)*100)) -> -0.55463858
A9: 2025 | B9: Sep | C9: =A9&" "&B9 -> 2025 Sep | D9: =IF(Evolucion!F10="","",Evolucion!F10) -> 5.199101 | E9: 2.81 | F9: =IF(D9="","",IF(F8="",D9,((1+F8/100)*(1+D9/100)-1)*100)) -> 18.066978 | G9: =IF(E9="","",IF(G8="",E9,((1+G8/100)*(1+E9/100)-1)*100)) -> 2.2397761
A10: 2025 | B10: Oct | C10: =A10&" "&B10 -> 2025 Oct | D10: =IF(Evolucion!F11="","",Evolucion!F11) -> 2.8539951 | E10: 3.83 | F10: =IF(D10="","",IF(F9="",D10,((1+F9/100)*(1+D10/100)-1)*100)) -> 21.436604 | G10: =IF(E10="","",IF(G9="",E10,((1+G9/100)*(1+E10/100)-1)*100)) -> 6.1555595
A11: 2025 | B11: Nov | C11: =A11&" "&B11 -> 2025 Nov | D11: =IF(Evolucion!F12="","",Evolucion!F12) -> -0.26796206 | E11: -0.27 | F11: =IF(D11="","",IF(F10="",D11,((1+F10/100)*(1+D11/100)-1)*100)) -> 21.1112 | G11: =IF(E11="","",IF(G10="",E11,((1+G10/100)*(1+E11/100)-1)*100)) -> 5.8689395
A12: 2025 | B12: Dic | C12: =A12&" "&B12 -> 2025 Dic | D12: =IF(Evolucion!F13="","",Evolucion!F13) -> 3.8535399 | E12: -0.4 | F12: =IF(D12="","",IF(F11="",D12,((1+F11/100)*(1+D12/100)-1)*100)) -> 25.778268 | G12: =IF(E12="","",IF(G11="",E12,((1+G11/100)*(1+E12/100)-1)*100)) -> 5.4454637
A13: 2026 | B13: Ene | C13: =A13&" "&B13 -> 2026 Ene | D13: =IF(Evolucion!F19="","",Evolucion!F19) -> 2.4312151 | E13: 0.92 | F13: =IF(D13="","",IF(F12="",D13,((1+F12/100)*(1+D13/100)-1)*100)) -> 28.836209 | G13: =IF(E13="","",IF(G12="",E13,((1+G12/100)*(1+E13/100)-1)*100)) -> 6.415562
A14: 2026 | B14: Feb | C14: =A14&" "&B14 -> 2026 Feb | D14: =IF(Evolucion!F20="","",Evolucion!F20) -> -0.36578947 | E14: 1.49 | F14: =IF(D14="","",IF(F13="",D14,((1+F13/100)*(1+D14/100)-1)*100)) -> 28.364939 | G14: =IF(E14="","",IF(G13="",E14,((1+G13/100)*(1+E14/100)-1)*100)) -> 8.0011539
A15: 2026 | B15: Mar | C15: =A15&" "&B15 -> 2026 Mar | D15: =IF(Evolucion!F21="","",Evolucion!F21) -> -5.3283086 | E15: -4.04 | F15: =IF(D15="","",IF(F14="",D15,((1+F14/100)*(1+D15/100)-1)*100)) -> 21.525259 | G15: =IF(E15="","",IF(G14="",E15,((1+G14/100)*(1+E15/100)-1)*100)) -> 3.6379073
A16: 2026 | B16: Abr | C16: =A16&" "&B16 -> 2026 Abr | D16: =IF(Evolucion!F22="","",Evolucion!F22) -> 5.4242632 | E16: 7.65 | F16: =IF(D16="","",IF(F15="",D16,((1+F15/100)*(1+D16/100)-1)*100)) -> 28.117109 | G16: =IF(E16="","",IF(G15="",E16,((1+G15/100)*(1+E16/100)-1)*100)) -> 11.566207
A17: 2026 | B17: May | C17: =A17&" "&B17 -> 2026 May | D17: =IF(Evolucion!F23="","",Evolucion!F23) -> 5.2199929 | E17: 5.1 | F17: =IF(D17="","",IF(F16="",D17,((1+F16/100)*(1+D17/100)-1)*100)) -> 34.804813 | G17: =IF(E17="","",IF(G16="",E17,((1+G16/100)*(1+E17/100)-1)*100)) -> 17.256084
A18: 2026 | B18: Jun | C18: =A18&" "&B18 -> 2026 Jun | D18: =IF(Evolucion!F24="","",Evolucion!F24) -> 0.088066931 | E18: 1.33 | F18: =IF(D18="","",IF(F17="",D18,((1+F17/100)*(1+D18/100)-1)*100)) -> 34.923532 | G18: =IF(E18="","",IF(G17="",E18,((1+G17/100)*(1+E18/100)-1)*100)) -> 18.81559
A19: 2026 | B19: Jul | C19: =A19&" "&B19 -> 2026 Jul | D19: =IF(Evolucion!F25="","",Evolucion!F25) -> 2.2952112 | E19: -0.14 | F19: =IF(D19="","",IF(F18="",D19,((1+F18/100)*(1+D19/100)-1)*100)) -> 38.020312 | G19: =IF(E19="","",IF(G18="",E19,((1+G18/100)*(1+E19/100)-1)*100)) -> 18.649248
A20: 2026 | B20: Ago | C20: =A20&" "&B20 -> 2026 Ago | D20: =IF(Evolucion!F26="","",Evolucion!F26) -> 1.6014405 | E20: 1.59 | F20: =IF(D20="","",IF(F19="",D20,((1+F19/100)*(1+D20/100)-1)*100)) -> 40.230625 | G20: =IF(E20="","",IF(G19="",E20,((1+G19/100)*(1+E20/100)-1)*100)) -> 20.535771
A21: 2026 | B21: Sep | C21: =A21&" "&B21 -> 2026 Sep | D21: =IF(Evolucion!F27="","",Evolucion!F27) -> -1.5291825 | E21: -0.82 | F21: =IF(D21="","",IF(F20="",D21,((1+F20/100)*(1+D21/100)-1)*100)) -> 38.086242 | G21: =IF(E21="","",IF(G20="",E21,((1+G20/100)*(1+E21/100)-1)*100)) -> 19.547378
A22: 2026 | B22: Oct | C22: =A22&" "&B22 -> 2026 Oct | D22: =IF(Evolucion!F28="","",Evolucion!F28) | F22: =IF(D22="","",IF(F21="",D22,((1+F21/100)*(1+D22/100)-1)*100)) | G22: =IF(E22="","",IF(G21="",E22,((1+G21/100)*(1+E22/100)-1)*100))
A23: 2026 | B23: Nov | C23: =A23&" "&B23 -> 2026 Nov | D23: =IF(Evolucion!F29="","",Evolucion!F29) | F23: =IF(D23="","",IF(F22="",D23,((1+F22/100)*(1+D23/100)-1)*100)) | G23: =IF(E23="","",IF(G22="",E23,((1+G22/100)*(1+E23/100)-1)*100))
A24: 2026 | B24: Dic | C24: =A24&" "&B24 -> 2026 Dic | D24: =IF(Evolucion!F30="","",Evolucion!F30) | F24: =IF(D24="","",IF(F23="",D24,((1+F23/100)*(1+D24/100)-1)*100)) | G24: =IF(E24="","",IF(G23="",E24,((1+G23/100)*(1+E24/100)-1)*100))

Sheet Objetivos
A1: OBJETIVOS Y APORTACIONES
A2: Referencia inicial = pesos actuales; edita tus objetivos.
A3: Próxima aportación € | C3: 0
A4: Reparto proporcional al déficit, sin vender posiciones.
A5: Activo | B5: Actual | C5: Objetivo
A6: =Cartera!A2 -> ETF Global Desarrollado | B6: =Cartera!C2 -> 0.23422769 | C6: 0.24579613
A7: =Cartera!A3 -> ETF Mercados Emergentes | B7: =Cartera!C3 -> 0.081979692 | C7: 0.079079207
A8: =Cartera!A4 -> Fondo Asia Pacífico | B8: =Cartera!C4 -> 0.029278462 | C8: 0.026290154
A9: =Cartera!A5 -> Fondo Value Global | B9: =Cartera!C5 -> 0.087835385 | C9: 0.081734895
A10: =Cartera!A6 -> Fondo Internacional A | B10: =Cartera!C6 -> 0.058556923 | C10: 0.059909544
A11: =Cartera!A7 -> Fondo Internacional B | B11: =Cartera!C7 -> 0.023422769 | C11: 0.024075148
A12: =Cartera!A8 -> Fondo Crédito Flexible | B12: =Cartera!C8 -> 0.058556923 | C12: 0.057659747
A13: =Cartera!A9 -> Fondo Mixto Defensivo | B13: =Cartera!C9 -> 0.099546769 | C13: 0.098144497
A14: =Cartera!A10 -> Fondo Retorno Absoluto | B14: =Cartera!C10 -> 0.035134154 | C14: 0.036924504
A15: =Cartera!A11 -> Cuenta de efectivo | B15: =Cartera!C11 -> 0.01624369 | C15: 0
A16: =Cartera!A12 -> Acción tecnológica | B16: =Cartera!C12 -> 0.17567077 | C16: 0.17781515
A17: =Cartera!A13 -> Acción industrial | B17: =Cartera!C13 -> 0.021080492 | C17: 0.021883335
... A20: =Cartera!A16 -> Bitcoin | B20: =Cartera!C16 -> 0.011711385 | C20: 0.012756581
A21: TOTAL | B21: =SUM(B6:B20) -> 1 | C21: =SUM(C6:C20) -> 1
A22: Estado | C22: =IF(AND(COUNT(C6:C20)=15,ABS(C21-1)<0.000001,MIN(C6:C20)>=0,MAX(C6:C20)<=1),"OK","REVISAR") -> OK
A23: Cambia el importe de C3 para simular una aportación.
A25: Activo | B25: Falta € | C25: Aportar €
A26: =A6 -> ETF Global Desarrollado | B26: =IF($C$22<>"OK","",MAX(0,$C6*(Cartera!$B$17+$C$3)-Cartera!B2)) -> 987.79387 | C26: =IF(OR($C$22<>"OK",NOT(ISNUMBER($C$3)),$C$3<0),"",IF(SUM($B$26:$B$40)=0,0,$C$3*B26/SUM($B$26:$B$40))) -> 0
A27: =A7 -> ETF Mercados Emergentes | B27: =IF($C$22<>"OK","",MAX(0,$C7*(Cartera!$B$17+$C$3)-Cartera!B3)) -> 0 | C27: =IF(OR($C$22<>"OK",NOT(ISNUMBER($C$3)),$C$3<0),"",IF(SUM($B$26:$B$40)=0,0,$C$3*B27/SUM($B$26:$B$40))) -> 0
A28: =A8 -> Fondo Asia Pacífico | B28: =IF($C$22<>"OK","",MAX(0,$C8*(Cartera!$B$17+$C$3)-Cartera!B4)) -> 0 | C28: =IF(OR($C$22<>"OK",NOT(ISNUMBER($C$3)),$C$3<0),"",IF(SUM($B$26:$B$40)=0,0,$C$3*B28/SUM($B$26:$B$40))) -> 0
A29: =A9 -> Fondo Value Global | B29: =IF($C$22<>"OK","",MAX(0,$C9*(Cartera!$B$17+$C$3)-Cartera!B5)) -> 0 | C29: =IF(OR($C$22<>"OK",NOT(ISNUMBER($C$3)),$C$3<0),"",IF(SUM($B$26:$B$40)=0,0,$C$3*B29/SUM($B$26:$B$40))) -> 0
A30: =A10 -> Fondo Internacional A | B30: =IF($C$22<>"OK","",MAX(0,$C10*(Cartera!$B$17+$C$3)-Cartera!B6)) -> 115.49625 | C30: =IF(OR($C$22<>"OK",NOT(ISNUMBER($C$3)),$C$3<0),"",IF(SUM($B$26:$B$40)=0,0,$C$3*B30/SUM($B$26:$B$40))) -> 0
A31: =A11 -> Fondo Internacional B | B31: =IF($C$22<>"OK","",MAX(0,$C11*(Cartera!$B$17+$C$3)-Cartera!B7)) -> 55.70465 | C31: =IF(OR($C$22<>"OK",NOT(ISNUMBER($C$3)),$C$3<0),"",IF(SUM($B$26:$B$40)=0,0,$C$3*B31/SUM($B$26:$B$40))) -> 0
A32: =A12 -> Fondo Crédito Flexible | B32: =IF($C$22<>"OK","",MAX(0,$C12*(Cartera!$B$17+$C$3)-Cartera!B8)) -> 0 | C32: =IF(OR($C$22<>"OK",NOT(ISNUMBER($C$3)),$C$3<0),"",IF(SUM($B$26:$B$40)=0,0,$C$3*B32/SUM($B$26:$B$40))) -> 0
A33: =A13 -> Fondo Mixto Defensivo | B33: =IF($C$22<>"OK","",MAX(0,$C13*(Cartera!$B$17+$C$3)-Cartera!B9)) -> 0 | C33: =IF(OR($C$22<>"OK",NOT(ISNUMBER($C$3)),$C$3<0),"",IF(SUM($B$26:$B$40)=0,0,$C$3*B33/SUM($B$26:$B$40))) -> 0
A34: =A14 -> Fondo Retorno Absoluto | B34: =IF($C$22<>"OK","",MAX(0,$C14*(Cartera!$B$17+$C$3)-Cartera!B10)) -> 152.87264 | C34: =IF(OR($C$22<>"OK",NOT(ISNUMBER($C$3)),$C$3<0),"",IF(SUM($B$26:$B$40)=0,0,$C$3*B34/SUM($B$26:$B$40))) -> 0
A35: =A15 -> Cuenta de efectivo | B35: =IF($C$22<>"OK","",MAX(0,$C15*(Cartera!$B$17+$C$3)-Cartera!B11)) -> 0 | C35: =IF(OR($C$22<>"OK",NOT(ISNUMBER($C$3)),$C$3<0),"",IF(SUM($B$26:$B$40)=0,0,$C$3*B35/SUM($B$26:$B$40))) -> 0
A36: =A16 -> Acción tecnológica | B36: =IF($C$22<>"OK","",MAX(0,$C16*(Cartera!$B$17+$C$3)-Cartera!B12)) -> 183.10183 | C36: =IF(OR($C$22<>"OK",NOT(ISNUMBER($C$3)),$C$3<0),"",IF(SUM($B$26:$B$40)=0,0,$C$3*B36/SUM($B$26:$B$40))) -> 0
A37: =A17 -> Acción industrial | B37: =IF($C$22<>"OK","",MAX(0,$C17*(Cartera!$B$17+$C$3)-Cartera!B13)) -> 68.552348 | C37: =IF(OR($C$22<>"OK",NOT(ISNUMBER($C$3)),$C$3<0),"",IF(SUM($B$26:$B$40)=0,0,$C$3*B37/SUM($B$26:$B$40))) -> 0
... A40: =A20 -> Bitcoin | B40: =IF($C$22<>"OK","",MAX(0,$C20*(Cartera!$B$17+$C$3)-Cartera!B16)) -> 89.246202 | C40: =IF(OR($C$22<>"OK",NOT(ISNUMBER($C$3)),$C$3<0),"",IF(SUM($B$26:$B$40)=0,0,$C$3*B40/SUM($B$26:$B$40))) -> 0
A41: TOTAL | B41: =SUM(B26:B40) -> 2609.9543 | C41: =SUM(C26:C40) -> 0
A42: Reparto teórico: los importes se muestran redondeados.

Sheet Estadísticas avanzadas
A1: ESTADÍSTICAS AVANZADAS
A2: Rentabilidades mensuales · solo meses completos
A3: €STR anual / objetivo Sortino | C3: 0.0275
A4: Meses analizados | C4: =I55 -> 18
A5: RENTABILIDAD Y RIESGO
A6: Rentabilidad anualizada | C6: =A55 -> 0.25283895
A7: Volatilidad anualizada | C7: =E55 -> 0.088469613
A8: Máximo drawdown mensual | C8: =A52 -> -0.056746077
A9: Mejor mes | C9: =M55 -> 0.054242632
A10: RENTABILIDAD AJUSTADA AL RIESGO
A11: Sortino | C11: =E49 -> 4.4453847
A12: Sharpe | C12: =A49 -> 2.3028731
A13: Treynor | C13: =A58 -> 0.71742591
A14: COMPARACIÓN CON MSCI WORLD
A15: Beta | C15: =M49 -> 0.28397956
A16: Alpha de Jensen anual | C16: =I49 -> 0.17385018
A17: Tracking error anual | C17: =I52 -> 0.12147204
A18: Information ratio | C18: =E52 -> 0.81089411
A19: Correlación | C19: =M52 -> 0.40649275
A20: CONTEXTO DEL SORTINO
A21: Objetivo mensual | C21: =C3/12 -> 0.0022916667
A22: Meses bajo objetivo | C22: =COUNTIF(J77:J98,"<0") -> 4
A23: Proporción bajo objetivo | C23: =IFERROR(C22/C4,"") -> 0.22222222
A24: Muestra corta: los ratios pueden variar mucho.
A25: El drawdown utiliza cierres mensuales.
A26: €STR constante; no reproduce su evolución histórica.
A27: EVOLUCIÓN FRENTE AL BENCHMARK
A41: ESTADÍSTICAS AVANZADAS · PORTFOLIO
A43: €STR anual (tasa libre de riesgo) | C43: =$C$3 -> 0.0275
E44: Objetivo Sortino | G44: =$C$43 -> 0.0275
E45: Meses bajo objetivo | G45: =COUNTIF($J$77:$J$98,"<0") -> 4 | I45: =COUNTIF($J$77:$J$98,"<0")/COUNT($B$77:$B$98) -> 0.22222222
A46: Retornos mensuales en decimales, solo meses completos desde marzo de 2025. Febrero es la base. €STR constante de C3, convertido a mensual como C3/12. Ratios anualizados; drawdown entre cierres mensuales.
A48: Ratio Sharpe | E48: Ratio Sortino | I48: Alpha anual | M48: Beta vs MSCI World
A49: =IFERROR(__xludf.DUMMYFUNCTION("IFERROR(AVERAGE(FILTER($D$77:$D$98,$D$77:$D$98<>""""))/STDEV(FILTER($D$77:$D$98,$D$77:$D$98<>""""))*SQRT(12),"""")"),2.30287314634802) -> 2.3028731 | E49: =IFERROR(__xludf.DUMMYFUNCTION("IFERROR(AVERAGE(FILTER($D$77:$D$98,$D$77:$D$98<>""""))/SQRT(SUMSQ(FILTER($J$77:$J$98,$D$77:$D$98<>""""))/COUNT(FILTER($D$77:$D$98,$D$77:$D$98<>"""")))*SQRT(12),"""")"),4.44538466186077) -> 4.4453847 | I49: =IFERROR(__xludf.DUMMYFUNCTION("IFERROR((AVERAGE(FILTER($B$77:$B$98,$B$77:$B$98<>"""",$C$77:$C$98<>""""))-$C$43/12-$M$49*(AVERAGE(FILTER($C$77:$C$98,$B$77:$B$98<>"""",$C$77:$C$98<>""""))-$C$43/12))*12,"""")"),0.173850180349715) -> 0.17385018 | M49: =IFERROR(__xludf.DUMMYFUNCTION("IFERROR(SLOPE(FILTER($B$77:$B$98,$B$77:$B$98<>"""",$C$77:$C$98<>""""),FILTER($C$77:$C$98,$B$77:$B$98<>"""",$C$77:$C$98<>"""")),"""")"),0.283979564756541) -> 0.28397956
A51: Máximo drawdown | E51: Information ratio | I51: Tracking error anual | M51: Correlación
A52: =IFERROR(MIN($I$77:$I$98),"") -> -0.056746077 | E52: =IFERROR(__xludf.DUMMYFUNCTION("IFERROR(AVERAGE(FILTER($E$77:$E$98,$E$77:$E$98<>""""))/STDEV(FILTER($E$77:$E$98,$E$77:$E$98<>""""))*SQRT(12),"""")"),0.810894112661004) -> 0.81089411 | I52: =IFERROR(__xludf.DUMMYFUNCTION("IFERROR(STDEV(FILTER($E$77:$E$98,$E$77:$E$98<>""""))*SQRT(12),"""")"),0.121472041387777) -> 0.12147204 | M52: =IFERROR(__xludf.DUMMYFUNCTION("IFERROR(CORREL(FILTER($B$77:$B$98,$B$77:$B$98<>"""",$C$77:$C$98<>""""),FILTER($C$77:$C$98,$B$77:$B$98<>"""",$C$77:$C$98<>"""")),"""")"),0.406492745665897) -> 0.40649275
A54: Rentabilidad anualizada | E54: Volatilidad anualizada | I54: Meses analizados | M54: Mejor mes
A55: =IFERROR(__xludf.DUMMYFUNCTION("IFERROR(INDEX(FILTER($F$77:$F$98,$F$77:$F$98<>""""),COUNT(FILTER($F$77:$F$98,$F$77:$F$98<>"""")))^(12/COUNT($B$77:$B$98))-1,"""")"),0.252838946498591) -> 0.25283895 | E55: =IFERROR(__xludf.DUMMYFUNCTION("IFERROR(STDEV(FILTER($B$77:$B$98,$B$77:$B$98<>""""))*SQRT(12),"""")"),0.0884696132180293) -> 0.088469613 | I55: =COUNT($B$77:$B$98) -> 18 | M55: =IFERROR(MAX($B$77:$B$98),"") -> 0.054242632
A57: Ratio Treynor
A58: =IFERROR(__xludf.DUMMYFUNCTION("IFERROR((AVERAGE(FILTER($B$77:$B$98,$B$77:$B$98<>"""",$C$77:$C$98<>""""))*12-$C$43)/$M$49,"""")"),0.717425906058624) -> 0.71742591
A73: DETALLE DE CÁLCULO · RENTABILIDADES MENSUALES
A76: =Comparativa!C2 -> 2025 Feb | B76: =IF(Comparativa!D2="","",Comparativa!D2/100) -> 0 | C76: =IF(Comparativa!E2="","",Comparativa!E2/100) -> 0 | D76: =IF(B76="","",B76-$C$43/12) -> -0.0022916667 | E76: =IF(OR(B76="",C76=""),"",B76-C76) -> 0 | F76: =IF(B76="","",1+B76) -> 1 | G76: =IF(C76="","",1+C76) -> 1 | H76: =IF(F76="","",F76) -> 1 | I76: =IF(F76="","",F76/H76-1) -> 0 | J76: =IF(D76="","",MIN(D76,0)) -> -0.0022916667 | L76: =IF(OR(F76="",G76=""),"",A76) -> 2025 Feb | M76: =IF(L76="","",F76) -> 1 | N76: =IF(L76="","",G76) -> 1 | P76: =IF(E76="","",A76) -> 2025 Feb | Q76: =IF(P76="","",E76) -> 0
A77: =Comparativa!C3 -> 2025 Mar | B77: =IF(OR(DATE(2025,4,1)>TODAY(),NOT(ISNUMBER(Comparativa!D3))),"",Comparativa!D3/100) -> 0.038357366 | C77: =IF(OR(DATE(2025,4,1)>TODAY(),NOT(ISNUMBER(Comparativa!E3))),"",Comparativa!E3/100) -> -0.0697 | D77: =IF(B77="","",B77-$C$43/12) -> 0.0360657 | E77: =IF(OR(B77="",C77=""),"",B77-C77) -> 0.10805737 | F77: =IF(B77="","",F76*(1+B77)) -> 1.0383574 | G77: =IF(C77="","",G76*(1+C77)) -> 0.9303 | H77: =IF(F77="","",MAX(H76,F77)) -> 1.0383574 | I77: =IF(F77="","",F77/H77-1) -> 0 | J77: =IF(D77="","",MIN(D77,0)) -> 0 | L77: =IF(OR(F77="",G77=""),"",A77) -> 2025 Mar | M77: =IF(L77="","",F77) -> 1.0383574 | N77: =IF(L77="","",G77) -> 0.9303 | P77: =IF(E77="","",A77) -> 2025 Mar | Q77: =IF(P77="","",E77) -> 0.10805737
A78: =Comparativa!C4 -> 2025 Abr | B78: =IF(OR(DATE(2025,5,1)>TODAY(),NOT(ISNUMBER(Comparativa!D4))),"",Comparativa!D4/100) -> 0.021654364 | C78: =IF(OR(DATE(2025,5,1)>TODAY(),NOT(ISNUMBER(Comparativa!E4))),"",Comparativa!E4/100) -> -0.0412 | D78: =IF(B78="","",B78-$C$43/12) -> 0.019362698 | E78: =IF(OR(B78="",C78=""),"",B78-C78) -> 0.062854364 | F78: =IF(B78="","",F77*(1+B78)) -> 1.0608423 | G78: =IF(C78="","",G77*(1+C78)) -> 0.89197164 | H78: =IF(F78="","",MAX(H77,F78)) -> 1.0608423 | I78: =IF(F78="","",F78/H78-1) -> 0 | J78: =IF(D78="","",MIN(D78,0)) -> 0 | L78: =IF(OR(F78="",G78=""),"",A78) -> 2025 Abr | M78: =IF(L78="","",F78) -> 1.0608423 | N78: =IF(L78="","",G78) -> 0.89197164 | P78: =IF(E78="","",A78) -> 2025 Abr | Q78: =IF(P78="","",E78) -> 0.062854364
A79: =Comparativa!C5 -> 2025 May | B79: =IF(OR(DATE(2025,6,1)>TODAY(),NOT(ISNUMBER(Comparativa!D5))),"",Comparativa!D5/100) -> 0.022706153 | C79: =IF(OR(DATE(2025,6,1)>TODAY(),NOT(ISNUMBER(Comparativa!E5))),"",Comparativa!E5/100) -> 0.0607 | D79: =IF(B79="","",B79-$C$43/12) -> 0.020414486 | E79: =IF(OR(B79="",C79=""),"",B79-C79) -> -0.037993847 | F79: =IF(B79="","",F78*(1+B79)) -> 1.08493 | G79: =IF(C79="","",G78*(1+C79)) -> 0.94611432 | H79: =IF(F79="","",MAX(H78,F79)) -> 1.08493 | I79: =IF(F79="","",F79/H79-1) -> 0 | J79: =IF(D79="","",MIN(D79,0)) -> 0 | L79: =IF(OR(F79="",G79=""),"",A79) -> 2025 May | M79: =IF(L79="","",F79) -> 1.08493 | N79: =IF(L79="","",G79) -> 0.94611432 | P79: =IF(E79="","",A79) -> 2025 May | Q79: =IF(P79="","",E79) -> -0.037993847
A80: =Comparativa!C6 -> 2025 Jun | B80: =IF(OR(DATE(2025,7,1)>TODAY(),NOT(ISNUMBER(Comparativa!D6))),"",Comparativa!D6/100) -> 0.011130311 | C80: =IF(OR(DATE(2025,7,1)>TODAY(),NOT(ISNUMBER(Comparativa!E6))),"",Comparativa!E6/100) -> 0.0088 | D80: =IF(B80="","",B80-$C$43/12) -> 0.0088386444 | E80: =IF(OR(B80="",C80=""),"",B80-C80) -> 0.002330311 | F80: =IF(B80="","",F79*(1+B80)) -> 1.0970056 | G80: =IF(C80="","",G79*(1+C80)) -> 0.95444012 | H80: =IF(F80="","",MAX(H79,F80)) -> 1.0970056 | I80: =IF(F80="","",F80/H80-1) -> 0 | J80: =IF(D80="","",MIN(D80,0)) -> 0 | L80: =IF(OR(F80="",G80=""),"",A80) -> 2025 Jun | M80: =IF(L80="","",F80) -> 1.0970056 | N80: =IF(L80="","",G80) -> 0.95444012 | P80: =IF(E80="","",A80) -> 2025 Jun | Q80: =IF(P80="","",E80) -> 0.002330311
A81: =Comparativa!C7 -> 2025 Jul | B81: =IF(OR(DATE(2025,8,1)>TODAY(),NOT(ISNUMBER(Comparativa!D7))),"",Comparativa!D7/100) -> 0.014954045 | C81: =IF(OR(DATE(2025,8,1)>TODAY(),NOT(ISNUMBER(Comparativa!E7))),"",Comparativa!E7/100) -> 0.0386 | D81: =IF(B81="","",B81-$C$43/12) -> 0.012662378 | E81: =IF(OR(B81="",C81=""),"",B81-C81) -> -0.023645955 | F81: =IF(B81="","",F80*(1+B81)) -> 1.1134103 | G81: =IF(C81="","",G80*(1+C81)) -> 0.99128151 | H81: =IF(F81="","",MAX(H80,F81)) -> 1.1134103 | I81: =IF(F81="","",F81/H81-1) -> 0 | J81: =IF(D81="","",MIN(D81,0)) -> 0 | L81: =IF(OR(F81="",G81=""),"",A81) -> 2025 Jul | M81: =IF(L81="","",F81) -> 1.1134103 | N81: =IF(L81="","",G81) -> 0.99128151 | P81: =IF(E81="","",A81) -> 2025 Jul | Q81: =IF(P81="","",E81) -> -0.023645955
A82: =Comparativa!C8 -> 2025 Ago | B82: =IF(OR(DATE(2025,9,1)>TODAY(),NOT(ISNUMBER(Comparativa!D8))),"",Comparativa!D8/100) -> 0.0080015487 | C82: =IF(OR(DATE(2025,9,1)>TODAY(),NOT(ISNUMBER(Comparativa!E8))),"",Comparativa!E8/100) -> 0.0032 | D82: =IF(B82="","",B82-$C$43/12) -> 0.005709882 | E82: =IF(OR(B82="",C82=""),"",B82-C82) -> 0.0048015487 | F82: =IF(B82="","",F81*(1+B82)) -> 1.1223193 | G82: =IF(C82="","",G81*(1+C82)) -> 0.99445361 | H82: =IF(F82="","",MAX(H81,F82)) -> 1.1223193 | I82: =IF(F82="","",F82/H82-1) -> 0 | J82: =IF(D82="","",MIN(D82,0)) -> 0 | L82: =IF(OR(F82="",G82=""),"",A82) -> 2025 Ago | M82: =IF(L82="","",F82) -> 1.1223193 | N82: =IF(L82="","",G82) -> 0.99445361 | P82: =IF(E82="","",A82) -> 2025 Ago | Q82: =IF(P82="","",E82) -> 0.0048015487
A83: =Comparativa!C9 -> 2025 Sep | B83: =IF(OR(DATE(2025,10,1)>TODAY(),NOT(ISNUMBER(Comparativa!D9))),"",Comparativa!D9/100) -> 0.05199101 | C83: =IF(OR(DATE(2025,10,1)>TODAY(),NOT(ISNUMBER(Comparativa!E9))),"",Comparativa!E9/100) -> 0.0281 | D83: =IF(B83="","",B83-$C$43/12) -> 0.049699344 | E83: =IF(OR(B83="",C83=""),"",B83-C83) -> 0.02389101 | F83: =IF(B83="","",F82*(1+B83)) -> 1.1806698 | G83: =IF(C83="","",G82*(1+C83)) -> 1.0223978 | H83: =IF(F83="","",MAX(H82,F83)) -> 1.1806698 | I83: =IF(F83="","",F83/H83-1) -> 0 | J83: =IF(D83="","",MIN(D83,0)) -> 0 | L83: =IF(OR(F83="",G83=""),"",A83) -> 2025 Sep | M83: =IF(L83="","",F83) -> 1.1806698 | N83: =IF(L83="","",G83) -> 1.0223978 | P83: =IF(E83="","",A83) -> 2025 Sep | Q83: =IF(P83="","",E83) -> 0.02389101
A84: =Comparativa!C10 -> 2025 Oct | B84: =IF(OR(DATE(2025,11,1)>TODAY(),NOT(ISNUMBER(Comparativa!D10))),"",Comparativa!D10/100) -> 0.028539951 | C84: =IF(OR(DATE(2025,11,1)>TODAY(),NOT(ISNUMBER(Comparativa!E10))),"",Comparativa!E10/100) -> 0.0383 | D84: =IF(B84="","",B84-$C$43/12) -> 0.026248285 | E84: =IF(OR(B84="",C84=""),"",B84-C84) -> -0.0097600485 | F84: =IF(B84="","",F83*(1+B84)) -> 1.214366 | G84: =IF(C84="","",G83*(1+C84)) -> 1.0615556 | H84: =IF(F84="","",MAX(H83,F84)) -> 1.214366 | I84: =IF(F84="","",F84/H84-1) -> 0 | J84: =IF(D84="","",MIN(D84,0)) -> 0 | L84: =IF(OR(F84="",G84=""),"",A84) -> 2025 Oct | M84: =IF(L84="","",F84) -> 1.214366 | N84: =IF(L84="","",G84) -> 1.0615556 | P84: =IF(E84="","",A84) -> 2025 Oct | Q84: =IF(P84="","",E84) -> -0.0097600485
A85: =Comparativa!C11 -> 2025 Nov | B85: =IF(OR(DATE(2025,12,1)>TODAY(),NOT(ISNUMBER(Comparativa!D11))),"",Comparativa!D11/100) -> -0.0026796206 | C85: =IF(OR(DATE(2025,12,1)>TODAY(),NOT(ISNUMBER(Comparativa!E11))),"",Comparativa!E11/100) -> -0.0027 | D85: =IF(B85="","",B85-$C$43/12) -> -0.0049712872 | E85: =IF(OR(B85="",C85=""),"",B85-C85) -> 2.0379446e-05 | F85: =IF(B85="","",F84*(1+B85)) -> 1.211112 | G85: =IF(C85="","",G84*(1+C85)) -> 1.0586894 | H85: =IF(F85="","",MAX(H84,F85)) -> 1.214366 | I85: =IF(F85="","",F85/H85-1) -> -0.0026796206 | J85: =IF(D85="","",MIN(D85,0)) -> -0.0049712872 | L85: =IF(OR(F85="",G85=""),"",A85) -> 2025 Nov | M85: =IF(L85="","",F85) -> 1.211112 | N85: =IF(L85="","",G85) -> 1.0586894 | P85: =IF(E85="","",A85) -> 2025 Nov | Q85: =IF(P85="","",E85) -> 2.0379446e-05
A86: =Comparativa!C12 -> 2025 Dic | B86: =IF(OR(DATE(2025,13,1)>TODAY(),NOT(ISNUMBER(Comparativa!D12))),"",Comparativa!D12/100) -> 0.038535399 | C86: =IF(OR(DATE(2025,13,1)>TODAY(),NOT(ISNUMBER(Comparativa!E12))),"",Comparativa!E12/100) -> -0.004 | D86: =IF(B86="","",B86-$C$43/12) -> 0.036243732 | E86: =IF(OR(B86="",C86=""),"",B86-C86) -> 0.042535399 | F86: =IF(B86="","",F85*(1+B86)) -> 1.2577827 | G86: =IF(C86="","",G85*(1+C86)) -> 1.0544546 | H86: =IF(F86="","",MAX(H85,F86)) -> 1.2577827 | I86: =IF(F86="","",F86/H86-1) -> 0 | J86: =IF(D86="","",MIN(D86,0)) -> 0 | L86: =IF(OR(F86="",G86=""),"",A86) -> 2025 Dic | M86: =IF(L86="","",F86) -> 1.2577827 | N86: =IF(L86="","",G86) -> 1.0544546 | P86: =IF(E86="","",A86) -> 2025 Dic | Q86: =IF(P86="","",E86) -> 0.042535399
A87: =Comparativa!C13 -> 2026 Ene | B87: =IF(OR(DATE(2025,14,1)>TODAY(),NOT(ISNUMBER(Comparativa!D13))),"",Comparativa!D13/100) -> 0.024312151 | C87: =IF(OR(DATE(2025,14,1)>TODAY(),NOT(ISNUMBER(Comparativa!E13))),"",Comparativa!E13/100) -> 0.0092 | D87: =IF(B87="","",B87-$C$43/12) -> 0.022020484 | E87: =IF(OR(B87="",C87=""),"",B87-C87) -> 0.015112151 | F87: =IF(B87="","",F86*(1+B87)) -> 1.2883621 | G87: =IF(C87="","",G86*(1+C87)) -> 1.0641556 | H87: =IF(F87="","",MAX(H86,F87)) -> 1.2883621 | I87: =IF(F87="","",F87/H87-1) -> 0 | J87: =IF(D87="","",MIN(D87,0)) -> 0 | L87: =IF(OR(F87="",G87=""),"",A87) -> 2026 Ene | M87: =IF(L87="","",F87) -> 1.2883621 | N87: =IF(L87="","",G87) -> 1.0641556 | P87: =IF(E87="","",A87) -> 2026 Ene | Q87: =IF(P87="","",E87) -> 0.015112151
A88: =Comparativa!C14 -> 2026 Feb | B88: =IF(OR(DATE(2025,15,1)>TODAY(),NOT(ISNUMBER(Comparativa!D14))),"",Comparativa!D14/100) -> -0.0036578947 | C88: =IF(OR(DATE(2025,15,1)>TODAY(),NOT(ISNUMBER(Comparativa!E14))),"",Comparativa!E14/100) -> 0.0149 | D88: =IF(B88="","",B88-$C$43/12) -> -0.0059495614 | E88: =IF(OR(B88="",C88=""),"",B88-C88) -> -0.018557895 | F88: =IF(B88="","",F87*(1+B88)) -> 1.2836494 | G88: =IF(C88="","",G87*(1+C88)) -> 1.0800115 | H88: =IF(F88="","",MAX(H87,F88)) -> 1.2883621 | I88: =IF(F88="","",F88/H88-1) -> -0.0036578947 | J88: =IF(D88="","",MIN(D88,0)) -> -0.0059495614 | L88: =IF(OR(F88="",G88=""),"",A88) -> 2026 Feb | M88: =IF(L88="","",F88) -> 1.2836494 | N88: =IF(L88="","",G88) -> 1.0800115 | P88: =IF(E88="","",A88) -> 2026 Feb | Q88: =IF(P88="","",E88) -> -0.018557895
A89: =Comparativa!C15 -> 2026 Mar | B89: =IF(OR(DATE(2025,16,1)>TODAY(),NOT(ISNUMBER(Comparativa!D15))),"",Comparativa!D15/100) -> -0.053283086 | C89: =IF(OR(DATE(2025,16,1)>TODAY(),NOT(ISNUMBER(Comparativa!E15))),"",Comparativa!E15/100) -> -0.0404 | D89: =IF(B89="","",B89-$C$43/12) -> -0.055574753 | E89: =IF(OR(B89="",C89=""),"",B89-C89) -> -0.012883086 | F89: =IF(B89="","",F88*(1+B89)) -> 1.2152526 | G89: =IF(C89="","",G88*(1+C89)) -> 1.0363791 | H89: =IF(F89="","",MAX(H88,F89)) -> 1.2883621 | I89: =IF(F89="","",F89/H89-1) -> -0.056746077 | J89: =IF(D89="","",MIN(D89,0)) -> -0.055574753 | L89: =IF(OR(F89="",G89=""),"",A89) -> 2026 Mar | M89: =IF(L89="","",F89) -> 1.2152526 | N89: =IF(L89="","",G89) -> 1.0363791 | P89: =IF(E89="","",A89) -> 2026 Mar | Q89: =IF(P89="","",E89) -> -0.012883086
A90: =Comparativa!C16 -> 2026 Abr | B90: =IF(OR(DATE(2025,17,1)>TODAY(),NOT(ISNUMBER(Comparativa!D16))),"",Comparativa!D16/100) -> 0.054242632 | C90: =IF(OR(DATE(2025,17,1)>TODAY(),NOT(ISNUMBER(Comparativa!E16))),"",Comparativa!E16/100) -> 0.0765 | D90: =IF(B90="","",B90-$C$43/12) -> 0.051950965 | E90: =IF(OR(B90="",C90=""),"",B90-C90) -> -0.022257368 | F90: =IF(B90="","",F89*(1+B90)) -> 1.2811711 | G90: =IF(C90="","",G89*(1+C90)) -> 1.1156621 | H90: =IF(F90="","",MAX(H89,F90)) -> 1.2883621 | I90: =IF(F90="","",F90/H90-1) -> -0.0055815015 | J90: =IF(D90="","",MIN(D90,0)) -> 0 | L90: =IF(OR(F90="",G90=""),"",A90) -> 2026 Abr | M90: =IF(L90="","",F90) -> 1.2811711 | N90: =IF(L90="","",G90) -> 1.1156621 | P90: =IF(E90="","",A90) -> 2026 Abr | Q90: =IF(P90="","",E90) -> -0.022257368
A91: =Comparativa!C17 -> 2026 May | B91: =IF(OR(DATE(2025,18,1)>TODAY(),NOT(ISNUMBER(Comparativa!D17))),"",Comparativa!D17/100) -> 0.052199929 | C91: =IF(OR(DATE(2025,18,1)>TODAY(),NOT(ISNUMBER(Comparativa!E17))),"",Comparativa!E17/100) -> 0.051 | D91: =IF(B91="","",B91-$C$43/12) -> 0.049908262 | E91: =IF(OR(B91="",C91=""),"",B91-C91) -> 0.0011999291 | F91: =IF(B91="","",F90*(1+B91)) -> 1.3480481 | G91: =IF(C91="","",G90*(1+C91)) -> 1.1725608 | H91: =IF(F91="","",MAX(H90,F91)) -> 1.3480481 | I91: =IF(F91="","",F91/H91-1) -> 0 | J91: =IF(D91="","",MIN(D91,0)) -> 0 | L91: =IF(OR(F91="",G91=""),"",A91) -> 2026 May | M91: =IF(L91="","",F91) -> 1.3480481 | N91: =IF(L91="","",G91) -> 1.1725608 | P91: =IF(E91="","",A91) -> 2026 May | Q91: =IF(P91="","",E91) -> 0.0011999291
A92: =Comparativa!C18 -> 2026 Jun | B92: =IF(OR(DATE(2025,19,1)>TODAY(),NOT(ISNUMBER(Comparativa!D18))),"",Comparativa!D18/100) -> 0.00088066931 | C92: =IF(OR(DATE(2025,19,1)>TODAY(),NOT(ISNUMBER(Comparativa!E18))),"",Comparativa!E18/100) -> 0.0133 | D92: =IF(B92="","",B92-$C$43/12) -> -0.0014109974 | E92: =IF(OR(B92="",C92=""),"",B92-C92) -> -0.012419331 | F92: =IF(B92="","",F91*(1+B92)) -> 1.3492353 | G92: =IF(C92="","",G91*(1+C92)) -> 1.1881559 | H92: =IF(F92="","",MAX(H91,F92)) -> 1.3492353 | I92: =IF(F92="","",F92/H92-1) -> 0 | J92: =IF(D92="","",MIN(D92,0)) -> -0.0014109974 | L92: =IF(OR(F92="",G92=""),"",A92) -> 2026 Jun | M92: =IF(L92="","",F92) -> 1.3492353 | N92: =IF(L92="","",G92) -> 1.1881559 | P92: =IF(E92="","",A92) -> 2026 Jun | Q92: =IF(P92="","",E92) -> -0.012419331
A93: =Comparativa!C19 -> 2026 Jul | B93: =IF(OR(DATE(2025,20,1)>TODAY(),NOT(ISNUMBER(Comparativa!D19))),"",Comparativa!D19/100) -> 0.022952112 | C93: =IF(OR(DATE(2025,20,1)>TODAY(),NOT(ISNUMBER(Comparativa!E19))),"",Comparativa!E19/100) -> -0.0014 | D93: =IF(B93="","",B93-$C$43/12) -> 0.020660445 | E93: =IF(OR(B93="",C93=""),"",B93-C93) -> 0.024352112 | F93: =IF(B93="","",F92*(1+B93)) -> 1.3802031 | G93: =IF(C93="","",G92*(1+C93)) -> 1.1864925 | H93: =IF(F93="","",MAX(H92,F93)) -> 1.3802031 | I93: =IF(F93="","",F93/H93-1) -> 0 | J93: =IF(D93="","",MIN(D93,0)) -> 0 | L93: =IF(OR(F93="",G93=""),"",A93) -> 2026 Jul | M93: =IF(L93="","",F93) -> 1.3802031 | N93: =IF(L93="","",G93) -> 1.1864925 | P93: =IF(E93="","",A93) -> 2026 Jul | Q93: =IF(P93="","",E93) -> 0.024352112
A94: =Comparativa!C20 -> 2026 Ago | B94: =IF(OR(DATE(2025,21,1)>TODAY(),NOT(ISNUMBER(Comparativa!D20))),"",Comparativa!D20/100) -> 0.016014405 | C94: =IF(OR(DATE(2025,21,1)>TODAY(),NOT(ISNUMBER(Comparativa!E20))),"",Comparativa!E20/100) -> 0.0159 | D94: =IF(B94="","",B94-$C$43/12) -> 0.013722738 | E94: =IF(OR(B94="",C94=""),"",B94-C94) -> 0.00011440462 | F94: =IF(B94="","",F93*(1+B94)) -> 1.4023062 | G94: =IF(C94="","",G93*(1+C94)) -> 1.2053577 | H94: =IF(F94="","",MAX(H93,F94)) -> 1.4023062 | I94: =IF(F94="","",F94/H94-1) -> 0 | J94: =IF(D94="","",MIN(D94,0)) -> 0 | L94: =IF(OR(F94="",G94=""),"",A94) -> 2026 Ago | M94: =IF(L94="","",F94) -> 1.4023062 | N94: =IF(L94="","",G94) -> 1.2053577 | P94: =IF(E94="","",A94) -> 2026 Ago | Q94: =IF(P94="","",E94) -> 0.00011440462
A95: =Comparativa!C21 -> 2026 Sep | B95: =IF(OR(DATE(2025,22,1)>TODAY(),NOT(ISNUMBER(Comparativa!D21))),"",Comparativa!D21/100) | C95: =IF(OR(DATE(2025,22,1)>TODAY(),NOT(ISNUMBER(Comparativa!E21))),"",Comparativa!E21/100) | D95: =IF(B95="","",B95-$C$43/12) | E95: =IF(OR(B95="",C95=""),"",B95-C95) | F95: =IF(B95="","",F94*(1+B95)) | G95: =IF(C95="","",G94*(1+C95)) | H95: =IF(F95="","",MAX(H94,F95)) | I95: =IF(F95="","",F95/H95-1) | J95: =IF(D95="","",MIN(D95,0)) | L95: =IF(OR(F95="",G95=""),"",A95) | M95: =IF(L95="","",F95) | N95: =IF(L95="","",G95) | P95: =IF(E95="","",A95) | Q95: =IF(P95="","",E95)
A96: =Comparativa!C22 -> 2026 Oct | B96: =IF(OR(DATE(2025,23,1)>TODAY(),NOT(ISNUMBER(Comparativa!D22))),"",Comparativa!D22/100) | C96: =IF(OR(DATE(2025,23,1)>TODAY(),NOT(ISNUMBER(Comparativa!E22))),"",Comparativa!E22/100) | D96: =IF(B96="","",B96-$C$43/12) | E96: =IF(OR(B96="",C96=""),"",B96-C96) | F96: =IF(B96="","",F95*(1+B96)) | G96: =IF(C96="","",G95*(1+C96)) | H96: =IF(F96="","",MAX(H95,F96)) | I96: =IF(F96="","",F96/H96-1) | J96: =IF(D96="","",MIN(D96,0)) | L96: =IF(OR(F96="",G96=""),"",A96) | M96: =IF(L96="","",F96) | N96: =IF(L96="","",G96) | P96: =IF(E96="","",A96) | Q96: =IF(P96="","",E96)
A97: =Comparativa!C23 -> 2026 Nov | B97: =IF(OR(DATE(2025,24,1)>TODAY(),NOT(ISNUMBER(Comparativa!D23))),"",Comparativa!D23/100) | C97: =IF(OR(DATE(2025,24,1)>TODAY(),NOT(ISNUMBER(Comparativa!E23))),"",Comparativa!E23/100) | D97: =IF(B97="","",B97-$C$43/12) | E97: =IF(OR(B97="",C97=""),"",B97-C97) | F97: =IF(B97="","",F96*(1+B97)) | G97: =IF(C97="","",G96*(1+C97)) | H97: =IF(F97="","",MAX(H96,F97)) | I97: =IF(F97="","",F97/H97-1) | J97: =IF(D97="","",MIN(D97,0)) | L97: =IF(OR(F97="",G97=""),"",A97) | M97: =IF(L97="","",F97) | N97: =IF(L97="","",G97) | P97: =IF(E97="","",A97) | Q97: =IF(P97="","",E97)
A98: =Comparativa!C24 -> 2026 Dic | B98: =IF(OR(DATE(2025,25,1)>TODAY(),NOT(ISNUMBER(Comparativa!D24))),"",Comparativa!D24/100) | C98: =IF(OR(DATE(2025,25,1)>TODAY(),NOT(ISNUMBER(Comparativa!E24))),"",Comparativa!E24/100) | D98: =IF(B98="","",B98-$C$43/12) | E98: =IF(OR(B98="",C98=""),"",B98-C98) | F98: =IF(B98="","",F97*(1+B98)) | G98: =IF(C98="","",G97*(1+C98)) | H98: =IF(F98="","",MAX(H97,F98)) | I98: =IF(F98="","",F98/H98-1) | J98: =IF(D98="","",MIN(D98,0)) | L98: =IF(OR(F98="",G98=""),"",A98) | M98: =IF(L98="","",F98) | N98: =IF(L98="","",G98) | P98: =IF(E98="","",A98) | Q98: =IF(P98="","",E98)

Sheet Control
A1: CONTROL DE DATOS
A2: Avisos automáticos; revisa los marcados REVISAR.
A3: Pesos de cartera | C3: =IF(AND(COUNT(Cartera!B2:B16)=15,MIN(Cartera!B2:B16)>=0,ABS(SUM(Cartera!C2:C16)-1)<0.000001),"OK","REVISAR") -> OK
A4: Total de cartera | C4: =IF(ABS(Cartera!B17-SUM(Cartera!B2:B16))<0.01,"OK","REVISAR") -> OK
A5: Objetivos suman 100 % | C5: =Objetivos!C22 -> OK
A6: Cuadre mensual | C6: =IF(COUNTIF(K41:K75,"REVISAR")=0,"OK","REVISAR") -> OK
A7: Falta MSCI en mes cerrado | C7: =SUMPRODUCT(N(ISNUMBER(I42:I75)),N(E42:E75<EOMONTH(TODAY(),-1)+1),N(ISNUMBER(J42:J75)=FALSE)) -> 0
A8: Meses cerrados sin cartera | C8: =SUMPRODUCT(N(E42:E75<EOMONTH(TODAY(),-1)+1),N(ISNUMBER(F42:F75)=FALSE)) -> 0
A9: Movimientos incompletos | C9: =SUMPRODUCT(N((LEN(Movimientos!A6:A505)+LEN(Movimientos!B6:B505)+LEN(Movimientos!C6:C505))>0),N((ISNUMBER(Movimientos!D6:D505)*ISNUMBER(Movimientos!B6:B505))=0)) -> 0
A10: Posibles duplicados | C10: =SUMPRODUCT(N(Movimientos!A6:A505<>""),N(COUNTIFS(Movimientos!A6:A505,Movimientos!A6:A505,Movimientos!B6:B505,Movimientos!B6:B505,Movimientos!C6:C505,Movimientos!C6:C505)>1)) -> 0
A11: Históricos sin fecha utilizable | C11: =COUNTIFS(Movimientos!E6:E505,FALSE,Movimientos!C6:C505,"<>Fecha inferida*") -> 0
A12: Cartera − último diario € | C12: =IFERROR(Cartera!B17-LOOKUP(2,1/((Diario!B6:B370<>"")*(Diario!A6:A370<=TODAY())),Diario!B6:B370),"") -> 0
A13: La diferencia puede deberse a fechas de actualización.
A14: Estado general | C14: =IF(OR(COUNTIF(C3:C6,"REVISAR")>0,SUM(C7:C10)>0,C20="REVISAR",C21>0,C23>0),"REVISAR",IF(ABS(C12)>0.01,"AVISO","OK")) -> OK
A15: Supuestos
A16: Mensual: flujos al final del mes.
A17: Diario: días naturales consecutivos; fechas exactas o inferidas identificadas.
A18: €STR constante editable; no es una serie histórica.
A19: Ganancia acumulada desde la base de febrero de 2025.
A20: Comparativa vs Evolución | C20: =IF(AND(ABS(Comparativa!D3/100-I42)<0.00002,ABS(Comparativa!D4/100-I43)<0.00002,ABS(Comparativa!D5/100-I44)<0.00002,ABS(Comparativa!D6/100-I45)<0.00002,ABS(Comparativa!D7/100-I46)<0.00002,ABS(Comparativa!D8/100-I47)<0.00002,ABS(Comparativa!D9/100-I48)<0.00002,ABS(Comparativa!D10/100-I49)<0.00002,ABS(Comparativa!D11/100-I50)<0.00002,ABS(Comparativa!D12/100-I51)<0.00002,ABS(Comparativa!D13/100-I52)<0.00002,ABS(Comparativa!D14/100-I53)<0.00002,ABS(Comparativa!D15/100-I54)<0.00002,ABS(Comparativa!D16/100-I55)<0.00002,ABS(Comparativa!D17/100-I56)<0.00002,ABS(Comparativa!D18/100-I57)<0.00002,ABS(Comparativa!D19/100-I58)<0.00002,ABS(Comparativa!D20/100-I59)<0.00002,ABS(Comparativa!D21/100-I60)<0.00002),"OK","REVISAR") -> OK
A21: Meses con total y detalle | C21: =SUMPRODUCT(N(Movimientos!E6:E505=FALSE),N(Movimientos!A6:A505<>""),N(COUNTIFS(Movimientos!D6:D505,">="&Movimientos!D6:D505,Movimientos!D6:D505,"<"&IFERROR(EOMONTH(Movimientos!D6:D505,0)+1,0),Movimientos!E6:E505,TRUE)>0)) -> 0
A22: Fecha diaria más reciente | C22: =IFERROR(LOOKUP(2,1/((Diario!B6:B370<>"")*(Diario!A6:A370<=TODAY())),Diario!A6:A370),"") -> 46275
A23: Datos diarios con fecha futura | C23: =COUNTIFS(Diario!A6:A370,">"&TODAY(),Diario!B6:B370,">=0") -> 0
E40: Mes | F40: Patrimonio | G40: Capital neto | H40: Ganancia | I40: Retorno | J40: MSCI | K40: Coherencia | L40: Inicial | M40: Flujo neto | N40: Plusvalía mes
E41: =DATE(2025,2,1) -> 45689 | F41: =IF(Evolucion!B3="","",Evolucion!B3) -> 52428 | G41: =IF(F41="","",Evolucion!$C$3+SUMIFS(Movimientos!$B$6:$B$505,Movimientos!$D$6:$D$505,"<="&EOMONTH(E41,0),Movimientos!$D$6:$D$505,">="&DATE(2025,2,1))) -> 52428 | H41: =IF(F41="","",F41-G41) -> 0 | I41: ="" | J41: =IF(Comparativa!E2="","",Comparativa!E2/100) -> 0 | K41: ="BASE" -> BASE | L41: =IF(F41="","",Evolucion!C3) -> 51728 | M41: =IF(F41="","",Evolucion!D3) -> 700 | N41: =IF(F41="","",Evolucion!E3) -> 0
E42: =DATE(2025,3,1) -> 45717 | F42: =IF(Evolucion!B4="","",Evolucion!B4) -> 55139 | G42: =IF(F42="","",Evolucion!$C$3+SUMIFS(Movimientos!$B$6:$B$505,Movimientos!$D$6:$D$505,"<="&EOMONTH(E42,0),Movimientos!$D$6:$D$505,">="&DATE(2025,2,1))) -> 53128 | H42: =IF(F42="","",F42-G42) -> 2011 | I42: =IF(Evolucion!F4="","",Evolucion!F4/100) -> 0.038357366 | J42: =IF(Comparativa!E3="","",Comparativa!E3/100) -> -0.0697 | K42: =IF(F42="","SIN DATO",IF(AND(ISNUMBER(I42),ABS(F42-L42-M42-N42)<0.01,ABS(I42-IFERROR((F42-L42-M42)/L42,999))<0.00002),"OK","REVISAR")) -> OK | L42: =IF(F42="","",Evolucion!C4) -> 52428 | M42: =IF(F42="","",Evolucion!D4) -> 700 | N42: =IF(F42="","",Evolucion!E4) -> 2011
E43: =DATE(2025,4,1) -> 45748 | F43: =IF(Evolucion!B5="","",Evolucion!B5) -> 57033 | G43: =IF(F43="","",Evolucion!$C$3+SUMIFS(Movimientos!$B$6:$B$505,Movimientos!$D$6:$D$505,"<="&EOMONTH(E43,0),Movimientos!$D$6:$D$505,">="&DATE(2025,2,1))) -> 53828 | H43: =IF(F43="","",F43-G43) -> 3205 | I43: =IF(Evolucion!F5="","",Evolucion!F5/100) -> 0.021654364 | J43: =IF(Comparativa!E4="","",Comparativa!E4/100) -> -0.0412 | K43: =IF(F43="","SIN DATO",IF(AND(ISNUMBER(I43),ABS(F43-L43-M43-N43)<0.01,ABS(I43-IFERROR((F43-L43-M43)/L43,999))<0.00002),"OK","REVISAR")) -> OK | L43: =IF(F43="","",Evolucion!C5) -> 55139 | M43: =IF(F43="","",Evolucion!D5) -> 700 | N43: =IF(F43="","",Evolucion!E5) -> 1194
E44: =DATE(2025,5,1) -> 45778 | F44: =IF(Evolucion!B6="","",Evolucion!B6) -> 59028 | G44: =IF(F44="","",Evolucion!$C$3+SUMIFS(Movimientos!$B$6:$B$505,Movimientos!$D$6:$D$505,"<="&EOMONTH(E44,0),Movimientos!$D$6:$D$505,">="&DATE(2025,2,1))) -> 54528 | H44: =IF(F44="","",F44-G44) -> 4500 | I44: =IF(Evolucion!F6="","",Evolucion!F6/100) -> 0.022706153 | J44: =IF(Comparativa!E5="","",Comparativa!E5/100) -> 0.0607 | K44: =IF(F44="","SIN DATO",IF(AND(ISNUMBER(I44),ABS(F44-L44-M44-N44)<0.01,ABS(I44-IFERROR((F44-L44-M44)/L44,999))<0.00002),"OK","REVISAR")) -> OK | L44: =IF(F44="","",Evolucion!C6) -> 57033 | M44: =IF(F44="","",Evolucion!D6) -> 700 | N44: =IF(F44="","",Evolucion!E6) -> 1295
E45: =DATE(2025,6,1) -> 45809 | F45: =IF(Evolucion!B7="","",Evolucion!B7) -> 60385 | G45: =IF(F45="","",Evolucion!$C$3+SUMIFS(Movimientos!$B$6:$B$505,Movimientos!$D$6:$D$505,"<="&EOMONTH(E45,0),Movimientos!$D$6:$D$505,">="&DATE(2025,2,1))) -> 55228 | H45: =IF(F45="","",F45-G45) -> 5157 | I45: =IF(Evolucion!F7="","",Evolucion!F7/100) -> 0.011130311 | J45: =IF(Comparativa!E6="","",Comparativa!E6/100) -> 0.0088 | K45: =IF(F45="","SIN DATO",IF(AND(ISNUMBER(I45),ABS(F45-L45-M45-N45)<0.01,ABS(I45-IFERROR((F45-L45-M45)/L45,999))<0.00002),"OK","REVISAR")) -> OK | L45: =IF(F45="","",Evolucion!C7) -> 59028 | M45: =IF(F45="","",Evolucion!D7) -> 700 | N45: =IF(F45="","",Evolucion!E7) -> 657
E46: =DATE(2025,7,1) -> 45839 | F46: =IF(Evolucion!B8="","",Evolucion!B8) -> 61988 | G46: =IF(F46="","",Evolucion!$C$3+SUMIFS(Movimientos!$B$6:$B$505,Movimientos!$D$6:$D$505,"<="&EOMONTH(E46,0),Movimientos!$D$6:$D$505,">="&DATE(2025,2,1))) -> 55928 | H46: =IF(F46="","",F46-G46) -> 6060 | I46: =IF(Evolucion!F8="","",Evolucion!F8/100) -> 0.014954045 | J46: =IF(Comparativa!E7="","",Comparativa!E7/100) -> 0.0386 | K46: =IF(F46="","SIN DATO",IF(AND(ISNUMBER(I46),ABS(F46-L46-M46-N46)<0.01,ABS(I46-IFERROR((F46-L46-M46)/L46,999))<0.00002),"OK","REVISAR")) -> OK | L46: =IF(F46="","",Evolucion!C8) -> 60385 | M46: =IF(F46="","",Evolucion!D8) -> 700 | N46: =IF(F46="","",Evolucion!E8) -> 903
E47: =DATE(2025,8,1) -> 45870 | F47: =IF(Evolucion!B9="","",Evolucion!B9) -> 63184 | G47: =IF(F47="","",Evolucion!$C$3+SUMIFS(Movimientos!$B$6:$B$505,Movimientos!$D$6:$D$505,"<="&EOMONTH(E47,0),Movimientos!$D$6:$D$505,">="&DATE(2025,2,1))) -> 56628 | H47: =IF(F47="","",F47-G47) -> 6556 | I47: =IF(Evolucion!F9="","",Evolucion!F9/100) -> 0.0080015487 | J47: =IF(Comparativa!E8="","",Comparativa!E8/100) -> 0.0032 | K47: =IF(F47="","SIN DATO",IF(AND(ISNUMBER(I47),ABS(F47-L47-M47-N47)<0.01,ABS(I47-IFERROR((F47-L47-M47)/L47,999))<0.00002),"OK","REVISAR")) -> OK | L47: =IF(F47="","",Evolucion!C9) -> 61988 | M47: =IF(F47="","",Evolucion!D9) -> 700 | N47: =IF(F47="","",Evolucion!E9) -> 496
E48: =DATE(2025,9,1) -> 45901 | F48: =IF(Evolucion!B10="","",Evolucion!B10) -> 67169 | G48: =IF(F48="","",Evolucion!$C$3+SUMIFS(Movimientos!$B$6:$B$505,Movimientos!$D$6:$D$505,"<="&EOMONTH(E48,0),Movimientos!$D$6:$D$505,">="&DATE(2025,2,1))) -> 57328 | H48: =IF(F48="","",F48-G48) -> 9841 | I48: =IF(Evolucion!F10="","",Evolucion!F10/100) -> 0.05199101 | J48: =IF(Comparativa!E9="","",Comparativa!E9/100) -> 0.0281 | K48: =IF(F48="","SIN DATO",IF(AND(ISNUMBER(I48),ABS(F48-L48-M48-N48)<0.01,ABS(I48-IFERROR((F48-L48-M48)/L48,999))<0.00002),"OK","REVISAR")) -> OK | L48: =IF(F48="","",Evolucion!C10) -> 63184 | M48: =IF(F48="","",Evolucion!D10) -> 700 | N48: =IF(F48="","",Evolucion!E10) -> 3285
E49: =DATE(2025,10,1) -> 45931 | F49: =IF(Evolucion!B11="","",Evolucion!B11) -> 69786 | G49: =IF(F49="","",Evolucion!$C$3+SUMIFS(Movimientos!$B$6:$B$505,Movimientos!$D$6:$D$505,"<="&EOMONTH(E49,0),Movimientos!$D$6:$D$505,">="&DATE(2025,2,1))) -> 58028 | H49: =IF(F49="","",F49-G49) -> 11758 | I49: =IF(Evolucion!F11="","",Evolucion!F11/100) -> 0.028539951 | J49: =IF(Comparativa!E10="","",Comparativa!E10/100) -> 0.0383 | K49: =IF(F49="","SIN DATO",IF(AND(ISNUMBER(I49),ABS(F49-L49-M49-N49)<0.01,ABS(I49-IFERROR((F49-L49-M49)/L49,999))<0.00002),"OK","REVISAR")) -> OK | L49: =IF(F49="","",Evolucion!C11) -> 67169 | M49: =IF(F49="","",Evolucion!D11) -> 700 | N49: =IF(F49="","",Evolucion!E11) -> 1917
E50: =DATE(2025,11,1) -> 45962 | F50: =IF(Evolucion!B12="","",Evolucion!B12) -> 70299 | G50: =IF(F50="","",Evolucion!$C$3+SUMIFS(Movimientos!$B$6:$B$505,Movimientos!$D$6:$D$505,"<="&EOMONTH(E50,0),Movimientos!$D$6:$D$505,">="&DATE(2025,2,1))) -> 58728 | H50: =IF(F50="","",F50-G50) -> 11571 | I50: =IF(Evolucion!F12="","",Evolucion!F12/100) -> -0.0026796206 | J50: =IF(Comparativa!E11="","",Comparativa!E11/100) -> -0.0027 | K50: =IF(F50="","SIN DATO",IF(AND(ISNUMBER(I50),ABS(F50-L50-M50-N50)<0.01,ABS(I50-IFERROR((F50-L50-M50)/L50,999))<0.00002),"OK","REVISAR")) -> OK | L50: =IF(F50="","",Evolucion!C12) -> 69786 | M50: =IF(F50="","",Evolucion!D12) -> 700 | N50: =IF(F50="","",Evolucion!E12) -> -187
E51: =DATE(2025,12,1) -> 45992 | F51: =IF(Evolucion!B13="","",Evolucion!B13) -> 73708 | G51: =IF(F51="","",Evolucion!$C$3+SUMIFS(Movimientos!$B$6:$B$505,Movimientos!$D$6:$D$505,"<="&EOMONTH(E51,0),Movimientos!$D$6:$D$505,">="&DATE(2025,2,1))) -> 59428 | H51: =IF(F51="","",F51-G51) -> 14280 | I51: =IF(Evolucion!F13="","",Evolucion!F13/100) -> 0.038535399 | J51: =IF(Comparativa!E12="","",Comparativa!E12/100) -> -0.004 | K51: =IF(F51="","SIN DATO",IF(AND(ISNUMBER(I51),ABS(F51-L51-M51-N51)<0.01,ABS(I51-IFERROR((F51-L51-M51)/L51,999))<0.00002),"OK","REVISAR")) -> OK | L51: =IF(F51="","",Evolucion!C13) -> 70299 | M51: =IF(F51="","",Evolucion!D13) -> 700 | N51: =IF(F51="","",Evolucion!E13) -> 2709
E52: =DATE(2026,1,1) -> 46023 | F52: =IF(Evolucion!B19="","",Evolucion!B19) -> 76000 | G52: =IF(F52="","",Evolucion!$C$3+SUMIFS(Movimientos!$B$6:$B$505,Movimientos!$D$6:$D$505,"<="&EOMONTH(E52,0),Movimientos!$D$6:$D$505,">="&DATE(2025,2,1))) -> 59928 | H52: =IF(F52="","",F52-G52) -> 16072 | I52: =IF(Evolucion!F19="","",Evolucion!F19/100) -> 0.024312151 | J52: =IF(Comparativa!E13="","",Comparativa!E13/100) -> 0.0092 | K52: =IF(F52="","SIN DATO",IF(AND(ISNUMBER(I52),ABS(F52-L52-M52-N52)<0.01,ABS(I52-IFERROR((F52-L52-M52)/L52,999))<0.00002),"OK","REVISAR")) -> OK | L52: =IF(F52="","",Evolucion!C19) -> 73708 | M52: =IF(F52="","",Evolucion!D19) -> 500 | N52: =IF(F52="","",Evolucion!E19) -> 1792
E53: =DATE(2026,2,1) -> 46054 | F53: =IF(Evolucion!B20="","",Evolucion!B20) -> 76422 | G53: =IF(F53="","",Evolucion!$C$3+SUMIFS(Movimientos!$B$6:$B$505,Movimientos!$D$6:$D$505,"<="&EOMONTH(E53,0),Movimientos!$D$6:$D$505,">="&DATE(2025,2,1))) -> 60628 | H53: =IF(F53="","",F53-G53) -> 15794 | I53: =IF(Evolucion!F20="","",Evolucion!F20/100) -> -0.0036578947 | J53: =IF(Comparativa!E14="","",Comparativa!E14/100) -> 0.0149 | K53: =IF(F53="","SIN DATO",IF(AND(ISNUMBER(I53),ABS(F53-L53-M53-N53)<0.01,ABS(I53-IFERROR((F53-L53-M53)/L53,999))<0.00002),"OK","REVISAR")) -> OK | L53: =IF(F53="","",Evolucion!C20) -> 76000 | M53: =IF(F53="","",Evolucion!D20) -> 700 | N53: =IF(F53="","",Evolucion!E20) -> -278
E54: =DATE(2026,3,1) -> 46082 | F54: =IF(Evolucion!B21="","",Evolucion!B21) -> 72950 | G54: =IF(F54="","",Evolucion!$C$3+SUMIFS(Movimientos!$B$6:$B$505,Movimientos!$D$6:$D$505,"<="&EOMONTH(E54,0),Movimientos!$D$6:$D$505,">="&DATE(2025,2,1))) -> 61228 | H54: =IF(F54="","",F54-G54) -> 11722 | I54: =IF(Evolucion!F21="","",Evolucion!F21/100) -> -0.053283086 | J54: =IF(Comparativa!E15="","",Comparativa!E15/100) -> -0.0404 | K54: =IF(F54="","SIN DATO",IF(AND(ISNUMBER(I54),ABS(F54-L54-M54-N54)<0.01,ABS(I54-IFERROR((F54-L54-M54)/L54,999))<0.00002),"OK","REVISAR")) -> OK | L54: =IF(F54="","",Evolucion!C21) -> 76422 | M54: =IF(F54="","",Evolucion!D21) -> 600 | N54: =IF(F54="","",Evolucion!E21) -> -4072
E55: =DATE(2026,4,1) -> 46113 | F55: =IF(Evolucion!B22="","",Evolucion!B22) -> 76207 | G55: =IF(F55="","",Evolucion!$C$3+SUMIFS(Movimientos!$B$6:$B$505,Movimientos!$D$6:$D$505,"<="&EOMONTH(E55,0),Movimientos!$D$6:$D$505,">="&DATE(2025,2,1))) -> 60528 | H55: =IF(F55="","",F55-G55) -> 15679 | I55: =IF(Evolucion!F22="","",Evolucion!F22/100) -> 0.054242632 | J55: =IF(Comparativa!E16="","",Comparativa!E16/100) -> 0.0765 | K55: =IF(F55="","SIN DATO",IF(AND(ISNUMBER(I55),ABS(F55-L55-M55-N55)<0.01,ABS(I55-IFERROR((F55-L55-M55)/L55,999))<0.00002),"OK","REVISAR")) -> OK | L55: =IF(F55="","",Evolucion!C22) -> 72950 | M55: =IF(F55="","",Evolucion!D22) -> -700 | N55: =IF(F55="","",Evolucion!E22) -> 3957
E56: =DATE(2026,5,1) -> 46143 | F56: =IF(Evolucion!B23="","",Evolucion!B23) -> 79485 | G56: =IF(F56="","",Evolucion!$C$3+SUMIFS(Movimientos!$B$6:$B$505,Movimientos!$D$6:$D$505,"<="&EOMONTH(E56,0),Movimientos!$D$6:$D$505,">="&DATE(2025,2,1))) -> 59828 | H56: =IF(F56="","",F56-G56) -> 19657 | I56: =IF(Evolucion!F23="","",Evolucion!F23/100) -> 0.052199929 | J56: =IF(Comparativa!E17="","",Comparativa!E17/100) -> 0.051 | K56: =IF(F56="","SIN DATO",IF(AND(ISNUMBER(I56),ABS(F56-L56-M56-N56)<0.01,ABS(I56-IFERROR((F56-L56-M56)/L56,999))<0.00002),"OK","REVISAR")) -> OK | L56: =IF(F56="","",Evolucion!C23) -> 76207 | M56: =IF(F56="","",Evolucion!D23) -> -700 | N56: =IF(F56="","",Evolucion!E23) -> 3978
E57: =DATE(2026,6,1) -> 46174 | F57: =IF(Evolucion!B24="","",Evolucion!B24) -> 76115 | G57: =IF(F57="","",Evolucion!$C$3+SUMIFS(Movimientos!$B$6:$B$505,Movimientos!$D$6:$D$505,"<="&EOMONTH(E57,0),Movimientos!$D$6:$D$505,">="&DATE(2025,2,1))) -> 56388 | H57: =IF(F57="","",F57-G57) -> 19727 | I57: =IF(Evolucion!F24="","",Evolucion!F24/100) -> 0.00088066931 | J57: =IF(Comparativa!E18="","",Comparativa!E18/100) -> 0.0133 | K57: =IF(F57="","SIN DATO",IF(AND(ISNUMBER(I57),ABS(F57-L57-M57-N57)<0.01,ABS(I57-IFERROR((F57-L57-M57)/L57,999))<0.00002),"OK","REVISAR")) -> OK | L57: =IF(F57="","",Evolucion!C24) -> 79485 | M57: =IF(F57="","",Evolucion!D24) -> -3440 | N57: =IF(F57="","",Evolucion!E24) -> 70
E58: =DATE(2026,7,1) -> 46204 | F58: =IF(Evolucion!B25="","",Evolucion!B25) -> 83862 | G58: =IF(F58="","",Evolucion!$C$3+SUMIFS(Movimientos!$B$6:$B$505,Movimientos!$D$6:$D$505,"<="&EOMONTH(E58,0),Movimientos!$D$6:$D$505,">="&DATE(2025,2,1))) -> 62388 | H58: =IF(F58="","",F58-G58) -> 21474 | I58: =IF(Evolucion!F25="","",Evolucion!F25/100) -> 0.022952112 | J58: =IF(Comparativa!E19="","",Comparativa!E19/100) -> -0.0014 | K58: =IF(F58="","SIN DATO",IF(AND(ISNUMBER(I58),ABS(F58-L58-M58-N58)<0.01,ABS(I58-IFERROR((F58-L58-M58)/L58,999))<0.00002),"OK","REVISAR")) -> OK | L58: =IF(F58="","",Evolucion!C25) -> 76115 | M58: =IF(F58="","",Evolucion!D25) -> 6000 | N58: =IF(F58="","",Evolucion!E25) -> 1747
E59: =DATE(2026,8,1) -> 46235 | F59: =IF(Evolucion!B26="","",Evolucion!B26) -> 86713 | G59: =IF(F59="","",Evolucion!$C$3+SUMIFS(Movimientos!$B$6:$B$505,Movimientos!$D$6:$D$505,"<="&EOMONTH(E59,0),Movimientos!$D$6:$D$505,">="&DATE(2025,2,1))) -> 63896 | H59: =IF(F59="","",F59-G59) -> 22817 | I59: =IF(Evolucion!F26="","",Evolucion!F26/100) -> 0.016014405 | J59: =IF(Comparativa!E20="","",Comparativa!E20/100) -> 0.0159 | K59: =IF(F59="","SIN DATO",IF(AND(ISNUMBER(I59),ABS(F59-L59-M59-N59)<0.01,ABS(I59-IFERROR((F59-L59-M59)/L59,999))<0.00002),"OK","REVISAR")) -> OK | L59: =IF(F59="","",Evolucion!C26) -> 83862 | M59: =IF(F59="","",Evolucion!D26) -> 1508 | N59: =IF(F59="","",Evolucion!E26) -> 1343
E60: =DATE(2026,9,1) -> 46266 | F60: =IF(Evolucion!B27="","",Evolucion!B27) -> 85387 | G60: =IF(F60="","",Evolucion!$C$3+SUMIFS(Movimientos!$B$6:$B$505,Movimientos!$D$6:$D$505,"<="&EOMONTH(E60,0),Movimientos!$D$6:$D$505,">="&DATE(2025,2,1))) -> 63896 | H60: =IF(F60="","",F60-G60) -> 21491 | I60: =IF(Evolucion!F27="","",Evolucion!F27/100) -> -0.015291825 | J60: =IF(Comparativa!E21="","",Comparativa!E21/100) -> -0.0082 | K60: =IF(F60="","SIN DATO",IF(AND(ISNUMBER(I60),ABS(F60-L60-M60-N60)<0.01,ABS(I60-IFERROR((F60-L60-M60)/L60,999))<0.00002),"OK","REVISAR")) -> OK | L60: =IF(F60="","",Evolucion!C27) -> 86713 | M60: =IF(F60="","",Evolucion!D27) -> 0 | N60: =IF(F60="","",Evolucion!E27) -> -1326
E61: =DATE(2026,10,1) -> 46296 | F61: =IF(Evolucion!B28="","",Evolucion!B28) | G61: =IF(F61="","",Evolucion!$C$3+SUMIFS(Movimientos!$B$6:$B$505,Movimientos!$D$6:$D$505,"<="&EOMONTH(E61,0),Movimientos!$D$6:$D$505,">="&DATE(2025,2,1))) | H61: =IF(F61="","",F61-G61) | I61: =IF(Evolucion!F28="","",Evolucion!F28/100) | J61: =IF(Comparativa!E22="","",Comparativa!E22/100) | K61: =IF(F61="","SIN DATO",IF(AND(ISNUMBER(I61),ABS(F61-L61-M61-N61)<0.01,ABS(I61-IFERROR((F61-L61-M61)/L61,999))<0.00002),"OK","REVISAR")) -> SIN DATO | L61: =IF(F61="","",Evolucion!C28) | M61: =IF(F61="","",Evolucion!D28) | N61: =IF(F61="","",Evolucion!E28)
E62: =DATE(2026,11,1) -> 46327 | F62: =IF(Evolucion!B29="","",Evolucion!B29) | G62: =IF(F62="","",Evolucion!$C$3+SUMIFS(Movimientos!$B$6:$B$505,Movimientos!$D$6:$D$505,"<="&EOMONTH(E62,0),Movimientos!$D$6:$D$505,">="&DATE(2025,2,1))) | H62: =IF(F62="","",F62-G62) | I62: =IF(Evolucion!F29="","",Evolucion!F29/100) | J62: =IF(Comparativa!E23="","",Comparativa!E23/100) | K62: =IF(F62="","SIN DATO",IF(AND(ISNUMBER(I62),ABS(F62-L62-M62-N62)<0.01,ABS(I62-IFERROR((F62-L62-M62)/L62,999))<0.00002),"OK","REVISAR")) -> SIN DATO | L62: =IF(F62="","",Evolucion!C29) | M62: =IF(F62="","",Evolucion!D29) | N62: =IF(F62="","",Evolucion!E29)
E63: =DATE(2026,12,1) -> 46357 | F63: =IF(Evolucion!B30="","",Evolucion!B30) | G63: =IF(F63="","",Evolucion!$C$3+SUMIFS(Movimientos!$B$6:$B$505,Movimientos!$D$6:$D$505,"<="&EOMONTH(E63,0),Movimientos!$D$6:$D$505,">="&DATE(2025,2,1))) | H63: =IF(F63="","",F63-G63) | I63: =IF(Evolucion!F30="","",Evolucion!F30/100) | J63: =IF(Comparativa!E24="","",Comparativa!E24/100) | K63: =IF(F63="","SIN DATO",IF(AND(ISNUMBER(I63),ABS(F63-L63-M63-N63)<0.01,ABS(I63-IFERROR((F63-L63-M63)/L63,999))<0.00002),"OK","REVISAR")) -> SIN DATO | L63: =IF(F63="","",Evolucion!C30) | M63: =IF(F63="","",Evolucion!D30) | N63: =IF(F63="","",Evolucion!E30)
E64: =DATE(2027,1,1) -> 46388 | F64: =IF(Evolucion!B36="","",Evolucion!B36) | G64: =IF(F64="","",Evolucion!$C$3+SUMIFS(Movimientos!$B$6:$B$505,Movimientos!$D$6:$D$505,"<="&EOMONTH(E64,0),Movimientos!$D$6:$D$505,">="&DATE(2025,2,1))) | H64: =IF(F64="","",F64-G64) | I64: =IF(Evolucion!F36="","",Evolucion!F36/100) | J64: ="" | K64: =IF(F64="","SIN DATO",IF(AND(ISNUMBER(I64),ABS(F64-L64-M64-N64)<0.01,ABS(I64-IFERROR((F64-L64-M64)/L64,999))<0.00002),"OK","REVISAR")) -> SIN DATO | L64: =IF(F64="","",Evolucion!C36) | M64: =IF(F64="","",Evolucion!D36) | N64: =IF(F64="","",Evolucion!E36)
E65: =DATE(2027,2,1) -> 46419 | F65: =IF(Evolucion!B37="","",Evolucion!B37) | G65: =IF(F65="","",Evolucion!$C$3+SUMIFS(Movimientos!$B$6:$B$505,Movimientos!$D$6:$D$505,"<="&EOMONTH(E65,0),Movimientos!$D$6:$D$505,">="&DATE(2025,2,1))) | H65: =IF(F65="","",F65-G65) | I65: =IF(Evolucion!F37="","",Evolucion!F37/100) | J65: ="" | K65: =IF(F65="","SIN DATO",IF(AND(ISNUMBER(I65),ABS(F65-L65-M65-N65)<0.01,ABS(I65-IFERROR((F65-L65-M65)/L65,999))<0.00002),"OK","REVISAR")) -> SIN DATO | L65: =IF(F65="","",Evolucion!C37) | M65: =IF(F65="","",Evolucion!D37) | N65: =IF(F65="","",Evolucion!E37)
E66: =DATE(2027,3,1) -> 46447 | F66: =IF(Evolucion!B38="","",Evolucion!B38) | G66: =IF(F66="","",Evolucion!$C$3+SUMIFS(Movimientos!$B$6:$B$505,Movimientos!$D$6:$D$505,"<="&EOMONTH(E66,0),Movimientos!$D$6:$D$505,">="&DATE(2025,2,1))) | H66: =IF(F66="","",F66-G66) | I66: =IF(Evolucion!F38="","",Evolucion!F38/100) | J66: ="" | K66: =IF(F66="","SIN DATO",IF(AND(ISNUMBER(I66),ABS(F66-L66-M66-N66)<0.01,ABS(I66-IFERROR((F66-L66-M66)/L66,999))<0.00002),"OK","REVISAR")) -> SIN DATO | L66: =IF(F66="","",Evolucion!C38) | M66: =IF(F66="","",Evolucion!D38) | N66: =IF(F66="","",Evolucion!E38)
E67: =DATE(2027,4,1) -> 46478 | F67: =IF(Evolucion!B39="","",Evolucion!B39) | G67: =IF(F67="","",Evolucion!$C$3+SUMIFS(Movimientos!$B$6:$B$505,Movimientos!$D$6:$D$505,"<="&EOMONTH(E67,0),Movimientos!$D$6:$D$505,">="&DATE(2025,2,1))) | H67: =IF(F67="","",F67-G67) | I67: =IF(Evolucion!F39="","",Evolucion!F39/100) | J67: ="" | K67: =IF(F67="","SIN DATO",IF(AND(ISNUMBER(I67),ABS(F67-L67-M67-N67)<0.01,ABS(I67-IFERROR((F67-L67-M67)/L67,999))<0.00002),"OK","REVISAR")) -> SIN DATO | L67: =IF(F67="","",Evolucion!C39) | M67: =IF(F67="","",Evolucion!D39) | N67: =IF(F67="","",Evolucion!E39)
E68: =DATE(2027,5,1) -> 46508 | F68: =IF(Evolucion!B40="","",Evolucion!B40) | G68: =IF(F68="","",Evolucion!$C$3+SUMIFS(Movimientos!$B$6:$B$505,Movimientos!$D$6:$D$505,"<="&EOMONTH(E68,0),Movimientos!$D$6:$D$505,">="&DATE(2025,2,1))) | H68: =IF(F68="","",F68-G68) | I68: =IF(Evolucion!F40="","",Evolucion!F40/100) | J68: ="" | K68: =IF(F68="","SIN DATO",IF(AND(ISNUMBER(I68),ABS(F68-L68-M68-N68)<0.01,ABS(I68-IFERROR((F68-L68-M68)/L68,999))<0.00002),"OK","REVISAR")) -> SIN DATO | L68: =IF(F68="","",Evolucion!C40) | M68: =IF(F68="","",Evolucion!D40) | N68: =IF(F68="","",Evolucion!E40)
E69: =DATE(2027,6,1) -> 46539 | F69: =IF(Evolucion!B41="","",Evolucion!B41) | G69: =IF(F69="","",Evolucion!$C$3+SUMIFS(Movimientos!$B$6:$B$505,Movimientos!$D$6:$D$505,"<="&EOMONTH(E69,0),Movimientos!$D$6:$D$505,">="&DATE(2025,2,1))) | H69: =IF(F69="","",F69-G69) | I69: =IF(Evolucion!F41="","",Evolucion!F41/100) | J69: ="" | K69: =IF(F69="","SIN DATO",IF(AND(ISNUMBER(I69),ABS(F69-L69-M69-N69)<0.01,ABS(I69-IFERROR((F69-L69-M69)/L69,999))<0.00002),"OK","REVISAR")) -> SIN DATO | L69: =IF(F69="","",Evolucion!C41) | M69: =IF(F69="","",Evolucion!D41) | N69: =IF(F69="","",Evolucion!E41)
E70: =DATE(2027,7,1) -> 46569 | F70: =IF(Evolucion!B42="","",Evolucion!B42) | G70: =IF(F70="","",Evolucion!$C$3+SUMIFS(Movimientos!$B$6:$B$505,Movimientos!$D$6:$D$505,"<="&EOMONTH(E70,0),Movimientos!$D$6:$D$505,">="&DATE(2025,2,1))) | H70: =IF(F70="","",F70-G70) | I70: =IF(Evolucion!F42="","",Evolucion!F42/100) | J70: ="" | K70: =IF(F70="","SIN DATO",IF(AND(ISNUMBER(I70),ABS(F70-L70-M70-N70)<0.01,ABS(I70-IFERROR((F70-L70-M70)/L70,999))<0.00002),"OK","REVISAR")) -> SIN DATO | L70: =IF(F70="","",Evolucion!C42) | M70: =IF(F70="","",Evolucion!D42) | N70: =IF(F70="","",Evolucion!E42)
E71: =DATE(2027,8,1) -> 46600 | F71: =IF(Evolucion!B43="","",Evolucion!B43) | G71: =IF(F71="","",Evolucion!$C$3+SUMIFS(Movimientos!$B$6:$B$505,Movimientos!$D$6:$D$505,"<="&EOMONTH(E71,0),Movimientos!$D$6:$D$505,">="&DATE(2025,2,1))) | H71: =IF(F71="","",F71-G71) | I71: =IF(Evolucion!F43="","",Evolucion!F43/100) | J71: ="" | K71: =IF(F71="","SIN DATO",IF(AND(ISNUMBER(I71),ABS(F71-L71-M71-N71)<0.01,ABS(I71-IFERROR((F71-L71-M71)/L71,999))<0.00002),"OK","REVISAR")) -> SIN DATO | L71: =IF(F71="","",Evolucion!C43) | M71: =IF(F71="","",Evolucion!D43) | N71: =IF(F71="","",Evolucion!E43)
E72: =DATE(2027,9,1) -> 46631 | F72: =IF(Evolucion!B44="","",Evolucion!B44) | G72: =IF(F72="","",Evolucion!$C$3+SUMIFS(Movimientos!$B$6:$B$505,Movimientos!$D$6:$D$505,"<="&EOMONTH(E72,0),Movimientos!$D$6:$D$505,">="&DATE(2025,2,1))) | H72: =IF(F72="","",F72-G72) | I72: =IF(Evolucion!F44="","",Evolucion!F44/100) | J72: ="" | K72: =IF(F72="","SIN DATO",IF(AND(ISNUMBER(I72),ABS(F72-L72-M72-N72)<0.01,ABS(I72-IFERROR((F72-L72-M72)/L72,999))<0.00002),"OK","REVISAR")) -> SIN DATO | L72: =IF(F72="","",Evolucion!C44) | M72: =IF(F72="","",Evolucion!D44) | N72: =IF(F72="","",Evolucion!E44)
E73: =DATE(2027,10,1) -> 46661 | F73: =IF(Evolucion!B45="","",Evolucion!B45) | G73: =IF(F73="","",Evolucion!$C$3+SUMIFS(Movimientos!$B$6:$B$505,Movimientos!$D$6:$D$505,"<="&EOMONTH(E73,0),Movimientos!$D$6:$D$505,">="&DATE(2025,2,1))) | H73: =IF(F73="","",F73-G73) | I73: =IF(Evolucion!F45="","",Evolucion!F45/100) | J73: ="" | K73: =IF(F73="","SIN DATO",IF(AND(ISNUMBER(I73),ABS(F73-L73-M73-N73)<0.01,ABS(I73-IFERROR((F73-L73-M73)/L73,999))<0.00002),"OK","REVISAR")) -> SIN DATO | L73: =IF(F73="","",Evolucion!C45) | M73: =IF(F73="","",Evolucion!D45) | N73: =IF(F73="","",Evolucion!E45)
E74: =DATE(2027,11,1) -> 46692 | F74: =IF(Evolucion!B46="","",Evolucion!B46) | G74: =IF(F74="","",Evolucion!$C$3+SUMIFS(Movimientos!$B$6:$B$505,Movimientos!$D$6:$D$505,"<="&EOMONTH(E74,0),Movimientos!$D$6:$D$505,">="&DATE(2025,2,1))) | H74: =IF(F74="","",F74-G74) | I74: =IF(Evolucion!F46="","",Evolucion!F46/100) | J74: ="" | K74: =IF(F74="","SIN DATO",IF(AND(ISNUMBER(I74),ABS(F74-L74-M74-N74)<0.01,ABS(I74-IFERROR((F74-L74-M74)/L74,999))<0.00002),"OK","REVISAR")) -> SIN DATO | L74: =IF(F74="","",Evolucion!C46) | M74: =IF(F74="","",Evolucion!D46) | N74: =IF(F74="","",Evolucion!E46)
E75: =DATE(2027,12,1) -> 46722 | F75: =IF(Evolucion!B47="","",Evolucion!B47) | G75: =IF(F75="","",Evolucion!$C$3+SUMIFS(Movimientos!$B$6:$B$505,Movimientos!$D$6:$D$505,"<="&EOMONTH(E75,0),Movimientos!$D$6:$D$505,">="&DATE(2025,2,1))) | H75: =IF(F75="","",F75-G75) | I75: =IF(Evolucion!F47="","",Evolucion!F47/100) | J75: ="" | K75: =IF(F75="","SIN DATO",IF(AND(ISNUMBER(I75),ABS(F75-L75-M75-N75)<0.01,ABS(I75-IFERROR((F75-L75-M75)/L75,999))<0.00002),"OK","REVISAR")) -> SIN DATO | L75: =IF(F75="","",Evolucion!C47) | M75: =IF(F75="","",Evolucion!D47) | N75: =IF(F75="","",Evolucion!E47)
E80: Mes | F80: Capital neto | G80: Ganancia | J80: Fecha 2025 | K80: Fecha 2026 | L80: Fecha comparativa | N80: Mes | O80: Capital neto | P80: Ganancia
E81: =IFERROR(__xludf.DUMMYFUNCTION("FILTER(CHOOSECOLS(E41:H75,1,3,4),ISNUMBER(F41:F75),E41:E75<EOMONTH(TODAY(),-1)+1)"),45689) -> 45689 | F81: =IFERROR(__xludf.DUMMYFUNCTION("""COMPUTED_VALUE"""),52428) -> 52428 | G81: =IFERROR(__xludf.DUMMYFUNCTION("""COMPUTED_VALUE"""),0) -> 0 | J81: =DATE(2025,2,1) -> 45689 | K81: =DATE(2026,1,1) -> 46023 | L81: =DATE(2025,2,1) -> 45689 | N81: =IF(E41="","",E41) -> 45689 | O81: =IF(G41="","",G41) -> 52428 | P81: =IF(H41="","",H41) -> 0
E82: =IFERROR(__xludf.DUMMYFUNCTION("""COMPUTED_VALUE"""),45717) -> 45717 | F82: =IFERROR(__xludf.DUMMYFUNCTION("""COMPUTED_VALUE"""),53128) -> 53128 | G82: =IFERROR(__xludf.DUMMYFUNCTION("""COMPUTED_VALUE"""),2011) -> 2011 | J82: =EDATE(J81,1) -> 45717 | K82: =EDATE(K81,1) -> 46054 | L82: =EDATE(L81,1) -> 45717 | N82: =IF(E42="","",E42) -> 45717 | O82: =IF(G42="","",G42) -> 53128 | P82: =IF(H42="","",H42) -> 2011
E83: =IFERROR(__xludf.DUMMYFUNCTION("""COMPUTED_VALUE"""),45748) -> 45748 | F83: =IFERROR(__xludf.DUMMYFUNCTION("""COMPUTED_VALUE"""),53828) -> 53828 | G83: =IFERROR(__xludf.DUMMYFUNCTION("""COMPUTED_VALUE"""),3205) -> 3205 | J83: =EDATE(J82,1) -> 45748 | K83: =EDATE(K82,1) -> 46082 | L83: =EDATE(L82,1) -> 45748 | N83: =IF(E43="","",E43) -> 45748 | O83: =IF(G43="","",G43) -> 53828 | P83: =IF(H43="","",H43) -> 3205
E84: =IFERROR(__xludf.DUMMYFUNCTION("""COMPUTED_VALUE"""),45778) -> 45778 | F84: =IFERROR(__xludf.DUMMYFUNCTION("""COMPUTED_VALUE"""),54528) -> 54528 | G84: =IFERROR(__xludf.DUMMYFUNCTION("""COMPUTED_VALUE"""),4500) -> 4500 | J84: =EDATE(J83,1) -> 45778 | K84: =EDATE(K83,1) -> 46113 | L84: =EDATE(L83,1) -> 45778 | N84: =IF(E44="","",E44) -> 45778 | O84: =IF(G44="","",G44) -> 54528 | P84: =IF(H44="","",H44) -> 4500
E85: =IFERROR(__xludf.DUMMYFUNCTION("""COMPUTED_VALUE"""),45809) -> 45809 | F85: =IFERROR(__xludf.DUMMYFUNCTION("""COMPUTED_VALUE"""),55228) -> 55228 | G85: =IFERROR(__xludf.DUMMYFUNCTION("""COMPUTED_VALUE"""),5157) -> 5157 | J85: =EDATE(J84,1) -> 45809 | K85: =EDATE(K84,1) -> 46143 | L85: =EDATE(L84,1) -> 45809 | N85: =IF(E45="","",E45) -> 45809 | O85: =IF(G45="","",G45) -> 55228 | P85: =IF(H45="","",H45) -> 5157
E86: =IFERROR(__xludf.DUMMYFUNCTION("""COMPUTED_VALUE"""),45839) -> 45839 | F86: =IFERROR(__xludf.DUMMYFUNCTION("""COMPUTED_VALUE"""),55928) -> 55928 | G86: =IFERROR(__xludf.DUMMYFUNCTION("""COMPUTED_VALUE"""),6060) -> 6060 | J86: =EDATE(J85,1) -> 45839 | K86: =EDATE(K85,1) -> 46174 | L86: =EDATE(L85,1) -> 45839 | N86: =IF(E46="","",E46) -> 45839 | O86: =IF(G46="","",G46) -> 55928 | P86: =IF(H46="","",H46) -> 6060
E87: =IFERROR(__xludf.DUMMYFUNCTION("""COMPUTED_VALUE"""),45870) -> 45870 | F87: =IFERROR(__xludf.DUMMYFUNCTION("""COMPUTED_VALUE"""),56628) -> 56628 | G87: =IFERROR(__xludf.DUMMYFUNCTION("""COMPUTED_VALUE"""),6556) -> 6556 | J87: =EDATE(J86,1) -> 45870 | K87: =EDATE(K86,1) -> 46204 | L87: =EDATE(L86,1) -> 45870 | N87: =IF(E47="","",E47) -> 45870 | O87: =IF(G47="","",G47) -> 56628 | P87: =IF(H47="","",H47) -> 6556
E88: =IFERROR(__xludf.DUMMYFUNCTION("""COMPUTED_VALUE"""),45901) -> 45901 | F88: =IFERROR(__xludf.DUMMYFUNCTION("""COMPUTED_VALUE"""),57328) -> 57328 | G88: =IFERROR(__xludf.DUMMYFUNCTION("""COMPUTED_VALUE"""),9841) -> 9841 | J88: =EDATE(J87,1) -> 45901 | K88: =EDATE(K87,1) -> 46235 | L88: =EDATE(L87,1) -> 45901 | N88: =IF(E48="","",E48) -> 45901 | O88: =IF(G48="","",G48) -> 57328 | P88: =IF(H48="","",H48) -> 9841
E89: =IFERROR(__xludf.DUMMYFUNCTION("""COMPUTED_VALUE"""),45931) -> 45931 | F89: =IFERROR(__xludf.DUMMYFUNCTION("""COMPUTED_VALUE"""),58028) -> 58028 | G89: =IFERROR(__xludf.DUMMYFUNCTION("""COMPUTED_VALUE"""),11758) -> 11758 | J89: =EDATE(J88,1) -> 45931 | K89: =EDATE(K88,1) -> 46266 | L89: =EDATE(L88,1) -> 45931 | N89: =IF(E49="","",E49) -> 45931 | O89: =IF(G49="","",G49) -> 58028 | P89: =IF(H49="","",H49) -> 11758
E90: =IFERROR(__xludf.DUMMYFUNCTION("""COMPUTED_VALUE"""),45962) -> 45962 | F90: =IFERROR(__xludf.DUMMYFUNCTION("""COMPUTED_VALUE"""),58728) -> 58728 | G90: =IFERROR(__xludf.DUMMYFUNCTION("""COMPUTED_VALUE"""),11571) -> 11571 | J90: =EDATE(J89,1) -> 45962 | K90: =EDATE(K89,1) -> 46296 | L90: =EDATE(L89,1) -> 45962 | N90: =IF(E50="","",E50) -> 45962 | O90: =IF(G50="","",G50) -> 58728 | P90: =IF(H50="","",H50) -> 11571
E91: =IFERROR(__xludf.DUMMYFUNCTION("""COMPUTED_VALUE"""),45992) -> 45992 | F91: =IFERROR(__xludf.DUMMYFUNCTION("""COMPUTED_VALUE"""),59428) -> 59428 | G91: =IFERROR(__xludf.DUMMYFUNCTION("""COMPUTED_VALUE"""),14280) -> 14280 | J91: =EDATE(J90,1) -> 45992 | K91: =EDATE(K90,1) -> 46327 | L91: =EDATE(L90,1) -> 45992 | N91: =IF(E51="","",E51) -> 45992 | O91: =IF(G51="","",G51) -> 59428 | P91: =IF(H51="","",H51) -> 14280
E92: =IFERROR(__xludf.DUMMYFUNCTION("""COMPUTED_VALUE"""),46023) -> 46023 | F92: =IFERROR(__xludf.DUMMYFUNCTION("""COMPUTED_VALUE"""),59928) -> 59928 | G92: =IFERROR(__xludf.DUMMYFUNCTION("""COMPUTED_VALUE"""),16072) -> 16072 | K92: =EDATE(K91,1) -> 46357 | L92: =EDATE(L91,1) -> 46023 | N92: Mes | O92: Capital neto | P92: Ganancia
E93: =IFERROR(__xludf.DUMMYFUNCTION("""COMPUTED_VALUE"""),46054) -> 46054 | F93: =IFERROR(__xludf.DUMMYFUNCTION("""COMPUTED_VALUE"""),60628) -> 60628 | G93: =IFERROR(__xludf.DUMMYFUNCTION("""COMPUTED_VALUE"""),15794) -> 15794 | L93: =EDATE(L92,1) -> 46054 | N93: =IF(E52="","",E52) -> 46023 | O93: =IF(G52="","",G52) -> 59928 | P93: =IF(H52="","",H52) -> 16072
E94: =IFERROR(__xludf.DUMMYFUNCTION("""COMPUTED_VALUE"""),46082) -> 46082 | F94: =IFERROR(__xludf.DUMMYFUNCTION("""COMPUTED_VALUE"""),61228) -> 61228 | G94: =IFERROR(__xludf.DUMMYFUNCTION("""COMPUTED_VALUE"""),11722) -> 11722 | L94: =EDATE(L93,1) -> 46082 | N94: =IF(E53="","",E53) -> 46054 | O94: =IF(G53="","",G53) -> 60628 | P94: =IF(H53="","",H53) -> 15794
E95: =IFERROR(__xludf.DUMMYFUNCTION("""COMPUTED_VALUE"""),46113) -> 46113 | F95: =IFERROR(__xludf.DUMMYFUNCTION("""COMPUTED_VALUE"""),60528) -> 60528 | G95: =IFERROR(__xludf.DUMMYFUNCTION("""COMPUTED_VALUE"""),15679) -> 15679 | L95: =EDATE(L94,1) -> 46113 | N95: =IF(E54="","",E54) -> 46082 | O95: =IF(G54="","",G54) -> 61228 | P95: =IF(H54="","",H54) -> 11722
E96: =IFERROR(__xludf.DUMMYFUNCTION("""COMPUTED_VALUE"""),46143) -> 46143 | F96: =IFERROR(__xludf.DUMMYFUNCTION("""COMPUTED_VALUE"""),59828) -> 59828 | G96: =IFERROR(__xludf.DUMMYFUNCTION("""COMPUTED_VALUE"""),19657) -> 19657 | L96: =EDATE(L95,1) -> 46143 | N96: =IF(E55="","",E55) -> 46113 | O96: =IF(G55="","",G55) -> 60528 | P96: =IF(H55="","",H55) -> 15679
E97: =IFERROR(__xludf.DUMMYFUNCTION("""COMPUTED_VALUE"""),46174) -> 46174 | F97: =IFERROR(__xludf.DUMMYFUNCTION("""COMPUTED_VALUE"""),56388) -> 56388 | G97: =IFERROR(__xludf.DUMMYFUNCTION("""COMPUTED_VALUE"""),19727) -> 19727 | L97: =EDATE(L96,1) -> 46174 | N97: =IF(E56="","",E56) -> 46143 | O97: =IF(G56="","",G56) -> 59828 | P97: =IF(H56="","",H56) -> 19657
E98: =IFERROR(__xludf.DUMMYFUNCTION("""COMPUTED_VALUE"""),46204) -> 46204 | F98: =IFERROR(__xludf.DUMMYFUNCTION("""COMPUTED_VALUE"""),62388) -> 62388 | G98: =IFERROR(__xludf.DUMMYFUNCTION("""COMPUTED_VALUE"""),21474) -> 21474 | L98: =EDATE(L97,1) -> 46204 | N98: =IF(E57="","",E57) -> 46174 | O98: =IF(G57="","",G57) -> 56388 | P98: =IF(H57="","",H57) -> 19727
E99: =IFERROR(__xludf.DUMMYFUNCTION("""COMPUTED_VALUE"""),46235) -> 46235 | F99: =IFERROR(__xludf.DUMMYFUNCTION("""COMPUTED_VALUE"""),63896) -> 63896 | G99: =IFERROR(__xludf.DUMMYFUNCTION("""COMPUTED_VALUE"""),22817) -> 22817 | L99: =EDATE(L98,1) -> 46235 | N99: =IF(E58="","",E58) -> 46204 | O99: =IF(G58="","",G58) -> 62388 | P99: =IF(H58="","",H58) -> 21474
L100: =EDATE(L99,1) -> 46266 | N100: =IF(E59="","",E59) -> 46235 | O100: =IF(G59="","",G59) -> 63896 | P100: =IF(H59="","",H59) -> 22817
L101: =EDATE(L100,1) -> 46296 | N101: =IF(E60="","",E60) -> 46266 | O101: =IF(G60="","",G60) -> 63896 | P101: =IF(H60="","",H60) -> 21491
L102: =EDATE(L101,1) -> 46327 | N102: =IF(E61="","",E61) -> 46296 | O102: =IF(G61="","",G61) | P102: =IF(H61="","",H61)
L103: =EDATE(L102,1) -> 46357 | N103: =IF(E62="","",E62) -> 46327 | O103: =IF(G62="","",G62) | P103: =IF(H62="","",H62)
N104: =IF(E63="","",E63) -> 46357 | O104: =IF(G63="","",G63) | P104: =IF(H63="","",H63)

Sheet Calendario
A1: CALENDARIO DEL PORTFOLIO · 2026
A2: Vista anual de consulta. Introduce los valores en Diario y las aportaciones o retiradas en Movimientos. Amarillo: valores diarios · Verde: cierres históricos. | I2: VOLATILIDAD DIARIA | M2: =IF(COUNT('Datos diarios'!D2:D366)>=2,TRUNC(STDEV('Datos diarios'!D2:D366)*SQRT(252),2),"—") -> 6 | Q2: MÉTODO ACTIVO | U2: =IF(COUNT('Datos diarios'!D2:D366)>=2,"Diario (√252)","Mensual histórico") -> Diario (√252)
I3: OBSERVACIONES DIARIAS | M3: =COUNT('Datos diarios'!D2:D366) -> 54 | Q3: ÚLTIMO DATO | U3: =IFERROR(__xludf.DUMMYFUNCTION("IFERROR(MAX(FILTER('Datos diarios'!A2:A366,'Datos diarios'!B2:B366<>"""")),""—"")"),46275) -> 46275
I4: LEYENDA · Verde: cierre mensual/base · Amarillo: entrada diaria · Gris: fin de semana
A6: ENERO | I6: FEBRERO | Q6: MARZO
A7: L | B7: M | C7: X | D7: J | E7: V | F7: S | G7: D | I7: L | J7: M | K7: X | L7: J | M7: V | N7: S | O7: D | Q7: L | R7: M | S7: X | T7: J | U7: V | V7: S | W7: D
D8: 1 | E8: 2 | F8: 3 | G8: 4 | O8: 1 | W8: 1
D9: =IF(Diario!B6="","",Diario!B6) | E9: =IF(Diario!B7="","",Diario!B7) | F9: =IF(Diario!B8="","",Diario!B8) | G9: =IF(Diario!B9="","",Diario!B9) | O9: =IF(Diario!B37="","",Diario!B37) | W9: =IF(Diario!B65="","",Diario!B65)
A10: 5 | B10: 6 | C10: 7 | D10: 8 | E10: 9 | F10: 10 | G10: 11 | I10: 2 | J10: 3 | K10: 4 | L10: 5 | M10: 6 | N10: 7 | O10: 8 | Q10: 2 | R10: 3 | S10: 4 | T10: 5 | U10: 6 | V10: 7 | W10: 8
A11: =IF(Diario!B10="","",Diario!B10) | B11: =IF(Diario!B11="","",Diario!B11) | C11: =IF(Diario!B12="","",Diario!B12) | D11: =IF(Diario!B13="","",Diario!B13) | E11: =IF(Diario!B14="","",Diario!B14) | F11: =IF(Diario!B15="","",Diario!B15) | G11: =IF(Diario!B16="","",Diario!B16) | I11: =IF(Diario!B38="","",Diario!B38) | J11: =IF(Diario!B39="","",Diario!B39) | K11: =IF(Diario!B40="","",Diario!B40) | L11: =IF(Diario!B41="","",Diario!B41) | M11: =IF(Diario!B42="","",Diario!B42) | N11: =IF(Diario!B43="","",Diario!B43) | O11: =IF(Diario!B44="","",Diario!B44) | Q11: =IF(Diario!B66="","",Diario!B66) | R11: =IF(Diario!B67="","",Diario!B67) | S11: =IF(Diario!B68="","",Diario!B68) | T11: =IF(Diario!B69="","",Diario!B69) | U11: =IF(Diario!B70="","",Diario!B70) | V11: =IF(Diario!B71="","",Diario!B71) | W11: =IF(Diario!B72="","",Diario!B72)
A12: 12 | B12: 13 | C12: 14 | D12: 15 | E12: 16 | F12: 17 | G12: 18 | I12: 9 | J12: 10 | K12: 11 | L12: 12 | M12: 13 | N12: 14 | O12: 15 | Q12: 9 | R12: 10 | S12: 11 | T12: 12 | U12: 13 | V12: 14 | W12: 15
A13: =IF(Diario!B17="","",Diario!B17) | B13: =IF(Diario!B18="","",Diario!B18) | C13: =IF(Diario!B19="","",Diario!B19) | D13: =IF(Diario!B20="","",Diario!B20) | E13: =IF(Diario!B21="","",Diario!B21) | F13: =IF(Diario!B22="","",Diario!B22) | G13: =IF(Diario!B23="","",Diario!B23) | I13: =IF(Diario!B45="","",Diario!B45) | J13: =IF(Diario!B46="","",Diario!B46) | K13: =IF(Diario!B47="","",Diario!B47) | L13: =IF(Diario!B48="","",Diario!B48) | M13: =IF(Diario!B49="","",Diario!B49) | N13: =IF(Diario!B50="","",Diario!B50) | O13: =IF(Diario!B51="","",Diario!B51) | Q13: =IF(Diario!B73="","",Diario!B73) | R13: =IF(Diario!B74="","",Diario!B74) | S13: =IF(Diario!B75="","",Diario!B75) | T13: =IF(Diario!B76="","",Diario!B76) | U13: =IF(Diario!B77="","",Diario!B77) | V13: =IF(Diario!B78="","",Diario!B78) | W13: =IF(Diario!B79="","",Diario!B79)
A14: 19 | B14: 20 | C14: 21 | D14: 22 | E14: 23 | F14: 24 | G14: 25 | I14: 16 | J14: 17 | K14: 18 | L14: 19 | M14: 20 | N14: 21 | O14: 22 | Q14: 16 | R14: 17 | S14: 18 | T14: 19 | U14: 20 | V14: 21 | W14: 22
A15: =IF(Diario!B24="","",Diario!B24) | B15: =IF(Diario!B25="","",Diario!B25) | C15: =IF(Diario!B26="","",Diario!B26) | D15: =IF(Diario!B27="","",Diario!B27) | E15: =IF(Diario!B28="","",Diario!B28) | F15: =IF(Diario!B29="","",Diario!B29) | G15: =IF(Diario!B30="","",Diario!B30) | I15: =IF(Diario!B52="","",Diario!B52) | J15: =IF(Diario!B53="","",Diario!B53) | K15: =IF(Diario!B54="","",Diario!B54) | L15: =IF(Diario!B55="","",Diario!B55) | M15: =IF(Diario!B56="","",Diario!B56) | N15: =IF(Diario!B57="","",Diario!B57) | O15: =IF(Diario!B58="","",Diario!B58) | Q15: =IF(Diario!B80="","",Diario!B80) | R15: =IF(Diario!B81="","",Diario!B81) | S15: =IF(Diario!B82="","",Diario!B82) | T15: =IF(Diario!B83="","",Diario!B83) | U15: =IF(Diario!B84="","",Diario!B84) | V15: =IF(Diario!B85="","",Diario!B85) | W15: =IF(Diario!B86="","",Diario!B86)
A16: 26 | B16: 27 | C16: 28 | D16: 29 | E16: 30 | F16: 31 | I16: 23 | J16: 24 | K16: 25 | L16: 26 | M16: 27 | N16: 28 | Q16: 23 | R16: 24 | S16: 25 | T16: 26 | U16: 27 | V16: 28 | W16: 29
A17: =IF(Diario!B31="","",Diario!B31) | B17: =IF(Diario!B32="","",Diario!B32) | C17: =IF(Diario!B33="","",Diario!B33) | D17: =IF(Diario!B34="","",Diario!B34) | E17: =IF(Diario!B35="","",Diario!B35) -> 76000 | F17: =IF(Diario!B36="","",Diario!B36) | I17: =IF(Diario!B59="","",Diario!B59) | J17: =IF(Diario!B60="","",Diario!B60) | K17: =IF(Diario!B61="","",Diario!B61) | L17: =IF(Diario!B62="","",Diario!B62) | M17: =IF(Diario!B63="","",Diario!B63) -> 76422 | N17: =IF(Diario!B64="","",Diario!B64) | Q17: =IF(Diario!B87="","",Diario!B87) | R17: =IF(Diario!B88="","",Diario!B88) | S17: =IF(Diario!B89="","",Diario!B89) | T17: =IF(Diario!B90="","",Diario!B90) | U17: =IF(Diario!B91="","",Diario!B91) | V17: =IF(Diario!B92="","",Diario!B92) | W17: =IF(Diario!B93="","",Diario!B93)
Q18: 30 | R18: 31
Q19: =IF(Diario!B94="","",Diario!B94) | R19: =IF(Diario!B95="","",Diario!B95) -> 72950
A22: ABRIL | I22: MAYO | Q22: JUNIO
A23: L | B23: M | C23: X | D23: J | E23: V | F23: S | G23: D | I23: L | J23: M | K23: X | L23: J | M23: V | N23: S | O23: D | Q23: L | R23: M | S23: X | T23: J | U23: V | V23: S | W23: D
C24: 1 | D24: 2 | E24: 3 | F24: 4 | G24: 5 | M24: 1 | N24: 2 | O24: 3 | Q24: 1 | R24: 2 | S24: 3 | T24: 4 | U24: 5 | V24: 6 | W24: 7
C25: =IF(Diario!B96="","",Diario!B96) | D25: =IF(Diario!B97="","",Diario!B97) | E25: =IF(Diario!B98="","",Diario!B98) | F25: =IF(Diario!B99="","",Diario!B99) | G25: =IF(Diario!B100="","",Diario!B100) | M25: =IF(Diario!B126="","",Diario!B126) | N25: =IF(Diario!B127="","",Diario!B127) | O25: =IF(Diario!B128="","",Diario!B128) | Q25: =IF(Diario!B157="","",Diario!B157) | R25: =IF(Diario!B158="","",Diario!B158) | S25: =IF(Diario!B159="","",Diario!B159) | T25: =IF(Diario!B160="","",Diario!B160) | U25: =IF(Diario!B161="","",Diario!B161) | V25: =IF(Diario!B162="","",Diario!B162) | W25: =IF(Diario!B163="","",Diario!B163)
A26: 6 | B26: 7 | C26: 8 | D26: 9 | E26: 10 | F26: 11 | G26: 12 | I26: 4 | J26: 5 | K26: 6 | L26: 7 | M26: 8 | N26: 9 | O26: 10 | Q26: 8 | R26: 9 | S26: 10 | T26: 11 | U26: 12 | V26: 13 | W26: 14
A27: =IF(Diario!B101="","",Diario!B101) | B27: =IF(Diario!B102="","",Diario!B102) | C27: =IF(Diario!B103="","",Diario!B103) | D27: =IF(Diario!B104="","",Diario!B104) | E27: =IF(Diario!B105="","",Diario!B105) | F27: =IF(Diario!B106="","",Diario!B106) | G27: =IF(Diario!B107="","",Diario!B107) | I27: =IF(Diario!B129="","",Diario!B129) | J27: =IF(Diario!B130="","",Diario!B130) | K27: =IF(Diario!B131="","",Diario!B131) | L27: =IF(Diario!B132="","",Diario!B132) | M27: =IF(Diario!B133="","",Diario!B133) | N27: =IF(Diario!B134="","",Diario!B134) | O27: =IF(Diario!B135="","",Diario!B135) | Q27: =IF(Diario!B164="","",Diario!B164) | R27: =IF(Diario!B165="","",Diario!B165) | S27: =IF(Diario!B166="","",Diario!B166) | T27: =IF(Diario!B167="","",Diario!B167) | U27: =IF(Diario!B168="","",Diario!B168) | V27: =IF(Diario!B169="","",Diario!B169) | W27: =IF(Diario!B170="","",Diario!B170)
A28: 13 | B28: 14 | C28: 15 | D28: 16 | E28: 17 | F28: 18 | G28: 19 | I28: 11 | J28: 12 | K28: 13 | L28: 14 | M28: 15 | N28: 16 | O28: 17 | Q28: 15 | R28: 16 | S28: 17 | T28: 18 | U28: 19 | V28: 20 | W28: 21
A29: =IF(Diario!B108="","",Diario!B108) | B29: =IF(Diario!B109="","",Diario!B109) | C29: =IF(Diario!B110="","",Diario!B110) | D29: =IF(Diario!B111="","",Diario!B111) | E29: =IF(Diario!B112="","",Diario!B112) | F29: =IF(Diario!B113="","",Diario!B113) | G29: =IF(Diario!B114="","",Diario!B114) | I29: =IF(Diario!B136="","",Diario!B136) | J29: =IF(Diario!B137="","",Diario!B137) | K29: =IF(Diario!B138="","",Diario!B138) | L29: =IF(Diario!B139="","",Diario!B139) | M29: =IF(Diario!B140="","",Diario!B140) | N29: =IF(Diario!B141="","",Diario!B141) | O29: =IF(Diario!B142="","",Diario!B142) | Q29: =IF(Diario!B171="","",Diario!B171) | R29: =IF(Diario!B172="","",Diario!B172) | S29: =IF(Diario!B173="","",Diario!B173) | T29: =IF(Diario!B174="","",Diario!B174) | U29: =IF(Diario!B175="","",Diario!B175) | V29: =IF(Diario!B176="","",Diario!B176) | W29: =IF(Diario!B177="","",Diario!B177)
A30: 20 | B30: 21 | C30: 22 | D30: 23 | E30: 24 | F30: 25 | G30: 26 | I30: 18 | J30: 19 | K30: 20 | L30: 21 | M30: 22 | N30: 23 | O30: 24 | Q30: 22 | R30: 23 | S30: 24 | T30: 25 | U30: 26 | V30: 27 | W30: 28
A31: =IF(Diario!B115="","",Diario!B115) | B31: =IF(Diario!B116="","",Diario!B116) | C31: =IF(Diario!B117="","",Diario!B117) | D31: =IF(Diario!B118="","",Diario!B118) | E31: =IF(Diario!B119="","",Diario!B119) | F31: =IF(Diario!B120="","",Diario!B120) | G31: =IF(Diario!B121="","",Diario!B121) | I31: =IF(Diario!B143="","",Diario!B143) | J31: =IF(Diario!B144="","",Diario!B144) | K31: =IF(Diario!B145="","",Diario!B145) | L31: =IF(Diario!B146="","",Diario!B146) | M31: =IF(Diario!B147="","",Diario!B147) | N31: =IF(Diario!B148="","",Diario!B148) | O31: =IF(Diario!B149="","",Diario!B149) | Q31: =IF(Diario!B178="","",Diario!B178) | R31: =IF(Diario!B179="","",Diario!B179) | S31: =IF(Diario!B180="","",Diario!B180) | T31: =IF(Diario!B181="","",Diario!B181) | U31: =IF(Diario!B182="","",Diario!B182) | V31: =IF(Diario!B183="","",Diario!B183) | W31: =IF(Diario!B184="","",Diario!B184)
A32: 27 | B32: 28 | C32: 29 | D32: 30 | I32: 25 | J32: 26 | K32: 27 | L32: 28 | M32: 29 | N32: 30 | O32: 31 | Q32: 29 | R32: 30
A33: =IF(Diario!B122="","",Diario!B122) | B33: =IF(Diario!B123="","",Diario!B123) | C33: =IF(Diario!B124="","",Diario!B124) | D33: =IF(Diario!B125="","",Diario!B125) -> 76207 | I33: =IF(Diario!B150="","",Diario!B150) | J33: =IF(Diario!B151="","",Diario!B151) | K33: =IF(Diario!B152="","",Diario!B152) | L33: =IF(Diario!B153="","",Diario!B153) | M33: =IF(Diario!B154="","",Diario!B154) -> 79485 | N33: =IF(Diario!B155="","",Diario!B155) | O33: =IF(Diario!B156="","",Diario!B156) | Q33: =IF(Diario!B185="","",Diario!B185) | R33: =IF(Diario!B186="","",Diario!B186) -> 76115
A38: JULIO | I38: AGOSTO | Q38: SEPTIEMBRE
A39: L | B39: M | C39: X | D39: J | E39: V | F39: S | G39: D | I39: L | J39: M | K39: X | L39: J | M39: V | N39: S | O39: D | Q39: L | R39: M | S39: X | T39: J | U39: V | V39: S | W39: D
C40: 1 | D40: 2 | E40: 3 | F40: 4 | G40: 5 | N40: 1 | O40: 2 | R40: 1 | S40: 2 | T40: 3 | U40: 4 | V40: 5 | W40: 6
C41: =IF(Diario!B187="","",Diario!B187) | D41: =IF(Diario!B188="","",Diario!B188) | E41: =IF(Diario!B189="","",Diario!B189) | F41: =IF(Diario!B190="","",Diario!B190) | G41: =IF(Diario!B191="","",Diario!B191) | N41: =IF(Diario!B218="","",Diario!B218) -> 84272 | O41: =IF(Diario!B219="","",Diario!B219) | R41: =IF(Diario!B249="","",Diario!B249) -> 86471 | S41: =IF(Diario!B250="","",Diario!B250) -> 86038 | T41: =IF(Diario!B251="","",Diario!B251) -> 86042 | U41: =IF(Diario!B252="","",Diario!B252) -> 86302 | V41: =IF(Diario!B253="","",Diario!B253) -> 86361 | W41: =IF(Diario!B254="","",Diario!B254) -> 86371
A42: 6 | B42: 7 | C42: 8 | D42: 9 | E42: 10 | F42: 11 | G42: 12 | I42: 3 | J42: 4 | K42: 5 | L42: 6 | M42: 7 | N42: 8 | O42: 9 | Q42: 7 | R42: 8 | S42: 9 | T42: 10 | U42: 11 | V42: 12 | W42: 13
A43: =IF(Diario!B192="","",Diario!B192) | B43: =IF(Diario!B193="","",Diario!B193) | C43: =IF(Diario!B194="","",Diario!B194) | D43: =IF(Diario!B195="","",Diario!B195) -> 77695 | E43: =IF(Diario!B196="","",Diario!B196) -> 77600 | F43: =IF(Diario!B197="","",Diario!B197) -> 77711 | G43: =IF(Diario!B198="","",Diario!B198) | I43: =IF(Diario!B220="","",Diario!B220) -> 84093 | J43: =IF(Diario!B221="","",Diario!B221) -> 84595 | K43: =IF(Diario!B222="","",Diario!B222) -> 84914 | L43: =IF(Diario!B223="","",Diario!B223) -> 85738 | M43: =IF(Diario!B224="","",Diario!B224) -> 85860 | N43: =IF(Diario!B225="","",Diario!B225) -> 85957 | O43: =IF(Diario!B226="","",Diario!B226) | Q43: =IF(Diario!B255="","",Diario!B255) -> 86256 | R43: =IF(Diario!B256="","",Diario!B256) -> 86358 | S43: =IF(Diario!B257="","",Diario!B257) -> 85913 | T43: =IF(Diario!B258="","",Diario!B258) -> 85387 | U43: =IF(Diario!B259="","",Diario!B259) | V43: =IF(Diario!B260="","",Diario!B260) | W43: =IF(Diario!B261="","",Diario!B261)
A44: 13 | B44: 14 | C44: 15 | D44: 16 | E44: 17 | F44: 18 | G44: 19 | I44: 10 | J44: 11 | K44: 12 | L44: 13 | M44: 14 | N44: 15 | O44: 16 | Q44: 14 | R44: 15 | S44: 16 | T44: 17 | U44: 18 | V44: 19 | W44: 20
A45: =IF(Diario!B199="","",Diario!B199) -> 77695 | B45: =IF(Diario!B200="","",Diario!B200) -> 77700 | C45: =IF(Diario!B201="","",Diario!B201) -> 77717 | D45: =IF(Diario!B202="","",Diario!B202) -> 77976 | E45: =IF(Diario!B203="","",Diario!B203) -> 77718 | F45: =IF(Diario!B204="","",Diario!B204) -> 77350 | G45: =IF(Diario!B205="","",Diario!B205) | I45: =IF(Diario!B227="","",Diario!B227) -> 86523 | J45: =IF(Diario!B228="","",Diario!B228) -> 86759 | K45: =IF(Diario!B229="","",Diario!B229) -> 87111 | L45: =IF(Diario!B230="","",Diario!B230) -> 87041 | M45: =IF(Diario!B231="","",Diario!B231) -> 86854 | N45: =IF(Diario!B232="","",Diario!B232) -> 86771 | O45: =IF(Diario!B233="","",Diario!B233) | Q45: =IF(Diario!B262="","",Diario!B262) | R45: =IF(Diario!B263="","",Diario!B263) | S45: =IF(Diario!B264="","",Diario!B264) | T45: =IF(Diario!B265="","",Diario!B265) | U45: =IF(Diario!B266="","",Diario!B266) | V45: =IF(Diario!B267="","",Diario!B267) | W45: =IF(Diario!B268="","",Diario!B268)
A46: 20 | B46: 21 | C46: 22 | D46: 23 | E46: 24 | F46: 25 | G46: 26 | I46: 17 | J46: 18 | K46: 19 | L46: 20 | M46: 21 | N46: 22 | O46: 23 | Q46: 21 | R46: 22 | S46: 23 | T46: 24 | U46: 25 | V46: 26 | W46: 27
A47: =IF(Diario!B206="","",Diario!B206) -> 77138 | B47: =IF(Diario!B207="","",Diario!B207) -> 77050 | C47: =IF(Diario!B208="","",Diario!B208) -> 77305 | D47: =IF(Diario!B209="","",Diario!B209) -> 77010 | E47: =IF(Diario!B210="","",Diario!B210) -> 76860 | F47: =IF(Diario!B211="","",Diario!B211) | G47: =IF(Diario!B212="","",Diario!B212) | I47: =IF(Diario!B234="","",Diario!B234) -> 86631 | J47: =IF(Diario!B235="","",Diario!B235) -> 86146 | K47: =IF(Diario!B236="","",Diario!B236) -> 85203 | L47: =IF(Diario!B237="","",Diario!B237) -> 84628 | M47: =IF(Diario!B238="","",Diario!B238) -> 84640 | N47: =IF(Diario!B239="","",Diario!B239) -> 84847 | O47: =IF(Diario!B240="","",Diario!B240) | Q47: =IF(Diario!B269="","",Diario!B269) | R47: =IF(Diario!B270="","",Diario!B270) | S47: =IF(Diario!B271="","",Diario!B271) | T47: =IF(Diario!B272="","",Diario!B272) | U47: =IF(Diario!B273="","",Diario!B273) | V47: =IF(Diario!B274="","",Diario!B274) | W47: =IF(Diario!B275="","",Diario!B275)
A48: 27 | B48: 28 | C48: 29 | D48: 30 | E48: 31 | I48: 24 | J48: 25 | K48: 26 | L48: 27 | M48: 28 | N48: 29 | O48: 30 | Q48: 28 | R48: 29 | S48: 30
A49: =IF(Diario!B213="","",Diario!B213) -> 83088 | B49: =IF(Diario!B214="","",Diario!B214) -> 83266 | C49: =IF(Diario!B215="","",Diario!B215) -> 83587 | D49: =IF(Diario!B216="","",Diario!B216) -> 84016 | E49: =IF(Diario!B217="","",Diario!B217) -> 83862 | I49: =IF(Diario!B241="","",Diario!B241) -> 84741 | J49: =IF(Diario!B242="","",Diario!B242) -> 84802 | K49: =IF(Diario!B243="","",Diario!B243) -> 85736 | L49: =IF(Diario!B244="","",Diario!B244) -> 86036 | M49: =IF(Diario!B245="","",Diario!B245) -> 86590 | N49: =IF(Diario!B246="","",Diario!B246) -> 86623 | O49: =IF(Diario!B247="","",Diario!B247) | Q49: =IF(Diario!B276="","",Diario!B276) | R49: =IF(Diario!B277="","",Diario!B277) | S49: =IF(Diario!B278="","",Diario!B278)
I50: 31
I51: =IF(Diario!B248="","",Diario!B248) -> 86713
A54: OCTUBRE | I54: NOVIEMBRE | Q54: DICIEMBRE
A55: L | B55: M | C55: X | D55: J | E55: V | F55: S | G55: D | I55: L | J55: M | K55: X | L55: J | M55: V | N55: S | O55: D | Q55: L | R55: M | S55: X | T55: J | U55: V | V55: S | W55: D
D56: 1 | E56: 2 | F56: 3 | G56: 4 | O56: 1 | R56: 1 | S56: 2 | T56: 3 | U56: 4 | V56: 5 | W56: 6
D57: =IF(Diario!B279="","",Diario!B279) | E57: =IF(Diario!B280="","",Diario!B280) | F57: =IF(Diario!B281="","",Diario!B281) | G57: =IF(Diario!B282="","",Diario!B282) | O57: =IF(Diario!B310="","",Diario!B310) | R57: =IF(Diario!B340="","",Diario!B340) | S57: =IF(Diario!B341="","",Diario!B341) | T57: =IF(Diario!B342="","",Diario!B342) | U57: =IF(Diario!B343="","",Diario!B343) | V57: =IF(Diario!B344="","",Diario!B344) | W57: =IF(Diario!B345="","",Diario!B345)
A58: 5 | B58: 6 | C58: 7 | D58: 8 | E58: 9 | F58: 10 | G58: 11 | I58: 2 | J58: 3 | K58: 4 | L58: 5 | M58: 6 | N58: 7 | O58: 8 | Q58: 7 | R58: 8 | S58: 9 | T58: 10 | U58: 11 | V58: 12 | W58: 13
A59: =IF(Diario!B283="","",Diario!B283) | B59: =IF(Diario!B284="","",Diario!B284) | C59: =IF(Diario!B285="","",Diario!B285) | D59: =IF(Diario!B286="","",Diario!B286) | E59: =IF(Diario!B287="","",Diario!B287) | F59: =IF(Diario!B288="","",Diario!B288) | G59: =IF(Diario!B289="","",Diario!B289) | I59: =IF(Diario!B311="","",Diario!B311) | J59: =IF(Diario!B312="","",Diario!B312) | K59: =IF(Diario!B313="","",Diario!B313) | L59: =IF(Diario!B314="","",Diario!B314) | M59: =IF(Diario!B315="","",Diario!B315) | N59: =IF(Diario!B316="","",Diario!B316) | O59: =IF(Diario!B317="","",Diario!B317) | Q59: =IF(Diario!B346="","",Diario!B346) | R59: =IF(Diario!B347="","",Diario!B347) | S59: =IF(Diario!B348="","",Diario!B348) | T59: =IF(Diario!B349="","",Diario!B349) | U59: =IF(Diario!B350="","",Diario!B350) | V59: =IF(Diario!B351="","",Diario!B351) | W59: =IF(Diario!B352="","",Diario!B352)
A60: 12 | B60: 13 | C60: 14 | D60: 15 | E60: 16 | F60: 17 | G60: 18 | I60: 9 | J60: 10 | K60: 11 | L60: 12 | M60: 13 | N60: 14 | O60: 15 | Q60: 14 | R60: 15 | S60: 16 | T60: 17 | U60: 18 | V60: 19 | W60: 20
A61: =IF(Diario!B290="","",Diario!B290) | B61: =IF(Diario!B291="","",Diario!B291) | C61: =IF(Diario!B292="","",Diario!B292) | D61: =IF(Diario!B293="","",Diario!B293) | E61: =IF(Diario!B294="","",Diario!B294) | F61: =IF(Diario!B295="","",Diario!B295) | G61: =IF(Diario!B296="","",Diario!B296) | I61: =IF(Diario!B318="","",Diario!B318) | J61: =IF(Diario!B319="","",Diario!B319) | K61: =IF(Diario!B320="","",Diario!B320) | L61: =IF(Diario!B321="","",Diario!B321) | M61: =IF(Diario!B322="","",Diario!B322) | N61: =IF(Diario!B323="","",Diario!B323) | O61: =IF(Diario!B324="","",Diario!B324) | Q61: =IF(Diario!B353="","",Diario!B353) | R61: =IF(Diario!B354="","",Diario!B354) | S61: =IF(Diario!B355="","",Diario!B355) | T61: =IF(Diario!B356="","",Diario!B356) | U61: =IF(Diario!B357="","",Diario!B357) | V61: =IF(Diario!B358="","",Diario!B358) | W61: =IF(Diario!B359="","",Diario!B359)
A62: 19 | B62: 20 | C62: 21 | D62: 22 | E62: 23 | F62: 24 | G62: 25 | I62: 16 | J62: 17 | K62: 18 | L62: 19 | M62: 20 | N62: 21 | O62: 22 | Q62: 21 | R62: 22 | S62: 23 | T62: 24 | U62: 25 | V62: 26 | W62: 27
A63: =IF(Diario!B297="","",Diario!B297) | B63: =IF(Diario!B298="","",Diario!B298) | C63: =IF(Diario!B299="","",Diario!B299) | D63: =IF(Diario!B300="","",Diario!B300) | E63: =IF(Diario!B301="","",Diario!B301) | F63: =IF(Diario!B302="","",Diario!B302) | G63: =IF(Diario!B303="","",Diario!B303) | I63: =IF(Diario!B325="","",Diario!B325) | J63: =IF(Diario!B326="","",Diario!B326) | K63: =IF(Diario!B327="","",Diario!B327) | L63: =IF(Diario!B328="","",Diario!B328) | M63: =IF(Diario!B329="","",Diario!B329) | N63: =IF(Diario!B330="","",Diario!B330) | O63: =IF(Diario!B331="","",Diario!B331) | Q63: =IF(Diario!B360="","",Diario!B360) | R63: =IF(Diario!B361="","",Diario!B361) | S63: =IF(Diario!B362="","",Diario!B362) | T63: =IF(Diario!B363="","",Diario!B363) | U63: =IF(Diario!B364="","",Diario!B364) | V63: =IF(Diario!B365="","",Diario!B365) | W63: =IF(Diario!B366="","",Diario!B366)
A64: 26 | B64: 27 | C64: 28 | D64: 29 | E64: 30 | F64: 31 | I64: 23 | J64: 24 | K64: 25 | L64: 26 | M64: 27 | N64: 28 | O64: 29 | Q64: 28 | R64: 29 | S64: 30 | T64: 31
A65: =IF(Diario!B304="","",Diario!B304) | B65: =IF(Diario!B305="","",Diario!B305) | C65: =IF(Diario!B306="","",Diario!B306) | D65: =IF(Diario!B307="","",Diario!B307) | E65: =IF(Diario!B308="","",Diario!B308) | F65: =IF(Diario!B309="","",Diario!B309) | I65: =IF(Diario!B332="","",Diario!B332) | J65: =IF(Diario!B333="","",Diario!B333) | K65: =IF(Diario!B334="","",Diario!B334) | L65: =IF(Diario!B335="","",Diario!B335) | M65: =IF(Diario!B336="","",Diario!B336) | N65: =IF(Diario!B337="","",Diario!B337) | O65: =IF(Diario!B338="","",Diario!B338) | Q65: =IF(Diario!B367="","",Diario!B367) | R65: =IF(Diario!B368="","",Diario!B368) | S65: =IF(Diario!B369="","",Diario!B369) | T65: =IF(Diario!B370="","",Diario!B370)
I66: 30
I67: =IF(Diario!B339="","",Diario!B339)
A70: MOVIMIENTOS → REGISTRO ÚNICO
A71: =HYPERLINK("https://docs.google.com/spreadsheets/d/19NBi4nJ9XKfUrlWNGbM50jAMxFWUWCtpNkLKhGpA36M/edit#gid=206090503","Abrir Movimientos") -> Abrir Movimientos | C71: Usa Movimientos: cada entrada se registra una sola vez.

Sheet Datos diarios
A1: Fecha | B1: Valor portfolio | C1: Flujo neto | D1: Retorno diario (%) | E1: Tipo de dato
A2: 46023 | B2: =IF(Diario!B6="","",Diario!B6) | C2: =SUMIFS(Movimientos!$B$6:$B$505,Movimientos!$D$6:$D$505,A2,Movimientos!$E$6:$E$505,TRUE) -> 0 | D2: ="" | E2: =IF(B2="","",IF(OR(A2=DATE(2026,1,30),A2=DATE(2026,2,27),A2=DATE(2026,3,31),A2=DATE(2026,4,30),A2=DATE(2026,5,29),A2=DATE(2026,6,30)),"Histórico mensual",IF(A2=DATE(2026,7,9),"Base diaria",IF(WEEKDAY(A2,2)>5,"Fin de semana","Diario"))))
A3: 46024 | B3: =IF(Diario!B7="","",Diario!B7) | C3: =SUMIFS(Movimientos!$B$6:$B$505,Movimientos!$D$6:$D$505,A3,Movimientos!$E$6:$E$505,TRUE) -> 0 | D3: =IFERROR(__xludf.DUMMYFUNCTION("IF(OR(B3="""",A3>TODAY(),E3=""Histórico mensual"",E3=""Base diaria""),"""",IFERROR(LET(prevDate,MAX(FILTER($A$2:A2,$B$2:B2<>"""",$A$2:A2<A3)),prevValue,XLOOKUP(prevDate,$A$2:A2,$B$2:B2),gap,A3-prevDate,unknown,COUNTIFS(Movimientos!$D$6:$D$505,"">""&prevDa"&"te,Movimientos!$D$6:$D$505,""<=""&A3,Movimientos!$E$6:$E$505,FALSE,Movimientos!$C$6:$C$505,""<>Fecha inferida*""),flow,SUMIFS(Movimientos!$B$6:$B$505,Movimientos!$D$6:$D$505,"">""&prevDate,Movimientos!$D$6:$D$505,""<=""&A3,Movimientos!$E$6:$E$505,TRUE)+SU"&"MIFS(Movimientos!$B$6:$B$505,Movimientos!$D$6:$D$505,"">""&prevDate,Movimientos!$D$6:$D$505,""<=""&A3,Movimientos!$C$6:$C$505,""Fecha inferida*""),net,B3-flow,IF(OR(gap<1,unknown>0,prevValue<=0,net<=0),"""",(POWER(net/prevValue,1/gap)-1)*100)),""""))"),"") | E3: =IF(B3="","",IF(OR(A3=DATE(2026,1,30),A3=DATE(2026,2,27),A3=DATE(2026,3,31),A3=DATE(2026,4,30),A3=DATE(2026,5,29),A3=DATE(2026,6,30)),"Histórico mensual",IF(A3=DATE(2026,7,9),"Base diaria",IF(WEEKDAY(A3,2)>5,"Fin de semana","Diario"))))
A4: 46025 | B4: =IF(Diario!B8="","",Diario!B8) | C4: =SUMIFS(Movimientos!$B$6:$B$505,Movimientos!$D$6:$D$505,A4,Movimientos!$E$6:$E$505,TRUE) -> 0 | D4: =IFERROR(__xludf.DUMMYFUNCTION("IF(OR(B4="""",A4>TODAY(),E4=""Histórico mensual"",E4=""Base diaria""),"""",IFERROR(LET(prevDate,MAX(FILTER($A$2:A3,$B$2:B3<>"""",$A$2:A3<A4)),prevValue,XLOOKUP(prevDate,$A$2:A3,$B$2:B3),gap,A4-prevDate,unknown,COUNTIFS(Movimientos!$D$6:$D$505,"">""&prevDa"&"te,Movimientos!$D$6:$D$505,""<=""&A4,Movimientos!$E$6:$E$505,FALSE,Movimientos!$C$6:$C$505,""<>Fecha inferida*""),flow,SUMIFS(Movimientos!$B$6:$B$505,Movimientos!$D$6:$D$505,"">""&prevDate,Movimientos!$D$6:$D$505,""<=""&A4,Movimientos!$E$6:$E$505,TRUE)+SU"&"MIFS(Movimientos!$B$6:$B$505,Movimientos!$D$6:$D$505,"">""&prevDate,Movimientos!$D$6:$D$505,""<=""&A4,Movimientos!$C$6:$C$505,""Fecha inferida*""),net,B4-flow,IF(OR(gap<1,unknown>0,prevValue<=0,net<=0),"""",(POWER(net/prevValue,1/gap)-1)*100)),""""))"),"") | E4: =IF(B4="","",IF(OR(A4=DATE(2026,1,30),A4=DATE(2026,2,27),A4=DATE(2026,3,31),A4=DATE(2026,4,30),A4=DATE(2026,5,29),A4=DATE(2026,6,30)),"Histórico mensual",IF(A4=DATE(2026,7,9),"Base diaria",IF(WEEKDAY(A4,2)>5,"Fin de semana","Diario"))))
A5: 46026 | B5: =IF(Diario!B9="","",Diario!B9) | C5: =SUMIFS(Movimientos!$B$6:$B$505,Movimientos!$D$6:$D$505,A5,Movimientos!$E$6:$E$505,TRUE) -> 0 | D5: =IFERROR(__xludf.DUMMYFUNCTION("IF(OR(B5="""",A5>TODAY(),E5=""Histórico mensual"",E5=""Base diaria""),"""",IFERROR(LET(prevDate,MAX(FILTER($A$2:A4,$B$2:B4<>"""",$A$2:A4<A5)),prevValue,XLOOKUP(prevDate,$A$2:A4,$B$2:B4),gap,A5-prevDate,unknown,COUNTIFS(Movimientos!$D$6:$D$505,"">""&prevDa"&"te,Movimientos!$D$6:$D$505,""<=""&A5,Movimientos!$E$6:$E$505,FALSE,Movimientos!$C$6:$C$505,""<>Fecha inferida*""),flow,SUMIFS(Movimientos!$B$6:$B$505,Movimientos!$D$6:$D$505,"">""&prevDate,Movimientos!$D$6:$D$505,""<=""&A5,Movimientos!$E$6:$E$505,TRUE)+SU"&"MIFS(Movimientos!$B$6:$B$505,Movimientos!$D$6:$D$505,"">""&prevDate,Movimientos!$D$6:$D$505,""<=""&A5,Movimientos!$C$6:$C$505,""Fecha inferida*""),net,B5-flow,IF(OR(gap<1,unknown>0,prevValue<=0,net<=0),"""",(POWER(net/prevValue,1/gap)-1)*100)),""""))"),"") | E5: =IF(B5="","",IF(OR(A5=DATE(2026,1,30),A5=DATE(2026,2,27),A5=DATE(2026,3,31),A5=DATE(2026,4,30),A5=DATE(2026,5,29),A5=DATE(2026,6,30)),"Histórico mensual",IF(A5=DATE(2026,7,9),"Base diaria",IF(WEEKDAY(A5,2)>5,"Fin de semana","Diario"))))
A6: 46027 | B6: =IF(Diario!B10="","",Diario!B10) | C6: =SUMIFS(Movimientos!$B$6:$B$505,Movimientos!$D$6:$D$505,A6,Movimientos!$E$6:$E$505,TRUE) -> 0 | D6: =IFERROR(__xludf.DUMMYFUNCTION("IF(OR(B6="""",A6>TODAY(),E6=""Histórico mensual"",E6=""Base diaria""),"""",IFERROR(LET(prevDate,MAX(FILTER($A$2:A5,$B$2:B5<>"""",$A$2:A5<A6)),prevValue,XLOOKUP(prevDate,$A$2:A5,$B$2:B5),gap,A6-prevDate,unknown,COUNTIFS(Movimientos!$D$6:$D$505,"">""&prevDa"&"te,Movimientos!$D$6:$D$505,""<=""&A6,Movimientos!$E$6:$E$505,FALSE,Movimientos!$C$6:$C$505,""<>Fecha inferida*""),flow,SUMIFS(Movimientos!$B$6:$B$505,Movimientos!$D$6:$D$505,"">""&prevDate,Movimientos!$D$6:$D$505,""<=""&A6,Movimientos!$E$6:$E$505,TRUE)+SU"&"MIFS(Movimientos!$B$6:$B$505,Movimientos!$D$6:$D$505,"">""&prevDate,Movimientos!$D$6:$D$505,""<=""&A6,Movimientos!$C$6:$C$505,""Fecha inferida*""),net,B6-flow,IF(OR(gap<1,unknown>0,prevValue<=0,net<=0),"""",(POWER(net/prevValue,1/gap)-1)*100)),""""))"),"") | E6: =IF(B6="","",IF(OR(A6=DATE(2026,1,30),A6=DATE(2026,2,27),A6=DATE(2026,3,31),A6=DATE(2026,4,30),A6=DATE(2026,5,29),A6=DATE(2026,6,30)),"Histórico mensual",IF(A6=DATE(2026,7,9),"Base diaria",IF(WEEKDAY(A6,2)>5,"Fin de semana","Diario"))))
A7: 46028 | B7: =IF(Diario!B11="","",Diario!B11) | C7: =SUMIFS(Movimientos!$B$6:$B$505,Movimientos!$D$6:$D$505,A7,Movimientos!$E$6:$E$505,TRUE) -> 0 | D7: =IFERROR(__xludf.DUMMYFUNCTION("IF(OR(B7="""",A7>TODAY(),E7=""Histórico mensual"",E7=""Base diaria""),"""",IFERROR(LET(prevDate,MAX(FILTER($A$2:A6,$B$2:B6<>"""",$A$2:A6<A7)),prevValue,XLOOKUP(prevDate,$A$2:A6,$B$2:B6),gap,A7-prevDate,unknown,COUNTIFS(Movimientos!$D$6:$D$505,"">""&prevDa"&"te,Movimientos!$D$6:$D$505,""<=""&A7,Movimientos!$E$6:$E$505,FALSE,Movimientos!$C$6:$C$505,""<>Fecha inferida*""),flow,SUMIFS(Movimientos!$B$6:$B$505,Movimientos!$D$6:$D$505,"">""&prevDate,Movimientos!$D$6:$D$505,""<=""&A7,Movimientos!$E$6:$E$505,TRUE)+SU"&"MIFS(Movimientos!$B$6:$B$505,Movimientos!$D$6:$D$505,"">""&prevDate,Movimientos!$D$6:$D$505,""<=""&A7,Movimientos!$C$6:$C$505,""Fecha inferida*""),net,B7-flow,IF(OR(gap<1,unknown>0,prevValue<=0,net<=0),"""",(POWER(net/prevValue,1/gap)-1)*100)),""""))"),"") | E7: =IF(B7="","",IF(OR(A7=DATE(2026,1,30),A7=DATE(2026,2,27),A7=DATE(2026,3,31),A7=DATE(2026,4,30),A7=DATE(2026,5,29),A7=DATE(2026,6,30)),"Histórico mensual",IF(A7=DATE(2026,7,9),"Base diaria",IF(WEEKDAY(A7,2)>5,"Fin de semana","Diario"))))
A8: 46029 | B8: =IF(Diario!B12="","",Diario!B12) | C8: =SUMIFS(Movimientos!$B$6:$B$505,Movimientos!$D$6:$D$505,A8,Movimientos!$E$6:$E$505,TRUE) -> 0 | D8: =IFERROR(__xludf.DUMMYFUNCTION("IF(OR(B8="""",A8>TODAY(),E8=""Histórico mensual"",E8=""Base diaria""),"""",IFERROR(LET(prevDate,MAX(FILTER($A$2:A7,$B$2:B7<>"""",$A$2:A7<A8)),prevValue,XLOOKUP(prevDate,$A$2:A7,$B$2:B7),gap,A8-prevDate,unknown,COUNTIFS(Movimientos!$D$6:$D$505,"">""&prevDa"&"te,Movimientos!$D$6:$D$505,""<=""&A8,Movimientos!$E$6:$E$505,FALSE,Movimientos!$C$6:$C$505,""<>Fecha inferida*""),flow,SUMIFS(Movimientos!$B$6:$B$505,Movimientos!$D$6:$D$505,"">""&prevDate,Movimientos!$D$6:$D$505,""<=""&A8,Movimientos!$E$6:$E$505,TRUE)+SU"&"MIFS(Movimientos!$B$6:$B$505,Movimientos!$D$6:$D$505,"">""&prevDate,Movimientos!$D$6:$D$505,""<=""&A8,Movimientos!$C$6:$C$505,""Fecha inferida*""),net,B8-flow,IF(OR(gap<1,unknown>0,prevValue<=0,net<=0),"""",(POWER(net/prevValue,1/gap)-1)*100)),""""))"),"") | E8: =IF(B8="","",IF(OR(A8=DATE(2026,1,30),A8=DATE(2026,2,27),A8=DATE(2026,3,31),A8=DATE(2026,4,30),A8=DATE(2026,5,29),A8=DATE(2026,6,30)),"Histórico mensual",IF(A8=DATE(2026,7,9),"Base diaria",IF(WEEKDAY(A8,2)>5,"Fin de semana","Diario"))))
A9: 46030 | B9: =IF(Diario!B13="","",Diario!B13) | C9: =SUMIFS(Movimientos!$B$6:$B$505,Movimientos!$D$6:$D$505,A9,Movimientos!$E$6:$E$505,TRUE) -> 0 | D9: =IFERROR(__xludf.DUMMYFUNCTION("IF(OR(B9="""",A9>TODAY(),E9=""Histórico mensual"",E9=""Base diaria""),"""",IFERROR(LET(prevDate,MAX(FILTER($A$2:A8,$B$2:B8<>"""",$A$2:A8<A9)),prevValue,XLOOKUP(prevDate,$A$2:A8,$B$2:B8),gap,A9-prevDate,unknown,COUNTIFS(Movimientos!$D$6:$D$505,"">""&prevDa"&"te,Movimientos!$D$6:$D$505,""<=""&A9,Movimientos!$E$6:$E$505,FALSE,Movimientos!$C$6:$C$505,""<>Fecha inferida*""),flow,SUMIFS(Movimientos!$B$6:$B$505,Movimientos!$D$6:$D$505,"">""&prevDate,Movimientos!$D$6:$D$505,""<=""&A9,Movimientos!$E$6:$E$505,TRUE)+SU"&"MIFS(Movimientos!$B$6:$B$505,Movimientos!$D$6:$D$505,"">""&prevDate,Movimientos!$D$6:$D$505,""<=""&A9,Movimientos!$C$6:$C$505,""Fecha inferida*""),net,B9-flow,IF(OR(gap<1,unknown>0,prevValue<=0,net<=0),"""",(POWER(net/prevValue,1/gap)-1)*100)),""""))"),"") | E9: =IF(B9="","",IF(OR(A9=DATE(2026,1,30),A9=DATE(2026,2,27),A9=DATE(2026,3,31),A9=DATE(2026,4,30),A9=DATE(2026,5,29),A9=DATE(2026,6,30)),"Histórico mensual",IF(A9=DATE(2026,7,9),"Base diaria",IF(WEEKDAY(A9,2)>5,"Fin de semana","Diario"))))
A10: 46031 | B10: =IF(Diario!B14="","",Diario!B14) | C10: =SUMIFS(Movimientos!$B$6:$B$505,Movimientos!$D$6:$D$505,A10,Movimientos!$E$6:$E$505,TRUE) -> 0 | D10: =IFERROR(__xludf.DUMMYFUNCTION("IF(OR(B10="""",A10>TODAY(),E10=""Histórico mensual"",E10=""Base diaria""),"""",IFERROR(LET(prevDate,MAX(FILTER($A$2:A9,$B$2:B9<>"""",$A$2:A9<A10)),prevValue,XLOOKUP(prevDate,$A$2:A9,$B$2:B9),gap,A10-prevDate,unknown,COUNTIFS(Movimientos!$D$6:$D$505,"">""&"&"prevDate,Movimientos!$D$6:$D$505,""<=""&A10,Movimientos!$E$6:$E$505,FALSE,Movimientos!$C$6:$C$505,""<>Fecha inferida*""),flow,SUMIFS(Movimientos!$B$6:$B$505,Movimientos!$D$6:$D$505,"">""&prevDate,Movimientos!$D$6:$D$505,""<=""&A10,Movimientos!$E$6:$E$505,"&"TRUE)+SUMIFS(Movimientos!$B$6:$B$505,Movimientos!$D$6:$D$505,"">""&prevDate,Movimientos!$D$6:$D$505,""<=""&A10,Movimientos!$C$6:$C$505,""Fecha inferida*""),net,B10-flow,IF(OR(gap<1,unknown>0,prevValue<=0,net<=0),"""",(POWER(net/prevValue,1/gap)-1)*100)),"&"""""))"),"") | E10: =IF(B10="","",IF(OR(A10=DATE(2026,1,30),A10=DATE(2026,2,27),A10=DATE(2026,3,31),A10=DATE(2026,4,30),A10=DATE(2026,5,29),A10=DATE(2026,6,30)),"Histórico mensual",IF(A10=DATE(2026,7,9),"Base diaria",IF(WEEKDAY(A10,2)>5,"Fin de semana","Diario"))))
A11: 46032 | B11: =IF(Diario!B15="","",Diario!B15) | C11: =SUMIFS(Movimientos!$B$6:$B$505,Movimientos!$D$6:$D$505,A11,Movimientos!$E$6:$E$505,TRUE) -> 0 | D11: =IFERROR(__xludf.DUMMYFUNCTION("IF(OR(B11="""",A11>TODAY(),E11=""Histórico mensual"",E11=""Base diaria""),"""",IFERROR(LET(prevDate,MAX(FILTER($A$2:A10,$B$2:B10<>"""",$A$2:A10<A11)),prevValue,XLOOKUP(prevDate,$A$2:A10,$B$2:B10),gap,A11-prevDate,unknown,COUNTIFS(Movimientos!$D$6:$D$505,"&""">""&prevDate,Movimientos!$D$6:$D$505,""<=""&A11,Movimientos!$E$6:$E$505,FALSE,Movimientos!$C$6:$C$505,""<>Fecha inferida*""),flow,SUMIFS(Movimientos!$B$6:$B$505,Movimientos!$D$6:$D$505,"">""&prevDate,Movimientos!$D$6:$D$505,""<=""&A11,Movimientos!$E$6:$"&"E$505,TRUE)+SUMIFS(Movimientos!$B$6:$B$505,Movimientos!$D$6:$D$505,"">""&prevDate,Movimientos!$D$6:$D$505,""<=""&A11,Movimientos!$C$6:$C$505,""Fecha inferida*""),net,B11-flow,IF(OR(gap<1,unknown>0,prevValue<=0,net<=0),"""",(POWER(net/prevValue,1/gap)-1)*1"&"00)),""""))"),"") | E11: =IF(B11="","",IF(OR(A11=DATE(2026,1,30),A11=DATE(2026,2,27),A11=DATE(2026,3,31),A11=DATE(2026,4,30),A11=DATE(2026,5,29),A11=DATE(2026,6,30)),"Histórico mensual",IF(A11=DATE(2026,7,9),"Base diaria",IF(WEEKDAY(A11,2)>5,"Fin de semana","Diario"))))
A12: 46033 | B12: =IF(Diario!B16="","",Diario!B16) | C12: =SUMIFS(Movimientos!$B$6:$B$505,Movimientos!$D$6:$D$505,A12,Movimientos!$E$6:$E$505,TRUE) -> 0 | D12: =IFERROR(__xludf.DUMMYFUNCTION("IF(OR(B12="""",A12>TODAY(),E12=""Histórico mensual"",E12=""Base diaria""),"""",IFERROR(LET(prevDate,MAX(FILTER($A$2:A11,$B$2:B11<>"""",$A$2:A11<A12)),prevValue,XLOOKUP(prevDate,$A$2:A11,$B$2:B11),gap,A12-prevDate,unknown,COUNTIFS(Movimientos!$D$6:$D$505,"&""">""&prevDate,Movimientos!$D$6:$D$505,""<=""&A12,Movimientos!$E$6:$E$505,FALSE,Movimientos!$C$6:$C$505,""<>Fecha inferida*""),flow,SUMIFS(Movimientos!$B$6:$B$505,Movimientos!$D$6:$D$505,"">""&prevDate,Movimientos!$D$6:$D$505,""<=""&A12,Movimientos!$E$6:$"&"E$505,TRUE)+SUMIFS(Movimientos!$B$6:$B$505,Movimientos!$D$6:$D$505,"">""&prevDate,Movimientos!$D$6:$D$505,""<=""&A12,Movimientos!$C$6:$C$505,""Fecha inferida*""),net,B12-flow,IF(OR(gap<1,unknown>0,prevValue<=0,net<=0),"""",(POWER(net/prevValue,1/gap)-1)*1"&"00)),""""))"),"") | E12: =IF(B12="","",IF(OR(A12=DATE(2026,1,30),A12=DATE(2026,2,27),A12=DATE(2026,3,31),A12=DATE(2026,4,30),A12=DATE(2026,5,29),A12=DATE(2026,6,30)),"Histórico mensual",IF(A12=DATE(2026,7,9),"Base diaria",IF(WEEKDAY(A12,2)>5,"Fin de semana","Diario"))))
A13: 46034 | B13: =IF(Diario!B17="","",Diario!B17) | C13: =SUMIFS(Movimientos!$B$6:$B$505,Movimientos!$D$6:$D$505,A13,Movimientos!$E$6:$E$505,TRUE) -> 0 | D13: =IFERROR(__xludf.DUMMYFUNCTION("IF(OR(B13="""",A13>TODAY(),E13=""Histórico mensual"",E13=""Base diaria""),"""",IFERROR(LET(prevDate,MAX(FILTER($A$2:A12,$B$2:B12<>"""",$A$2:A12<A13)),prevValue,XLOOKUP(prevDate,$A$2:A12,$B$2:B12),gap,A13-prevDate,unknown,COUNTIFS(Movimientos!$D$6:$D$505,"&""">""&prevDate,Movimientos!$D$6:$D$505,""<=""&A13,Movimientos!$E$6:$E$505,FALSE,Movimientos!$C$6:$C$505,""<>Fecha inferida*""),flow,SUMIFS(Movimientos!$B$6:$B$505,Movimientos!$D$6:$D$505,"">""&prevDate,Movimientos!$D$6:$D$505,""<=""&A13,Movimientos!$E$6:$"&"E$505,TRUE)+SUMIFS(Movimientos!$B$6:$B$505,Movimientos!$D$6:$D$505,"">""&prevDate,Movimientos!$D$6:$D$505,""<=""&A13,Movimientos!$C$6:$C$505,""Fecha inferida*""),net,B13-flow,IF(OR(gap<1,unknown>0,prevValue<=0,net<=0),"""",(POWER(net/prevValue,1/gap)-1)*1"&"00)),""""))"),"") | E13: =IF(B13="","",IF(OR(A13=DATE(2026,1,30),A13=DATE(2026,2,27),A13=DATE(2026,3,31),A13=DATE(2026,4,30),A13=DATE(2026,5,29),A13=DATE(2026,6,30)),"Histórico mensual",IF(A13=DATE(2026,7,9),"Base diaria",IF(WEEKDAY(A13,2)>5,"Fin de semana","Diario"))))
A14: 46035 | B14: =IF(Diario!B18="","",Diario!B18) | C14: =SUMIFS(Movimientos!$B$6:$B$505,Movimientos!$D$6:$D$505,A14,Movimientos!$E$6:$E$505,TRUE) -> 0 | D14: =IFERROR(__xludf.DUMMYFUNCTION("IF(OR(B14="""",A14>TODAY(),E14=""Histórico mensual"",E14=""Base diaria""),"""",IFERROR(LET(prevDate,MAX(FILTER($A$2:A13,$B$2:B13<>"""",$A$2:A13<A14)),prevValue,XLOOKUP(prevDate,$A$2:A13,$B$2:B13),gap,A14-prevDate,unknown,COUNTIFS(Movimientos!$D$6:$D$505,"&""">""&prevDate,Movimientos!$D$6:$D$505,""<=""&A14,Movimientos!$E$6:$E$505,FALSE,Movimientos!$C$6:$C$505,""<>Fecha inferida*""),flow,SUMIFS(Movimientos!$B$6:$B$505,Movimientos!$D$6:$D$505,"">""&prevDate,Movimientos!$D$6:$D$505,""<=""&A14,Movimientos!$E$6:$"&"E$505,TRUE)+SUMIFS(Movimientos!$B$6:$B$505,Movimientos!$D$6:$D$505,"">""&prevDate,Movimientos!$D$6:$D$505,""<=""&A14,Movimientos!$C$6:$C$505,""Fecha inferida*""),net,B14-flow,IF(OR(gap<1,unknown>0,prevValue<=0,net<=0),"""",(POWER(net/prevValue,1/gap)-1)*1"&"00)),""""))"),"") | E14: =IF(B14="","",IF(OR(A14=DATE(2026,1,30),A14=DATE(2026,2,27),A14=DATE(2026,3,31),A14=DATE(2026,4,30),A14=DATE(2026,5,29),A14=DATE(2026,6,30)),"Histórico mensual",IF(A14=DATE(2026,7,9),"Base diaria",IF(WEEKDAY(A14,2)>5,"Fin de semana","Diario"))))
A15: 46036 | B15: =IF(Diario!B19="","",Diario!B19) | C15: =SUMIFS(Movimientos!$B$6:$B$505,Movimientos!$D$6:$D$505,A15,Movimientos!$E$6:$E$505,TRUE) -> 0 | D15: =IFERROR(__xludf.DUMMYFUNCTION("IF(OR(B15="""",A15>TODAY(),E15=""Histórico mensual"",E15=""Base diaria""),"""",IFERROR(LET(prevDate,MAX(FILTER($A$2:A14,$B$2:B14<>"""",$A$2:A14<A15)),prevValue,XLOOKUP(prevDate,$A$2:A14,$B$2:B14),gap,A15-prevDate,unknown,COUNTIFS(Movimientos!$D$6:$D$505,"&""">""&prevDate,Movimientos!$D$6:$D$505,""<=""&A15,Movimientos!$E$6:$E$505,FALSE,Movimientos!$C$6:$C$505,""<>Fecha inferida*""),flow,SUMIFS(Movimientos!$B$6:$B$505,Movimientos!$D$6:$D$505,"">""&prevDate,Movimientos!$D$6:$D$505,""<=""&A15,Movimientos!$E$6:$"&"E$505,TRUE)+SUMIFS(Movimientos!$B$6:$B$505,Movimientos!$D$6:$D$505,"">""&prevDate,Movimientos!$D$6:$D$505,""<=""&A15,Movimientos!$C$6:$C$505,""Fecha inferida*""),net,B15-flow,IF(OR(gap<1,unknown>0,prevValue<=0,net<=0),"""",(POWER(net/prevValue,1/gap)-1)*1"&"00)),""""))"),"") | E15: =IF(B15="","",IF(OR(A15=DATE(2026,1,30),A15=DATE(2026,2,27),A15=DATE(2026,3,31),A15=DATE(2026,4,30),A15=DATE(2026,5,29),A15=DATE(2026,6,30)),"Histórico mensual",IF(A15=DATE(2026,7,9),"Base diaria",IF(WEEKDAY(A15,2)>5,"Fin de semana","Diario"))))
A16: 46037 | B16: =IF(Diario!B20="","",Diario!B20) | C16: =SUMIFS(Movimientos!$B$6:$B$505,Movimientos!$D$6:$D$505,A16,Movimientos!$E$6:$E$505,TRUE) -> 0 | D16: =IFERROR(__xludf.DUMMYFUNCTION("IF(OR(B16="""",A16>TODAY(),E16=""Histórico mensual"",E16=""Base diaria""),"""",IFERROR(LET(prevDate,MAX(FILTER($A$2:A15,$B$2:B15<>"""",$A$2:A15<A16)),prevValue,XLOOKUP(prevDate,$A$2:A15,$B$2:B15),gap,A16-prevDate,unknown,COUNTIFS(Movimientos!$D$6:$D$505,"&""">""&prevDate,Movimientos!$D$6:$D$505,""<=""&A16,Movimientos!$E$6:$E$505,FALSE,Movimientos!$C$6:$C$505,""<>Fecha inferida*""),flow,SUMIFS(Movimientos!$B$6:$B$505,Movimientos!$D$6:$D$505,"">""&prevDate,Movimientos!$D$6:$D$505,""<=""&A16,Movimientos!$E$6:$"&"E$505,TRUE)+SUMIFS(Movimientos!$B$6:$B$505,Movimientos!$D$6:$D$505,"">""&prevDate,Movimientos!$D$6:$D$505,""<=""&A16,Movimientos!$C$6:$C$505,""Fecha inferida*""),net,B16-flow,IF(OR(gap<1,unknown>0,prevValue<=0,net<=0),"""",(POWER(net/prevValue,1/gap)-1)*1"&"00)),""""))"),"") | E16: =IF(B16="","",IF(OR(A16=DATE(2026,1,30),A16=DATE(2026,2,27),A16=DATE(2026,3,31),A16=DATE(2026,4,30),A16=DATE(2026,5,29),A16=DATE(2026,6,30)),"Histórico mensual",IF(A16=DATE(2026,7,9),"Base diaria",IF(WEEKDAY(A16,2)>5,"Fin de semana","Diario"))))
A17: 46038 | B17: =IF(Diario!B21="","",Diario!B21) | C17: =SUMIFS(Movimientos!$B$6:$B$505,Movimientos!$D$6:$D$505,A17,Movimientos!$E$6:$E$505,TRUE) -> 0 | D17: =IFERROR(__xludf.DUMMYFUNCTION("IF(OR(B17="""",A17>TODAY(),E17=""Histórico mensual"",E17=""Base diaria""),"""",IFERROR(LET(prevDate,MAX(FILTER($A$2:A16,$B$2:B16<>"""",$A$2:A16<A17)),prevValue,XLOOKUP(prevDate,$A$2:A16,$B$2:B16),gap,A17-prevDate,unknown,COUNTIFS(Movimientos!$D$6:$D$505,"&""">""&prevDate,Movimientos!$D$6:$D$505,""<=""&A17,Movimientos!$E$6:$E$505,FALSE,Movimientos!$C$6:$C$505,""<>Fecha inferida*""),flow,SUMIFS(Movimientos!$B$6:$B$505,Movimientos!$D$6:$D$505,"">""&prevDate,Movimientos!$D$6:$D$505,""<=""&A17,Movimientos!$E$6:$"&"E$505,TRUE)+SUMIFS(Movimientos!$B$6:$B$505,Movimientos!$D$6:$D$505,"">""&prevDate,Movimientos!$D$6:$D$505,""<=""&A17,Movimientos!$C$6:$C$505,""Fecha inferida*""),net,B17-flow,IF(OR(gap<1,unknown>0,prevValue<=0,net<=0),"""",(POWER(net/prevValue,1/gap)-1)*1"&"00)),""""))"),"") | E17: =IF(B17="","",IF(OR(A17=DATE(2026,1,30),A17=DATE(2026,2,27),A17=DATE(2026,3,31),A17=DATE(2026,4,30),A17=DATE(2026,5,29),A17=DATE(2026,6,30)),"Histórico mensual",IF(A17=DATE(2026,7,9),"Base diaria",IF(WEEKDAY(A17,2)>5,"Fin de semana","Diario"))))
A18: 46039 | B18: =IF(Diario!B22="","",Diario!B22) | C18: =SUMIFS(Movimientos!$B$6:$B$505,Movimientos!$D$6:$D$505,A18,Movimientos!$E$6:$E$505,TRUE) -> 0 | D18: =IFERROR(__xludf.DUMMYFUNCTION("IF(OR(B18="""",A18>TODAY(),E18=""Histórico mensual"",E18=""Base diaria""),"""",IFERROR(LET(prevDate,MAX(FILTER($A$2:A17,$B$2:B17<>"""",$A$2:A17<A18)),prevValue,XLOOKUP(prevDate,$A$2:A17,$B$2:B17),gap,A18-prevDate,unknown,COUNTIFS(Movimientos!$D$6:$D$505,"&""">""&prevDate,Movimientos!$D$6:$D$505,""<=""&A18,Movimientos!$E$6:$E$505,FALSE,Movimientos!$C$6:$C$505,""<>Fecha inferida*""),flow,SUMIFS(Movimientos!$B$6:$B$505,Movimientos!$D$6:$D$505,"">""&prevDate,Movimientos!$D$6:$D$505,""<=""&A18,Movimientos!$E$6:$"&"E$505,TRUE)+SUMIFS(Movimientos!$B$6:$B$505,Movimientos!$D$6:$D$505,"">""&prevDate,Movimientos!$D$6:$D$505,""<=""&A18,Movimientos!$C$6:$C$505,""Fecha inferida*""),net,B18-flow,IF(OR(gap<1,unknown>0,prevValue<=0,net<=0),"""",(POWER(net/prevValue,1/gap)-1)*1"&"00)),""""))"),"") | E18: =IF(B18="","",IF(OR(A18=DATE(2026,1,30),A18=DATE(2026,2,27),A18=DATE(2026,3,31),A18=DATE(2026,4,30),A18=DATE(2026,5,29),A18=DATE(2026,6,30)),"Histórico mensual",IF(A18=DATE(2026,7,9),"Base diaria",IF(WEEKDAY(A18,2)>5,"Fin de semana","Diario"))))
A19: 46040 | B19: =IF(Diario!B23="","",Diario!B23) | C19: =SUMIFS(Movimientos!$B$6:$B$505,Movimientos!$D$6:$D$505,A19,Movimientos!$E$6:$E$505,TRUE) -> 0 | D19: =IFERROR(__xludf.DUMMYFUNCTION("IF(OR(B19="""",A19>TODAY(),E19=""Histórico mensual"",E19=""Base diaria""),"""",IFERROR(LET(prevDate,MAX(FILTER($A$2:A18,$B$2:B18<>"""",$A$2:A18<A19)),prevValue,XLOOKUP(prevDate,$A$2:A18,$B$2:B18),gap,A19-prevDate,unknown,COUNTIFS(Movimientos!$D$6:$D$505,"&""">""&prevDate,Movimientos!$D$6:$D$505,""<=""&A19,Movimientos!$E$6:$E$505,FALSE,Movimientos!$C$6:$C$505,""<>Fecha inferida*""),flow,SUMIFS(Movimientos!$B$6:$B$505,Movimientos!$D$6:$D$505,"">""&prevDate,Movimientos!$D$6:$D$505,""<=""&A19,Movimientos!$E$6:$"&"E$505,TRUE)+SUMIFS(Movimientos!$B$6:$B$505,Movimientos!$D$6:$D$505,"">""&prevDate,Movimientos!$D$6:$D$505,""<=""&A19,Movimientos!$C$6:$C$505,""Fecha inferida*""),net,B19-flow,IF(OR(gap<1,unknown>0,prevValue<=0,net<=0),"""",(POWER(net/prevValue,1/gap)-1)*1"&"00)),""""))"),"") | E19: =IF(B19="","",IF(OR(A19=DATE(2026,1,30),A19=DATE(2026,2,27),A19=DATE(2026,3,31),A19=DATE(2026,4,30),A19=DATE(2026,5,29),A19=DATE(2026,6,30)),"Histórico mensual",IF(A19=DATE(2026,7,9),"Base diaria",IF(WEEKDAY(A19,2)>5,"Fin de semana","Diario"))))
A20: 46041 | B20: =IF(Diario!B24="","",Diario!B24) | C20: =SUMIFS(Movimientos!$B$6:$B$505,Movimientos!$D$6:$D$505,A20,Movimientos!$E$6:$E$505,TRUE) -> 0 | D20: =IFERROR(__xludf.DUMMYFUNCTION("IF(OR(B20="""",A20>TODAY(),E20=""Histórico mensual"",E20=""Base diaria""),"""",IFERROR(LET(prevDate,MAX(FILTER($A$2:A19,$B$2:B19<>"""",$A$2:A19<A20)),prevValue,XLOOKUP(prevDate,$A$2:A19,$B$2:B19),gap,A20-prevDate,unknown,COUNTIFS(Movimientos!$D$6:$D$505,"&""">""&prevDate,Movimientos!$D$6:$D$505,""<=""&A20,Movimientos!$E$6:$E$505,FALSE,Movimientos!$C$6:$C$505,""<>Fecha inferida*""),flow,SUMIFS(Movimientos!$B$6:$B$505,Movimientos!$D$6:$D$505,"">""&prevDate,Movimientos!$D$6:$D$505,""<=""&A20,Movimientos!$E$6:$"&"E$505,TRUE)+SUMIFS(Movimientos!$B$6:$B$505,Movimientos!$D$6:$D$505,"">""&prevDate,Movimientos!$D$6:$D$505,""<=""&A20,Movimientos!$C$6:$C$505,""Fecha inferida*""),net,B20-flow,IF(OR(gap<1,unknown>0,prevValue<=0,net<=0),"""",(POWER(net/prevValue,1/gap)-1)*1"&"00)),""""))"),"") | E20: =IF(B20="","",IF(OR(A20=DATE(2026,1,30),A20=DATE(2026,2,27),A20=DATE(2026,3,31),A20=DATE(2026,4,30),A20=DATE(2026,5,29),A20=DATE(2026,6,30)),"Histórico mensual",IF(A20=DATE(2026,7,9),"Base diaria",IF(WEEKDAY(A20,2)>5,"Fin de semana","Diario"))))
A21: 46042 | B21: =IF(Diario!B25="","",Diario!B25) | C21: =SUMIFS(Movimientos!$B$6:$B$505,Movimientos!$D$6:$D$505,A21,Movimientos!$E$6:$E$505,TRUE) -> 0 | D21: =IFERROR(__xludf.DUMMYFUNCTION("IF(OR(B21="""",A21>TODAY(),E21=""Histórico mensual"",E21=""Base diaria""),"""",IFERROR(LET(prevDate,MAX(FILTER($A$2:A20,$B$2:B20<>"""",$A$2:A20<A21)),prevValue,XLOOKUP(prevDate,$A$2:A20,$B$2:B20),gap,A21-prevDate,unknown,COUNTIFS(Movimientos!$D$6:$D$505,"&""">""&prevDate,Movimientos!$D$6:$D$505,""<=""&A21,Movimientos!$E$6:$E$505,FALSE,Movimientos!$C$6:$C$505,""<>Fecha inferida*""),flow,SUMIFS(Movimientos!$B$6:$B$505,Movimientos!$D$6:$D$505,"">""&prevDate,Movimientos!$D$6:$D$505,""<=""&A21,Movimientos!$E$6:$"&"E$505,TRUE)+SUMIFS(Movimientos!$B$6:$B$505,Movimientos!$D$6:$D$505,"">""&prevDate,Movimientos!$D$6:$D$505,""<=""&A21,Movimientos!$C$6:$C$505,""Fecha inferida*""),net,B21-flow,IF(OR(gap<1,unknown>0,prevValue<=0,net<=0),"""",(POWER(net/prevValue,1/gap)-1)*1"&"00)),""""))"),"") | E21: =IF(B21="","",IF(OR(A21=DATE(2026,1,30),A21=DATE(2026,2,27),A21=DATE(2026,3,31),A21=DATE(2026,4,30),A21=DATE(2026,5,29),A21=DATE(2026,6,30)),"Histórico mensual",IF(A21=DATE(2026,7,9),"Base diaria",IF(WEEKDAY(A21,2)>5,"Fin de semana","Diario"))))
A22: 46043 | B22: =IF(Diario!B26="","",Diario!B26) | C22: =SUMIFS(Movimientos!$B$6:$B$505,Movimientos!$D$6:$D$505,A22,Movimientos!$E$6:$E$505,TRUE) -> 0 | D22: =IFERROR(__xludf.DUMMYFUNCTION("IF(OR(B22="""",A22>TODAY(),E22=""Histórico mensual"",E22=""Base diaria""),"""",IFERROR(LET(prevDate,MAX(FILTER($A$2:A21,$B$2:B21<>"""",$A$2:A21<A22)),prevValue,XLOOKUP(prevDate,$A$2:A21,$B$2:B21),gap,A22-prevDate,unknown,COUNTIFS(Movimientos!$D$6:$D$505,"&""">""&prevDate,Movimientos!$D$6:$D$505,""<=""&A22,Movimientos!$E$6:$E$505,FALSE,Movimientos!$C$6:$C$505,""<>Fecha inferida*""),flow,SUMIFS(Movimientos!$B$6:$B$505,Movimientos!$D$6:$D$505,"">""&prevDate,Movimientos!$D$6:$D$505,""<=""&A22,Movimientos!$E$6:$"&"E$505,TRUE)+SUMIFS(Movimientos!$B$6:$B$505,Movimientos!$D$6:$D$505,"">""&prevDate,Movimientos!$D$6:$D$505,""<=""&A22,Movimientos!$C$6:$C$505,""Fecha inferida*""),net,B22-flow,IF(OR(gap<1,unknown>0,prevValue<=0,net<=0),"""",(POWER(net/prevValue,1/gap)-1)*1"&"00)),""""))"),"") | E22: =IF(B22="","",IF(OR(A22=DATE(2026,1,30),A22=DATE(2026,2,27),A22=DATE(2026,3,31),A22=DATE(2026,4,30),A22=DATE(2026,5,29),A22=DATE(2026,6,30)),"Histórico mensual",IF(A22=DATE(2026,7,9),"Base diaria",IF(WEEKDAY(A22,2)>5,"Fin de semana","Diario"))))
A23: 46044 | B23: =IF(Diario!B27="","",Diario!B27) | C23: =SUMIFS(Movimientos!$B$6:$B$505,Movimientos!$D$6:$D$505,A23,Movimientos!$E$6:$E$505,TRUE) -> 0 | D23: =IFERROR(__xludf.DUMMYFUNCTION("IF(OR(B23="""",A23>TODAY(),E23=""Histórico mensual"",E23=""Base diaria""),"""",IFERROR(LET(prevDate,MAX(FILTER($A$2:A22,$B$2:B22<>"""",$A$2:A22<A23)),prevValue,XLOOKUP(prevDate,$A$2:A22,$B$2:B22),gap,A23-prevDate,unknown,COUNTIFS(Movimientos!$D$6:$D$505,"&""">""&prevDate,Movimientos!$D$6:$D$505,""<=""&A23,Movimientos!$E$6:$E$505,FALSE,Movimientos!$C$6:$C$505,""<>Fecha inferida*""),flow,SUMIFS(Movimientos!$B$6:$B$505,Movimientos!$D$6:$D$505,"">""&prevDate,Movimientos!$D$6:$D$505,""<=""&A23,Movimientos!$E$6:$"&"E$505,TRUE)+SUMIFS(Movimientos!$B$6:$B$505,Movimientos!$D$6:$D$505,"">""&prevDate,Movimientos!$D$6:$D$505,""<=""&A23,Movimientos!$C$6:$C$505,""Fecha inferida*""),net,B23-flow,IF(OR(gap<1,unknown>0,prevValue<=0,net<=0),"""",(POWER(net/prevValue,1/gap)-1)*1"&"00)),""""))"),"") | E23: =IF(B23="","",IF(OR(A23=DATE(2026,1,30),A23=DATE(2026,2,27),A23=DATE(2026,3,31),A23=DATE(2026,4,30),A23=DATE(2026,5,29),A23=DATE(2026,6,30)),"Histórico mensual",IF(A23=DATE(2026,7,9),"Base diaria",IF(WEEKDAY(A23,2)>5,"Fin de semana","Diario"))))
A24: 46045 | B24: =IF(Diario!B28="","",Diario!B28) | C24: =SUMIFS(Movimientos!$B$6:$B$505,Movimientos!$D$6:$D$505,A24,Movimientos!$E$6:$E$505,TRUE) -> 0 | D24: =IFERROR(__xludf.DUMMYFUNCTION("IF(OR(B24="""",A24>TODAY(),E24=""Histórico mensual"",E24=""Base diaria""),"""",IFERROR(LET(prevDate,MAX(FILTER($A$2:A23,$B$2:B23<>"""",$A$2:A23<A24)),prevValue,XLOOKUP(prevDate,$A$2:A23,$B$2:B23),gap,A24-prevDate,unknown,COUNTIFS(Movimientos!$D$6:$D$505,"&""">""&prevDate,Movimientos!$D$6:$D$505,""<=""&A24,Movimientos!$E$6:$E$505,FALSE,Movimientos!$C$6:$C$505,""<>Fecha inferida*""),flow,SUMIFS(Movimientos!$B$6:$B$505,Movimientos!$D$6:$D$505,"">""&prevDate,Movimientos!$D$6:$D$505,""<=""&A24,Movimientos!$E$6:$"&"E$505,TRUE)+SUMIFS(Movimientos!$B$6:$B$505,Movimientos!$D$6:$D$505,"">""&prevDate,Movimientos!$D$6:$D$505,""<=""&A24,Movimientos!$C$6:$C$505,""Fecha inferida*""),net,B24-flow,IF(OR(gap<1,unknown>0,prevValue<=0,net<=0),"""",(POWER(net/prevValue,1/gap)-1)*1"&"00)),""""))"),"") | E24: =IF(B24="","",IF(OR(A24=DATE(2026,1,30),A24=DATE(2026,2,27),A24=DATE(2026,3,31),A24=DATE(2026,4,30),A24=DATE(2026,5,29),A24=DATE(2026,6,30)),"Histórico mensual",IF(A24=DATE(2026,7,9),"Base diaria",IF(WEEKDAY(A24,2)>5,"Fin de semana","Diario"))))
A25: 46046 | B25: =IF(Diario!B29="","",Diario!B29) | C25: =SUMIFS(Movimientos!$B$6:$B$505,Movimientos!$D$6:$D$505,A25,Movimientos!$E$6:$E$505,TRUE) -> 0 | D25: =IFERROR(__xludf.DUMMYFUNCTION("IF(OR(B25="""",A25>TODAY(),E25=""Histórico mensual"",E25=""Base diaria""),"""",IFERROR(LET(prevDate,MAX(FILTER($A$2:A24,$B$2:B24<>"""",$A$2:A24<A25)),prevValue,XLOOKUP(prevDate,$A$2:A24,$B$2:B24),gap,A25-prevDate,unknown,COUNTIFS(Movimientos!$D$6:$D$505,"&""">""&prevDate,Movimientos!$D$6:$D$505,""<=""&A25,Movimientos!$E$6:$E$505,FALSE,Movimientos!$C$6:$C$505,""<>Fecha inferida*""),flow,SUMIFS(Movimientos!$B$6:$B$505,Movimientos!$D$6:$D$505,"">""&prevDate,Movimientos!$D$6:$D$505,""<=""&A25,Movimientos!$E$6:$"&"E$505,TRUE)+SUMIFS(Movimientos!$B$6:$B$505,Movimientos!$D$6:$D$505,"">""&prevDate,Movimientos!$D$6:$D$505,""<=""&A25,Movimientos!$C$6:$C$505,""Fecha inferida*""),net,B25-flow,IF(OR(gap<1,unknown>0,prevValue<=0,net<=0),"""",(POWER(net/prevValue,1/gap)-1)*1"&"00)),""""))"),"") | E25: =IF(B25="","",IF(OR(A25=DATE(2026,1,30),A25=DATE(2026,2,27),A25=DATE(2026,3,31),A25=DATE(2026,4,30),A25=DATE(2026,5,29),A25=DATE(2026,6,30)),"Histórico mensual",IF(A25=DATE(2026,7,9),"Base diaria",IF(WEEKDAY(A25,2)>5,"Fin de semana","Diario"))))
A26: 46047 | B26: =IF(Diario!B30="","",Diario!B30) | C26: =SUMIFS(Movimientos!$B$6:$B$505,Movimientos!$D$6:$D$505,A26,Movimientos!$E$6:$E$505,TRUE) -> 0 | D26: =IFERROR(__xludf.DUMMYFUNCTION("IF(OR(B26="""",A26>TODAY(),E26=""Histórico mensual"",E26=""Base diaria""),"""",IFERROR(LET(prevDate,MAX(FILTER($A$2:A25,$B$2:B25<>"""",$A$2:A25<A26)),prevValue,XLOOKUP(prevDate,$A$2:A25,$B$2:B25),gap,A26-prevDate,unknown,COUNTIFS(Movimientos!$D$6:$D$505,"&""">""&prevDate,Movimientos!$D$6:$D$505,""<=""&A26,Movimientos!$E$6:$E$505,FALSE,Movimientos!$C$6:$C$505,""<>Fecha inferida*""),flow,SUMIFS(Movimientos!$B$6:$B$505,Movimientos!$D$6:$D$505,"">""&prevDate,Movimientos!$D$6:$D$505,""<=""&A26,Movimientos!$E$6:$"&"E$505,TRUE)+SUMIFS(Movimientos!$B$6:$B$505,Movimientos!$D$6:$D$505,"">""&prevDate,Movimientos!$D$6:$D$505,""<=""&A26,Movimientos!$C$6:$C$505,""Fecha inferida*""),net,B26-flow,IF(OR(gap<1,unknown>0,prevValue<=0,net<=0),"""",(POWER(net/prevValue,1/gap)-1)*1"&"00)),""""))"),"") | E26: =IF(B26="","",IF(OR(A26=DATE(2026,1,30),A26=DATE(2026,2,27),A26=DATE(2026,3,31),A26=DATE(2026,4,30),A26=DATE(2026,5,29),A26=DATE(2026,6,30)),"Histórico mensual",IF(A26=DATE(2026,7,9),"Base diaria",IF(WEEKDAY(A26,2)>5,"Fin de semana","Diario"))))
A27: 46048 | B27: =IF(Diario!B31="","",Diario!B31) | C27: =SUMIFS(Movimientos!$B$6:$B$505,Movimientos!$D$6:$D$505,A27,Movimientos!$E$6:$E$505,TRUE) -> 0 | D27: =IFERROR(__xludf.DUMMYFUNCTION("IF(OR(B27="""",A27>TODAY(),E27=""Histórico mensual"",E27=""Base diaria""),"""",IFERROR(LET(prevDate,MAX(FILTER($A$2:A26,$B$2:B26<>"""",$A$2:A26<A27)),prevValue,XLOOKUP(prevDate,$A$2:A26,$B$2:B26),gap,A27-prevDate,unknown,COUNTIFS(Movimientos!$D$6:$D$505,"&""">""&prevDate,Movimientos!$D$6:$D$505,""<=""&A27,Movimientos!$E$6:$E$505,FALSE,Movimientos!$C$6:$C$505,""<>Fecha inferida*""),flow,SUMIFS(Movimientos!$B$6:$B$505,Movimientos!$D$6:$D$505,"">""&prevDate,Movimientos!$D$6:$D$505,""<=""&A27,Movimientos!$E$6:$"&"E$505,TRUE)+SUMIFS(Movimientos!$B$6:$B$505,Movimientos!$D$6:$D$505,"">""&prevDate,Movimientos!$D$6:$D$505,""<=""&A27,Movimientos!$C$6:$C$505,""Fecha inferida*""),net,B27-flow,IF(OR(gap<1,unknown>0,prevValue<=0,net<=0),"""",(POWER(net/prevValue,1/gap)-1)*1"&"00)),""""))"),"") | E27: =IF(B27="","",IF(OR(A27=DATE(2026,1,30),A27=DATE(2026,2,27),A27=DATE(2026,3,31),A27=DATE(2026,4,30),A27=DATE(2026,5,29),A27=DATE(2026,6,30)),"Histórico mensual",IF(A27=DATE(2026,7,9),"Base diaria",IF(WEEKDAY(A27,2)>5,"Fin de semana","Diario"))))
A28: 46049 | B28: =IF(Diario!B32="","",Diario!B32) | C28: =SUMIFS(Movimientos!$B$6:$B$505,Movimientos!$D$6:$D$505,A28,Movimientos!$E$6:$E$505,TRUE) -> 0 | D28: =IFERROR(__xludf.DUMMYFUNCTION("IF(OR(B28="""",A28>TODAY(),E28=""Histórico mensual"",E28=""Base diaria""),"""",IFERROR(LET(prevDate,MAX(FILTER($A$2:A27,$B$2:B27<>"""",$A$2:A27<A28)),prevValue,XLOOKUP(prevDate,$A$2:A27,$B$2:B27),gap,A28-prevDate,unknown,COUNTIFS(Movimientos!$D$6:$D$505,"&""">""&prevDate,Movimientos!$D$6:$D$505,""<=""&A28,Movimientos!$E$6:$E$505,FALSE,Movimientos!$C$6:$C$505,""<>Fecha inferida*""),flow,SUMIFS(Movimientos!$B$6:$B$505,Movimientos!$D$6:$D$505,"">""&prevDate,Movimientos!$D$6:$D$505,""<=""&A28,Movimientos!$E$6:$"&"E$505,TRUE)+SUMIFS(Movimientos!$B$6:$B$505,Movimientos!$D$6:$D$505,"">""&prevDate,Movimientos!$D$6:$D$505,""<=""&A28,Movimientos!$C$6:$C$505,""Fecha inferida*""),net,B28-flow,IF(OR(gap<1,unknown>0,prevValue<=0,net<=0),"""",(POWER(net/prevValue,1/gap)-1)*1"&"00)),""""))"),"") | E28: =IF(B28="","",IF(OR(A28=DATE(2026,1,30),A28=DATE(2026,2,27),A28=DATE(2026,3,31),A28=DATE(2026,4,30),A28=DATE(2026,5,29),A28=DATE(2026,6,30)),"Histórico mensual",IF(A28=DATE(2026,7,9),"Base diaria",IF(WEEKDAY(A28,2)>5,"Fin de semana","Diario"))))
A29: 46050 | B29: =IF(Diario!B33="","",Diario!B33) | C29: =SUMIFS(Movimientos!$B$6:$B$505,Movimientos!$D$6:$D$505,A29,Movimientos!$E$6:$E$505,TRUE) -> 0 | D29: =IFERROR(__xludf.DUMMYFUNCTION("IF(OR(B29="""",A29>TODAY(),E29=""Histórico mensual"",E29=""Base diaria""),"""",IFERROR(LET(prevDate,MAX(FILTER($A$2:A28,$B$2:B28<>"""",$A$2:A28<A29)),prevValue,XLOOKUP(prevDate,$A$2:A28,$B$2:B28),gap,A29-prevDate,unknown,COUNTIFS(Movimientos!$D$6:$D$505,"&""">""&prevDate,Movimientos!$D$6:$D$505,""<=""&A29,Movimientos!$E$6:$E$505,FALSE,Movimientos!$C$6:$C$505,""<>Fecha inferida*""),flow,SUMIFS(Movimientos!$B$6:$B$505,Movimientos!$D$6:$D$505,"">""&prevDate,Movimientos!$D$6:$D$505,""<=""&A29,Movimientos!$E$6:$"&"E$505,TRUE)+SUMIFS(Movimientos!$B$6:$B$505,Movimientos!$D$6:$D$505,"">""&prevDate,Movimientos!$D$6:$D$505,""<=""&A29,Movimientos!$C$6:$C$505,""Fecha inferida*""),net,B29-flow,IF(OR(gap<1,unknown>0,prevValue<=0,net<=0),"""",(POWER(net/prevValue,1/gap)-1)*1"&"00)),""""))"),"") | E29: =IF(B29="","",IF(OR(A29=DATE(2026,1,30),A29=DATE(2026,2,27),A29=DATE(2026,3,31),A29=DATE(2026,4,30),A29=DATE(2026,5,29),A29=DATE(2026,6,30)),"Histórico mensual",IF(A29=DATE(2026,7,9),"Base diaria",IF(WEEKDAY(A29,2)>5,"Fin de semana","Diario"))))
A30: 46051 | B30: =IF(Diario!B34="","",Diario!B34) | C30: =SUMIFS(Movimientos!$B$6:$B$505,Movimientos!$D$6:$D$505,A30,Movimientos!$E$6:$E$505,TRUE) -> 0 | D30: =IFERROR(__xludf.DUMMYFUNCTION("IF(OR(B30="""",A30>TODAY(),E30=""Histórico mensual"",E30=""Base diaria""),"""",IFERROR(LET(prevDate,MAX(FILTER($A$2:A29,$B$2:B29<>"""",$A$2:A29<A30)),prevValue,XLOOKUP(prevDate,$A$2:A29,$B$2:B29),gap,A30-prevDate,unknown,COUNTIFS(Movimientos!$D$6:$D$505,"&""">""&prevDate,Movimientos!$D$6:$D$505,""<=""&A30,Movimientos!$E$6:$E$505,FALSE,Movimientos!$C$6:$C$505,""<>Fecha inferida*""),flow,SUMIFS(Movimientos!$B$6:$B$505,Movimientos!$D$6:$D$505,"">""&prevDate,Movimientos!$D$6:$D$505,""<=""&A30,Movimientos!$E$6:$"&"E$505,TRUE)+SUMIFS(Movimientos!$B$6:$B$505,Movimientos!$D$6:$D$505,"">""&prevDate,Movimientos!$D$6:$D$505,""<=""&A30,Movimientos!$C$6:$C$505,""Fecha inferida*""),net,B30-flow,IF(OR(gap<1,unknown>0,prevValue<=0,net<=0),"""",(POWER(net/prevValue,1/gap)-1)*1"&"00)),""""))"),"") | E30: =IF(B30="","",IF(OR(A30=DATE(2026,1,30),A30=DATE(2026,2,27),A30=DATE(2026,3,31),A30=DATE(2026,4,30),A30=DATE(2026,5,29),A30=DATE(2026,6,30)),"Histórico mensual",IF(A30=DATE(2026,7,9),"Base diaria",IF(WEEKDAY(A30,2)>5,"Fin de semana","Diario"))))
A31: 46052 | B31: =IF(Diario!B35="","",Diario!B35) -> 76000 | C31: =SUMIFS(Movimientos!$B$6:$B$505,Movimientos!$D$6:$D$505,A31,Movimientos!$E$6:$E$505,TRUE) -> 500 | D31: =IFERROR(__xludf.DUMMYFUNCTION("IF(OR(B31="""",A31>TODAY(),E31=""Histórico mensual"",E31=""Base diaria""),"""",IFERROR(LET(prevDate,MAX(FILTER($A$2:A30,$B$2:B30<>"""",$A$2:A30<A31)),prevValue,XLOOKUP(prevDate,$A$2:A30,$B$2:B30),gap,A31-prevDate,unknown,COUNTIFS(Movimientos!$D$6:$D$505,"&""">""&prevDate,Movimientos!$D$6:$D$505,""<=""&A31,Movimientos!$E$6:$E$505,FALSE,Movimientos!$C$6:$C$505,""<>Fecha inferida*""),flow,SUMIFS(Movimientos!$B$6:$B$505,Movimientos!$D$6:$D$505,"">""&prevDate,Movimientos!$D$6:$D$505,""<=""&A31,Movimientos!$E$6:$"&"E$505,TRUE)+SUMIFS(Movimientos!$B$6:$B$505,Movimientos!$D$6:$D$505,"">""&prevDate,Movimientos!$D$6:$D$505,""<=""&A31,Movimientos!$C$6:$C$505,""Fecha inferida*""),net,B31-flow,IF(OR(gap<1,unknown>0,prevValue<=0,net<=0),"""",(POWER(net/prevValue,1/gap)-1)*1"&"00)),""""))"),"") | E31: =IF(B31="","",IF(OR(A31=DATE(2026,1,30),A31=DATE(2026,2,27),A31=DATE(2026,3,31),A31=DATE(2026,4,30),A31=DATE(2026,5,29),A31=DATE(2026,6,30)),"Histórico mensual",IF(A31=DATE(2026,7,9),"Base diaria",IF(WEEKDAY(A31,2)>5,"Fin de semana","Diario")))) -> Histórico mensual
A32: 46053 | B32: =IF(Diario!B36="","",Diario!B36) | C32: =SUMIFS(Movimientos!$B$6:$B$505,Movimientos!$D$6:$D$505,A32,Movimientos!$E$6:$E$505,TRUE) -> 0 | D32: =IFERROR(__xludf.DUMMYFUNCTION("IF(OR(B32="""",A32>TODAY(),E32=""Histórico mensual"",E32=""Base diaria""),"""",IFERROR(LET(prevDate,MAX(FILTER($A$2:A31,$B$2:B31<>"""",$A$2:A31<A32)),prevValue,XLOOKUP(prevDate,$A$2:A31,$B$2:B31),gap,A32-prevDate,unknown,COUNTIFS(Movimientos!$D$6:$D$505,"&""">""&prevDate,Movimientos!$D$6:$D$505,""<=""&A32,Movimientos!$E$6:$E$505,FALSE,Movimientos!$C$6:$C$505,""<>Fecha inferida*""),flow,SUMIFS(Movimientos!$B$6:$B$505,Movimientos!$D$6:$D$505,"">""&prevDate,Movimientos!$D$6:$D$505,""<=""&A32,Movimientos!$E$6:$"&"E$505,TRUE)+SUMIFS(Movimientos!$B$6:$B$505,Movimientos!$D$6:$D$505,"">""&prevDate,Movimientos!$D$6:$D$505,""<=""&A32,Movimientos!$C$6:$C$505,""Fecha inferida*""),net,B32-flow,IF(OR(gap<1,unknown>0,prevValue<=0,net<=0),"""",(POWER(net/prevValue,1/gap)-1)*1"&"00)),""""))"),"") | E32: =IF(B32="","",IF(OR(A32=DATE(2026,1,30),A32=DATE(2026,2,27),A32=DATE(2026,3,31),A32=DATE(2026,4,30),A32=DATE(2026,5,29),A32=DATE(2026,6,30)),"Histórico mensual",IF(A32=DATE(2026,7,9),"Base diaria",IF(WEEKDAY(A32,2)>5,"Fin de semana","Diario"))))
A33: 46054 | B33: =IF(Diario!B37="","",Diario!B37) | C33: =SUMIFS(Movimientos!$B$6:$B$505,Movimientos!$D$6:$D$505,A33,Movimientos!$E$6:$E$505,TRUE) -> 0 | D33: =IFERROR(__xludf.DUMMYFUNCTION("IF(OR(B33="""",A33>TODAY(),E33=""Histórico mensual"",E33=""Base diaria""),"""",IFERROR(LET(prevDate,MAX(FILTER($A$2:A32,$B$2:B32<>"""",$A$2:A32<A33)),prevValue,XLOOKUP(prevDate,$A$2:A32,$B$2:B32),gap,A33-prevDate,unknown,COUNTIFS(Movimientos!$D$6:$D$505,"&""">""&prevDate,Movimientos!$D$6:$D$505,""<=""&A33,Movimientos!$E$6:$E$505,FALSE,Movimientos!$C$6:$C$505,""<>Fecha inferida*""),flow,SUMIFS(Movimientos!$B$6:$B$505,Movimientos!$D$6:$D$505,"">""&prevDate,Movimientos!$D$6:$D$505,""<=""&A33,Movimientos!$E$6:$"&"E$505,TRUE)+SUMIFS(Movimientos!$B$6:$B$505,Movimientos!$D$6:$D$505,"">""&prevDate,Movimientos!$D$6:$D$505,""<=""&A33,Movimientos!$C$6:$C$505,""Fecha inferida*""),net,B33-flow,IF(OR(gap<1,unknown>0,prevValue<=0,net<=0),"""",(POWER(net/prevValue,1/gap)-1)*1"&"00)),""""))"),"") | E33: =IF(B33="","",IF(OR(A33=DATE(2026,1,30),A33=DATE(2026,2,27),A33=DATE(2026,3,31),A33=DATE(2026,4,30),A33=DATE(2026,5,29),A33=DATE(2026,6,30)),"Histórico mensual",IF(A33=DATE(2026,7,9),"Base diaria",IF(WEEKDAY(A33,2)>5,"Fin de semana","Diario"))))
A34: 46055 | B34: =IF(Diario!B38="","",Diario!B38) | C34: =SUMIFS(Movimientos!$B$6:$B$505,Movimientos!$D$6:$D$505,A34,Movimientos!$E$6:$E$505,TRUE) -> 0 | D34: =IFERROR(__xludf.DUMMYFUNCTION("IF(OR(B34="""",A34>TODAY(),E34=""Histórico mensual"",E34=""Base diaria""),"""",IFERROR(LET(prevDate,MAX(FILTER($A$2:A33,$B$2:B33<>"""",$A$2:A33<A34)),prevValue,XLOOKUP(prevDate,$A$2:A33,$B$2:B33),gap,A34-prevDate,unknown,COUNTIFS(Movimientos!$D$6:$D$505,"&""">""&prevDate,Movimientos!$D$6:$D$505,""<=""&A34,Movimientos!$E$6:$E$505,FALSE,Movimientos!$C$6:$C$505,""<>Fecha inferida*""),flow,SUMIFS(Movimientos!$B$6:$B$505,Movimientos!$D$6:$D$505,"">""&prevDate,Movimientos!$D$6:$D$505,""<=""&A34,Movimientos!$E$6:$"&"E$505,TRUE)+SUMIFS(Movimientos!$B$6:$B$505,Movimientos!$D$6:$D$505,"">""&prevDate,Movimientos!$D$6:$D$505,""<=""&A34,Movimientos!$C$6:$C$505,""Fecha inferida*""),net,B34-flow,IF(OR(gap<1,unknown>0,prevValue<=0,net<=0),"""",(POWER(net/prevValue,1/gap)-1)*1"&"00)),""""))"),"") | E34: =IF(B34="","",IF(OR(A34=DATE(2026,1,30),A34=DATE(2026,2,27),A34=DATE(2026,3,31),A34=DATE(2026,4,30),A34=DATE(2026,5,29),A34=DATE(2026,6,30)),"Histórico mensual",IF(A34=DATE(2026,7,9),"Base diaria",IF(WEEKDAY(A34,2)>5,"Fin de semana","Diario"))))
A35: 46056 | B35: =IF(Diario!B39="","",Diario!B39) | C35: =SUMIFS(Movimientos!$B$6:$B$505,Movimientos!$D$6:$D$505,A35,Movimientos!$E$6:$E$505,TRUE) -> 0 | D35: =IFERROR(__xludf.DUMMYFUNCTION("IF(OR(B35="""",A35>TODAY(),E35=""Histórico mensual"",E35=""Base diaria""),"""",IFERROR(LET(prevDate,MAX(FILTER($A$2:A34,$B$2:B34<>"""",$A$2:A34<A35)),prevValue,XLOOKUP(prevDate,$A$2:A34,$B$2:B34),gap,A35-prevDate,unknown,COUNTIFS(Movimientos!$D$6:$D$505,"&""">""&prevDate,Movimientos!$D$6:$D$505,""<=""&A35,Movimientos!$E$6:$E$505,FALSE,Movimientos!$C$6:$C$505,""<>Fecha inferida*""),flow,SUMIFS(Movimientos!$B$6:$B$505,Movimientos!$D$6:$D$505,"">""&prevDate,Movimientos!$D$6:$D$505,""<=""&A35,Movimientos!$E$6:$"&"E$505,TRUE)+SUMIFS(Movimientos!$B$6:$B$505,Movimientos!$D$6:$D$505,"">""&prevDate,Movimientos!$D$6:$D$505,""<=""&A35,Movimientos!$C$6:$C$505,""Fecha inferida*""),net,B35-flow,IF(OR(gap<1,unknown>0,prevValue<=0,net<=0),"""",(POWER(net/prevValue,1/gap)-1)*1"&"00)),""""))"),"") | E35: =IF(B35="","",IF(OR(A35=DATE(2026,1,30),A35=DATE(2026,2,27),A35=DATE(2026,3,31),A35=DATE(2026,4,30),A35=DATE(2026,5,29),A35=DATE(2026,6,30)),"Histórico mensual",IF(A35=DATE(2026,7,9),"Base diaria",IF(WEEKDAY(A35,2)>5,"Fin de semana","Diario"))))
A36: 46057 | B36: =IF(Diario!B40="","",Diario!B40) | C36: =SUMIFS(Movimientos!$B$6:$B$505,Movimientos!$D$6:$D$505,A36,Movimientos!$E$6:$E$505,TRUE) -> 0 | D36: =IFERROR(__xludf.DUMMYFUNCTION("IF(OR(B36="""",A36>TODAY(),E36=""Histórico mensual"",E36=""Base diaria""),"""",IFERROR(LET(prevDate,MAX(FILTER($A$2:A35,$B$2:B35<>"""",$A$2:A35<A36)),prevValue,XLOOKUP(prevDate,$A$2:A35,$B$2:B35),gap,A36-prevDate,unknown,COUNTIFS(Movimientos!$D$6:$D$505,"&""">""&prevDate,Movimientos!$D$6:$D$505,""<=""&A36,Movimientos!$E$6:$E$505,FALSE,Movimientos!$C$6:$C$505,""<>Fecha inferida*""),flow,SUMIFS(Movimientos!$B$6:$B$505,Movimientos!$D$6:$D$505,"">""&prevDate,Movimientos!$D$6:$D$505,""<=""&A36,Movimientos!$E$6:$"&"E$505,TRUE)+SUMIFS(Movimientos!$B$6:$B$505,Movimientos!$D$6:$D$505,"">""&prevDate,Movimientos!$D$6:$D$505,""<=""&A36,Movimientos!$C$6:$C$505,""Fecha inferida*""),net,B36-flow,IF(OR(gap<1,unknown>0,prevValue<=0,net<=0),"""",(POWER(net/prevValue,1/gap)-1)*1"&"00)),""""))"),"") | E36: =IF(B36="","",IF(OR(A36=DATE(2026,1,30),A36=DATE(2026,2,27),A36=DATE(2026,3,31),A36=DATE(2026,4,30),A36=DATE(2026,5,29),A36=DATE(2026,6,30)),"Histórico mensual",IF(A36=DATE(2026,7,9),"Base diaria",IF(WEEKDAY(A36,2)>5,"Fin de semana","Diario"))))
A37: 46058 | B37: =IF(Diario!B41="","",Diario!B41) | C37: =SUMIFS(Movimientos!$B$6:$B$505,Movimientos!$D$6:$D$505,A37,Movimientos!$E$6:$E$505,TRUE) -> 0 | D37: =IFERROR(__xludf.DUMMYFUNCTION("IF(OR(B37="""",A37>TODAY(),E37=""Histórico mensual"",E37=""Base diaria""),"""",IFERROR(LET(prevDate,MAX(FILTER($A$2:A36,$B$2:B36<>"""",$A$2:A36<A37)),prevValue,XLOOKUP(prevDate,$A$2:A36,$B$2:B36),gap,A37-prevDate,unknown,COUNTIFS(Movimientos!$D$6:$D$505,"&""">""&prevDate,Movimientos!$D$6:$D$505,""<=""&A37,Movimientos!$E$6:$E$505,FALSE,Movimientos!$C$6:$C$505,""<>Fecha inferida*""),flow,SUMIFS(Movimientos!$B$6:$B$505,Movimientos!$D$6:$D$505,"">""&prevDate,Movimientos!$D$6:$D$505,""<=""&A37,Movimientos!$E$6:$"&"E$505,TRUE)+SUMIFS(Movimientos!$B$6:$B$505,Movimientos!$D$6:$D$505,"">""&prevDate,Movimientos!$D$6:$D$505,""<=""&A37,Movimientos!$C$6:$C$505,""Fecha inferida*""),net,B37-flow,IF(OR(gap<1,unknown>0,prevValue<=0,net<=0),"""",(POWER(net/prevValue,1/gap)-1)*1"&"00)),""""))"),"") | E37: =IF(B37="","",IF(OR(A37=DATE(2026,1,30),A37=DATE(2026,2,27),A37=DATE(2026,3,31),A37=DATE(2026,4,30),A37=DATE(2026,5,29),A37=DATE(2026,6,30)),"Histórico mensual",IF(A37=DATE(2026,7,9),"Base diaria",IF(WEEKDAY(A37,2)>5,"Fin de semana","Diario"))))
A38: 46059 | B38: =IF(Diario!B42="","",Diario!B42) | C38: =SUMIFS(Movimientos!$B$6:$B$505,Movimientos!$D$6:$D$505,A38,Movimientos!$E$6:$E$505,TRUE) -> 0 | D38: =IFERROR(__xludf.DUMMYFUNCTION("IF(OR(B38="""",A38>TODAY(),E38=""Histórico mensual"",E38=""Base diaria""),"""",IFERROR(LET(prevDate,MAX(FILTER($A$2:A37,$B$2:B37<>"""",$A$2:A37<A38)),prevValue,XLOOKUP(prevDate,$A$2:A37,$B$2:B37),gap,A38-prevDate,unknown,COUNTIFS(Movimientos!$D$6:$D$505,"&""">""&prevDate,Movimientos!$D$6:$D$505,""<=""&A38,Movimientos!$E$6:$E$505,FALSE,Movimientos!$C$6:$C$505,""<>Fecha inferida*""),flow,SUMIFS(Movimientos!$B$6:$B$505,Movimientos!$D$6:$D$505,"">""&prevDate,Movimientos!$D$6:$D$505,""<=""&A38,Movimientos!$E$6:$"&"E$505,TRUE)+SUMIFS(Movimientos!$B$6:$B$505,Movimientos!$D$6:$D$505,"">""&prevDate,Movimientos!$D$6:$D$505,""<=""&A38,Movimientos!$C$6:$C$505,""Fecha inferida*""),net,B38-flow,IF(OR(gap<1,unknown>0,prevValue<=0,net<=0),"""",(POWER(net/prevValue,1/gap)-1)*1"&"00)),""""))"),"") | E38: =IF(B38="","",IF(OR(A38=DATE(2026,1,30),A38=DATE(2026,2,27),A38=DATE(2026,3,31),A38=DATE(2026,4,30),A38=DATE(2026,5,29),A38=DATE(2026,6,30)),"Histórico mensual",IF(A38=DATE(2026,7,9),"Base diaria",IF(WEEKDAY(A38,2)>5,"Fin de semana","Diario"))))
A39: 46060 | B39: =IF(Diario!B43="","",Diario!B43) | C39: =SUMIFS(Movimientos!$B$6:$B$505,Movimientos!$D$6:$D$505,A39,Movimientos!$E$6:$E$505,TRUE) -> 0 | D39: =IFERROR(__xludf.DUMMYFUNCTION("IF(OR(B39="""",A39>TODAY(),E39=""Histórico mensual"",E39=""Base diaria""),"""",IFERROR(LET(prevDate,MAX(FILTER($A$2:A38,$B$2:B38<>"""",$A$2:A38<A39)),prevValue,XLOOKUP(prevDate,$A$2:A38,$B$2:B38),gap,A39-prevDate,unknown,COUNTIFS(Movimientos!$D$6:$D$505,"&""">""&prevDate,Movimientos!$D$6:$D$505,""<=""&A39,Movimientos!$E$6:$E$505,FALSE,Movimientos!$C$6:$C$505,""<>Fecha inferida*""),flow,SUMIFS(Movimientos!$B$6:$B$505,Movimientos!$D$6:$D$505,"">""&prevDate,Movimientos!$D$6:$D$505,""<=""&A39,Movimientos!$E$6:$"&"E$505,TRUE)+SUMIFS(Movimientos!$B$6:$B$505,Movimientos!$D$6:$D$505,"">""&prevDate,Movimientos!$D$6:$D$505,""<=""&A39,Movimientos!$C$6:$C$505,""Fecha inferida*""),net,B39-flow,IF(OR(gap<1,unknown>0,prevValue<=0,net<=0),"""",(POWER(net/prevValue,1/gap)-1)*1"&"00)),""""))"),"") | E39: =IF(B39="","",IF(OR(A39=DATE(2026,1,30),A39=DATE(2026,2,27),A39=DATE(2026,3,31),A39=DATE(2026,4,30),A39=DATE(2026,5,29),A39=DATE(2026,6,30)),"Histórico mensual",IF(A39=DATE(2026,7,9),"Base diaria",IF(WEEKDAY(A39,2)>5,"Fin de semana","Diario"))))
A40: 46061 | B40: =IF(Diario!B44="","",Diario!B44) | C40: =SUMIFS(Movimientos!$B$6:$B$505,Movimientos!$D$6:$D$505,A40,Movimientos!$E$6:$E$505,TRUE) -> 0 | D40: =IFERROR(__xludf.DUMMYFUNCTION("IF(OR(B40="""",A40>TODAY(),E40=""Histórico mensual"",E40=""Base diaria""),"""",IFERROR(LET(prevDate,MAX(FILTER($A$2:A39,$B$2:B39<>"""",$A$2:A39<A40)),prevValue,XLOOKUP(prevDate,$A$2:A39,$B$2:B39),gap,A40-prevDate,unknown,COUNTIFS(Movimientos!$D$6:$D$505,"&""">""&prevDate,Movimientos!$D$6:$D$505,""<=""&A40,Movimientos!$E$6:$E$505,FALSE,Movimientos!$C$6:$C$505,""<>Fecha inferida*""),flow,SUMIFS(Movimientos!$B$6:$B$505,Movimientos!$D$6:$D$505,"">""&prevDate,Movimientos!$D$6:$D$505,""<=""&A40,Movimientos!$E$6:$"&"E$505,TRUE)+SUMIFS(Movimientos!$B$6:$B$505,Movimientos!$D$6:$D$505,"">""&prevDate,Movimientos!$D$6:$D$505,""<=""&A40,Movimientos!$C$6:$C$505,""Fecha inferida*""),net,B40-flow,IF(OR(gap<1,unknown>0,prevValue<=0,net<=0),"""",(POWER(net/prevValue,1/gap)-1)*1"&"00)),""""))"),"") | E40: =IF(B40="","",IF(OR(A40=DATE(2026,1,30),A40=DATE(2026,2,27),A40=DATE(2026,3,31),A40=DATE(2026,4,30),A40=DATE(2026,5,29),A40=DATE(2026,6,30)),"Histórico mensual",IF(A40=DATE(2026,7,9),"Base diaria",IF(WEEKDAY(A40,2)>5,"Fin de semana","Diario"))))
